Workbook

Sheet Cover
B12: Effective from 15th June 2026
B14: Contact Details
B15: General | C15: Info@alpinetradeblinds.com
B16: Orders | C16: Sales@alpinetradeblinds.com
B17: Issues | C17: Issues@alpinetradeblinds.com
B18: Spares | C18: Spares@alpinetradeblinds.com
B19: Online Portal | C19: Blindata Online
B20: Phone | C20: 0161 4 500 500
B21: Mobile/wattsapp | C21: 07933150545
B23: Credit Team | C23: accounts@alpinetradeblinds.com
B24: Mobile - whatsapp | D24: 077461709664
B26: Office Opening Hours
B27: Monday - Friday 9am - 4.30pm
B30: Orders below £400 ex vat will incur £20 delivery charge

Sheet Terms & Conditions
B2: ALPINE TRADE BLINDS LIMITED – TERMS & CONDITIONS
B4: 1. ACCEPTANCE OF TERMS
B5: • By placing an order, requesting a quotation, purchasing goods, making payment, opening a trade account, accessing pricing information, accepting delivery, or using any products or services supplied by Alpine Trade Blinds Limited, the customer confirms that they have read, understood, and accepted these Terms & Conditions in full.
B6: • These Terms & Conditions apply to all quotations, orders, sales, deliveries, products, services, installations, repairs, warranties, and any other dealings between Alpine Trade Blinds Limited and the customer unless otherwise agreed in writing by a Director of Alpine Trade Blinds Limited.
B7: • No variation to these Terms & Conditions shall be binding unless confirmed in writing by Alpine Trade Blinds Limited.
B9: 2. TRADE ONLY
B10: All prices, quotations, products, and services are supplied strictly to trade customers unless otherwise agreed in writing.
B12: 3. GENERAL
B13: All orders placed with Alpine Trade Blinds Limited are subject to these Terms & Conditions.
B14: The customer's submission of an order, acceptance of a quotation, payment of an invoice, acceptance of delivery, or use of any products or services supplied by Alpine Trade Blinds Limited shall constitute full acceptance of these Terms & Conditions.
B15: Where a customer provides a purchase order or their own terms and conditions, Alpine Trade Blinds Limited's Terms & Conditions shall prevail unless otherwise agreed in writing.
B17: 4. PRICING
... B155: OL1 3NL

Sheet Master Control
B2: Company Name | C2: Start Date
B3: Shades and Space | C3: 15.06.2026
I4: Max Width | J4: Max width
B5: Master Control | E5: Fabric Search | F5: Design | G5: Band | H5: Type | I5: mm | J5: inches | K5: Supplier | L5: Book | M5: Comments
B6: Discount is for Blind only and not any extras | E6: type here | F6: {=_xlfn._xlws.FILTER('Fabric Library'!B3:I891,IFERROR(ISNUMBER(SEARCH($E$6,'Fabric Library'!B3:B891)),FALSE),"NO RESULTS")} -> NO RESULTS
B7: Product | C7: Discount
B8: 127mm Vertical | C8: 0
B9: 25mm Aluminium | C9: 0.25
B10: 3BS Pleated | C10: 0.25
B11: 89mm Vertical | C11: 0.35
B12: Allusion | C12: 0.2
B13: Aquawood Fauxwood | C13: 0.25
B14: Essence Fauxwood | C14: 0.25
B15: Expressions Fauxwood | C15: 0.25
B16: Freehang Pleated | C16: 0.25
B17: Nightshade | C17: 0.2
B18: Perfect Fit Aluminium | C18: 0.25
B19: Perfect Fit Pleated | C19: 0.25
... B36: Fit to Frame Pleated | C36: 0

Sheet Fabric Library
B2: Design | C2: Band | D2: Type | E2: Max width - mm | F2: Max width - inches | G2: Supplier | H2: Book | I2: Comments
B3: Acacia | C3: C | D3: Roller | E3: 2000 | F3: =MROUND(E3/25.4,1/8) -> 78.75 | G3: Louvolite
B4: Ada | C4: A | D4: 89mm | E4: 89 | F4: =MROUND(E4/25.4,1/8) -> 3.5 | G4: Arena
B5: Ada | C5: B | D5: Roller | E5: 2000 | F5: =MROUND(E5/25.4,1/8) -> 78.75 | G5: Arena
B6: Ada | C6: B | D6: 89mm | E6: 89 | F6: =MROUND(E6/25.4,1/8) -> 3.5 | G6: Eclipse | H6: Market Collection
B7: Ada | C7: B | D7: Roller | E7: 2000 | F7: =MROUND(E7/25.4,1/8) -> 78.75 | G7: Eclipse | H7: Market Collection
B8: Aki (Not Available) | C8: F | D8: Roller | E8: 2800 | F8: =MROUND(E8/25.4,1/8) -> 110.25 | G8: Decora | H8: Fabric Box | I8: Fabric Not available - too many issues
B9: Akita | C9: C | D9: Roller | E9: 2000 | F9: =MROUND(E9/25.4,1/8) -> 78.75 | G9: Decora | H9: Fabric Box
B10: Akita Blackout | C10: D | D10: Roller | E10: 2000 | F10: =MROUND(E10/25.4,1/8) -> 78.75 | G10: Decora | H10: Fabric Box
B11: Alara | C11: E | D11: Roller | E11: 2400 | F11: =MROUND(E11/25.4,1/8) -> 94.5 | G11: Decora | H11: Fabric Box
B12: Alara | C12: E | D12: 89mm | E12: 89 | F12: =MROUND(E12/25.4,1/8) -> 3.5 | G12: Decora | H12: Fabric Box
B13: Albero | C13: D | D13: Vision | E13: 2800 | F13: =MROUND(E13/25.4,1/8) -> 110.25 | G13: Louvolite
B14: Alessi | C14: B | D14: Roller | E14: 2000 | F14: =MROUND(E14/25.4,1/8) -> 78.75 | G14: Decora | H14: Fabric Box | I14: Discontinued
B15: Alessi | C15: B | D15: 89mm | E15: 89 | F15: =MROUND(E15/25.4,1/8) -> 3.5 | G15: Decora | H15: Fabric Box | I15: Discontinued
B16: Algarve | C16: E | D16: Roller | E16: 2000 | F16: =MROUND(E16/25.4,1/8) -> 78.75 | G16: Eclipse
B17: Allegria | C17: C | D17: Vision | E17: 2800 | F17: =MROUND(E17/25.4,1/8) -> 110.25 | G17: Louvolite
B18: Allure | C18: D | D18: Vision | E18: 2800 | F18: =MROUND(E18/25.4,1/8) -> 110.25 | G18: Eclipse | H18: Mirage
B19: Alta | C19: C | D19: Roller | E19: 2000 | F19: =MROUND(E19/25.4,1/8) -> 78.75 | G19: Arena
B20: Alta | C20: C | D20: Roller | E20: 2000 | F20: =MROUND(E20/25.4,1/8) -> 78.75 | G20: Eclipse
B21: Alta Blackout | C21: E | D21: Roller | E21: 2000 | F21: =MROUND(E21/25.4,1/8) -> 78.75 | G21: Eclipse
B22: Alta Blackout | C22: E | D22: Roller | E22: 2000 | F22: =MROUND(E22/25.4,1/8) -> 78.75 | G22: Arena
B23: Altea | C23: C | D23: Roller | E23: 2000 | F23: =MROUND(E23/25.4,1/8) -> 78.75 | G23: Decora | H23: Fabric Box
B24: Altea | C24: D | D24: 89mm | E24: 89 | F24: =MROUND(E24/25.4,1/8) -> 3.5 | G24: Decora | H24: Fabric Box
B25: Alvor | C25: D | D25: Roller | E25: 2000 | F25: =MROUND(E25/25.4,1/8) -> 78.75 | G25: Decora | H25: Fabric Box
B26: Alvor | C26: E | D26: 89mm | E26: 89 | F26: =MROUND(E26/25.4,1/8) -> 3.5 | G26: Decora | H26: Fabric Box
B27: Amaris | C27: AA | D27: Roller | E27: 2000 | F27: =MROUND(E27/25.4,1/8) -> 78.75 | G27: Decora | H27: Excel
B28: Amaris | C28: AA | D28: 89mm | E28: 89 | F28: =MROUND(E28/25.4,1/8) -> 3.5 | G28: Decora | H28: Excel
B29: Amberley | C29: AA | D29: 89mm | E29: 89 | F29: =MROUND(E29/25.4,1/8) -> 3.5 | G29: Alutrade
B30: Amico | C30: C | D30: Roller | E30: 2400 | F30: =MROUND(E30/25.4,1/8) -> 94.5 | G30: Decora | H30: Fabric Box
B31: Argent N/A | C31: F | D31: 89mm | E31: 89 | F31: =MROUND(E31/25.4,1/8) -> 3.5 | G31: Louvolite | I31: Not Available
B32: Argent N/A | C32: E | D32: Roller | E32: 2000 | F32: =MROUND(E32/25.4,1/8) -> 78.75 | G32: Louvolite | I32: Not Available
B33: Argento | C33: NA | D33: Vision | E33: NA | F33: NA | G33: Louvolite | I33: Discontinued
B34: Aria | C34: B | D34: 89mm | E34: 89 | F34: =MROUND(E34/25.4,1/8) -> 3.5 | G34: Decora | H34: Fabric Box
B35: Ariana | C35: A | D35: 89mm | E35: 89 | F35: =MROUND(E35/25.4,1/8) -> 3.5 | G35: Eclipse | H35: Market Collection
B36: Ariana | C36: A | D36: Roller | E36: 2000 | F36: =MROUND(E36/25.4,1/8) -> 78.75 | G36: Eclipse | H36: Market Collection
B37: Ariel | C37: B | D37: 89mm | E37: 89 | F37: =MROUND(E37/25.4,1/8) -> 3.5 | G37: Alutrade
B38: Ariel | C38: B | D38: Roller | E38: 1830 | F38: =MROUND(E38/25.4,1/8) -> 72 | G38: Alutrade
B39: Arona | C39: C | D39: Roller | E39: 2400 | F39: =MROUND(E39/25.4,1/8) -> 94.5 | G39: Decora | H39: Fabric Box
B40: Arona | C40: C | D40: 89mm | E40: 89 | F40: =MROUND(E40/25.4,1/8) -> 3.5 | G40: Decora | H40: Fabric Box
B41: Arrezzo | C41: B | D41: Vision | E41: 2800 | F41: =MROUND(E41/25.4,1/8) -> 110.25 | G41: Louvolite
B42: Artisan | C42: E | D42: Roller | E42: 2000 | F42: =MROUND(E42/25.4,1/8) -> 78.75 | G42: Arena
B43: Arundel | C43: B | D43: Roller | E43: 2000 | F43: =MROUND(E43/25.4,1/8) -> 78.75 | G43: Eclipse | H43: Market Collection
B44: Aspen | C44: C | D44: 89mm | E44: 89 | F44: =MROUND(E44/25.4,1/8) -> 3.5 | G44: Arena
B45: Aspen | C45: D | D45: Roller | E45: 2000 | F45: =MROUND(E45/25.4,1/8) -> 78.75 | G45: Arena
B46: Aspen | C46: C | D46: 89mm | E46: 89 | F46: =MROUND(E46/25.4,1/8) -> 3.5 | G46: Eclipse
B47: Aspen | C47: D | D47: Roller | E47: 2000 | F47: =MROUND(E47/25.4,1/8) -> 78.75 | G47: Eclipse
B48: Astratto | C48: A | D48: 89mm | E48: 89 | F48: =MROUND(E48/25.4,1/8) -> 3.5 | G48: Arena
B49: Astratto | C49: A | D49: 89mm | E49: 89 | F49: =MROUND(E49/25.4,1/8) -> 3.5 | G49: Eclipse
B50: Astratto | C50: A | D50: 89mm | E50: 89 | F50: =MROUND(E50/25.4,1/8) -> 3.5 | G50: Eclipse | H50: Market Collection
B51: Astratto | C51: A | D51: Roller | E51: 2000 | F51: =MROUND(E51/25.4,1/8) -> 78.75 | G51: Eclipse | H51: Market Collection
B52: Athena | C52: D | D52: Roller | E52: 2000 | F52: =MROUND(E52/25.4,1/8) -> 78.75 | G52: Arena
B53: Atlantex | C53: B | D53: 89mm | E53: 89 | F53: =MROUND(E53/25.4,1/8) -> 3.5 | G53: Arena
B54: Atlantex | C54: B | D54: Roller | E54: 2000 | F54: =MROUND(E54/25.4,1/8) -> 78.75 | G54: Arena
B55: Atlantex | C55: B | D55: 89mm | E55: 89 | F55: =MROUND(E55/25.4,1/8) -> 3.5 | G55: Eclipse
B56: Atlantex | C56: B | D56: Roller | E56: 2000 | F56: =MROUND(E56/25.4,1/8) -> 78.75 | G56: Eclipse
B57: Atlantex Asc | C57: C | D57: Roller | E57: 2000 | F57: =MROUND(E57/25.4,1/8) -> 78.75 | G57: Arena
B58: Atlantex Asc | C58: B | D58: 89mm | E58: 89 | F58: =MROUND(E58/25.4,1/8) -> 3.5 | G58: Eclipse
B59: Atlantex Asc | C59: C | D59: Roller | E59: 2000 | F59: =MROUND(E59/25.4,1/8) -> 78.75 | G59: Eclipse
B60: Atlas | C60: A | D60: 89mm | E60: 89 | F60: =MROUND(E60/25.4,1/8) -> 3.5 | G60: Alutrade
B61: Atlas | C61: A | D61: Roller | E61: 1830-2500*-3000* | F61: 72 - 98.1/2 - 118.1/8 | G61: Alutrade | I61: 2500-3000 ONLY IN SELECTED COLOURS
B62: Aura | C62: E | D62: Vision | E62: 2700 | F62: =MROUND(E62/25.4,1/8) -> 106.25 | G62: Eclipse | H62: Mirage
B63: Autumn | C63: C | D63: Roller | E63: 2000 | F63: =MROUND(E63/25.4,1/8) -> 78.75 | G63: Arena
B64: Autumn | C64: E | D64: Roller | E64: 2000 | F64: =MROUND(E64/25.4,1/8) -> 78.75 | G64: Eclipse
B65: Aveline | C65: C | D65: 89mm | E65: 89 | F65: =MROUND(E65/25.4,1/8) -> 3.5 | G65: Eclipse
B66: Aveline | C66: D | D66: Roller | E66: 2000 | F66: =MROUND(E66/25.4,1/8) -> 78.75 | G66: Eclipse
B67: Axel | C67: E | D67: Roller | E67: 2000 | F67: =MROUND(E67/25.4,1/8) -> 78.75 | G67: Eclipse
B68: Azalea Blackout | C68: C | D68: Roller | E68: 2000 | F68: =MROUND(E68/25.4,1/8) -> 78.75 | G68: Louvolite
B69: Bahama | C69: C | D69: Roller | E69: 2100 | F69: =MROUND(E69/25.4,1/8) -> 82.625 | G69: Louvolite
B70: Balance | C70: E + 5% | D70: Vision | E70: 2800 | F70: =MROUND(E70/25.4,1/8) -> 110.25 | G70: Eclipse | H70: Mirage
B71: Bamboo | C71: A | D71: 89mm | E71: 89 | F71: =MROUND(E71/25.4,1/8) -> 3.5 | G71: Arena
B72: Bamboo | C72: C | D72: 89mm | E72: 89 | F72: =MROUND(E72/25.4,1/8) -> 3.5 | G72: Louvolite
B73: Bamboo | C73: B | D73: Roller | E73: 2000 | F73: =MROUND(E73/25.4,1/8) -> 78.75 | G73: Louvolite
B74: Bamboo | C74: A | D74: 89mm | E74: 89 | F74: =MROUND(E74/25.4,1/8) -> 3.5 | G74: Eclipse
B75: Bamboo | C75: A | D75: 89mm | E75: 89 | F75: =MROUND(E75/25.4,1/8) -> 3.5 | G75: Eclipse | H75: Market Collection
B76: Bamboo | C76: A | D76: Roller | E76: 2000 | F76: =MROUND(E76/25.4,1/8) -> 78.75 | G76: Eclipse | H76: Market Collection
B77: Bamboo | C77: A | D77: Roller | E77: 2000 | F77: =MROUND(E77/25.4,1/8) -> 78.75 | G77: Eclipse | H77: Market Collection
B78: Bamboo | C78: A | D78: Roller | E78: 2000 | F78: =MROUND(E78/25.4,1/8) -> 78.75 | G78: Arena
B79: Banlight Duo FR | C79: C | D79: 89mm | E79: 89 | F79: =MROUND(E79/25.4,1/8) -> 3.5 | G79: Eclipse
B80: Banlight Duo FR | C80: B | D80: Roller | E80: 2000-2400-3000 | F80: 78.74 - 94.5 - 118 1/8 | G80: Eclipse
B81: Banlight Duo Fr | C81: C | D81: 89mm | E81: 89 | F81: =MROUND(E81/25.4,1/8) -> 3.5 | G81: Arena
B82: Banlight Duo Fr | C82: B | D82: Roller | E82: 2000-2400-3000 | F82: 78.74 - 94.5 - 118 1/8 | G82: Arena
B83: Barclay | C83: B | D83: 89mm | E83: 89 | F83: =IFERROR(ROUND(E83/25.4,2),"") -> 3.5 | G83: Decora | H83: Fabric Box
B84: Barclay | C84: C | D84: Roller | E84: 3000 | F84: =IFERROR(ROUND(E84/25.4,2),"") -> 118.11 | G84: Decora | H84: Fabric Box
B85: Barclay | C85: C | D85: 127mm | E85: 127 | F85: =IFERROR(ROUND(E85/25.4,2),"") -> 5 | G85: Decora | H85: Fabric Box
B86: Beam | C86: D | D86: Vision | E86: 2700 | F86: =MROUND(E86/25.4,1/8) -> 106.25 | G86: Eclipse | H86: Mirage
B87: Bella | C87: B | D87: Roller | E87: 2000-3000* | F87: 78.75 - 118 1/8 | G87: Decora | H87: Fabric Box | I87: 3000-SELECTED COLOURS ONLY
B88: Bella | C88: B | D88: 127mm | E88: 127 | F88: =IFERROR(ROUND(E88/25.4,2),"") -> 5 | G88: Decora | H88: Fabric Box
B89: Bella | C89: D | D89: Vision | E89: 2800 | F89: =MROUND(E89/25.4,1/8) -> 110.25 | G89: Louvolite
B90: Bella | C90: B | D90: 89mm | E90: 89 | F90: =IFERROR(ROUND(E90/25.4,2),"") -> 3.5 | G90: Decora | H90: Fabric Box
B91: Bexley | C91: C | D91: Roller | E91: 2000 | F91: =MROUND(E91/25.4,1/8) -> 78.75 | G91: Decora | H91: Fabric Box
B92: Bexley | C92: C | D92: 89mm | E92: 89 | F92: =MROUND(E92/25.4,1/8) -> 3.5 | G92: Decora | H92: Fabric Box
B93: Birdsong | C93: C | D93: Roller | E93: 2000 | F93: =MROUND(E93/25.4,1/8) -> 78.75 | G93: Louvolite
B94: Blend | C94: A | D94: Roller | E94: 2300 | F94: =MROUND(E94/25.4,1/8) -> 90.5 | G94: Eclipse | H94: Market Collection
B95: Blend Bo | C95: B | D95: Roller | E95: 2300 | F95: =MROUND(E95/25.4,1/8) -> 90.5 | G95: Eclipse | H95: Market Collection
B96: Bliss | C96: B | D96: 89mm | E96: 89 | F96: =MROUND(E96/25.4,1/8) -> 3.5 | G96: Arena
B97: Bliss | C97: B | D97: 89mm | E97: 89 | F97: =MROUND(E97/25.4,1/8) -> 3.5 | G97: Eclipse
B98: Boheme | C98: B | D98: Roller | E98: 1830 | F98: =MROUND(E98/25.4,1/8) -> 72 | G98: Decora | H98: Fabric Box
B99: Boho | C99: C | D99: Roller | E99: 2000 | F99: =MROUND(E99/25.4,1/8) -> 78.75 | G99: Decora | H99: Fabric Box
B100: Boleyn Blackout | C100: C | D100: Roller | E100: 2000 | F100: =MROUND(E100/25.4,1/8) -> 78.75 | G100: Louvolite
B101: Bonsai | C101: D | D101: Roller | E101: 1950 | F101: =MROUND(E101/25.4,1/8) -> 76.75 | G101: Arena
...

Sheet Fabric Box 2025
B1: DECORA 2026
B2: Fabrics that are highlighted in Red are now discontinued
B3: Roller | E3: Roller | H3: EXCEL ROLLER | K3: Vertical | N3: 127MM | O3: Name | P3: Band
B4: Name | C4: Band | E4: Name | F4: Band | H4: Fabric | I4: Band | K4: Name | L4: Band | N4: Decora | O4: Barclay | P4: C
B5: Aki (Not available) | C5: F | E5: Mezza | F5: D | H5: Amaris | I5: AA | K5: Alara | L5: E | N5: Decora | O5: Bella | P5: B
B6: Akita | C6: C | E6: Midas | F6: F | H6: Cleo | I6: AA | K6: Altea | L6: D | N6: Decora | O6: Glimpse | P6: C
B7: Akita Blackout | C7: D | E7: Miro | F7: C | H7: Fiesta | I7: AA | K7: Alessi | L7: B | N7: Decora | O7: Hayden | P7: B
B8: Alara | C8: E | E8: Miro Blackout | F8: D | H8: Java | I8: AA | K8: Alvor | L8: E | N8: Decora | O8: Hayworth | P8: C
B9: Alessi | C9: B | E9: Mood | F9: A | H9: Kira | I9: AA | K9: Aria | L9: B | N9: Decora | O9: Rocha | P9: D
B10: Altea | C10: C | E10: Moxie | F10: C | H10: Malimo | I10: AA | K10: Arona | L10: C | N10: Decora | O10: Soma | P10: D
B11: Alvor | C11: D | E11: Musa | F11: B | H11: Monarch | I11: AA | K11: Barclay | L11: B | N11: Decora | O11: Splash | P11: A
B12: Amico | C12: C | E12: Myth | F12: C | H12: Opus | I12: AA | K12: Bella 89 OR 127 | L12: B | N12: Decora | O12: Unicolour | P12: B
B13: Arona | C13: C | E13: Napa | F13: C | H13: Verona | I13: AA | K13: Bexley | L13: C | N13: Decora | O13: Uniline | P13: A
B14: Barclay | C14: C | E14: Odin | F14: D | H14: Zara | I14: AA | K14: Como | L14: A | N14: Decora | O14: Unishade | P14: C
B15: Bella | C15: B | E15: Orissa | F15: C | K15: Devon | L15: C
B16: Bexley | C16: C | E16: Plaza | F16: B | K16: Diva | L16: B | N16: Softshade - Vision
B17: Boheme | C17: B | E17: Puriti | F17: C | H17: EXCEL 89mm | K17: Ennis | L17: C | N17: Fabric | O17: Band | P17: Max Width
B18: Boho | C18: C | E18: Renzo | F18: C | H18: Fabric | I18: Band | K18: Estella | L18: D | N18: Luna | O18: A | P18: 3000
B19: Botany | C19: C | E19: Rocha | F19: E | H19: Amaris | I19: AA | K19: Fleur | L19: B | N19: Nobis | O19: D | P19: 2600
B20: Calista | C20: D | E20: Sabina | F20: E | H20: Cameo | I20: AA | K20: Glimpse | L20: C | N20: Kanza | O20: D | P20: 3000
B21: Como | C21: A | E21: Sahara | F21: B | H21: Carlo | I21: AA | K21: Hayden | L21: B | N21: Rift | O21: B | P21: 2800
B22: Devon | C22: C | E22: Samba | F22: B | H22: Cleo | I22: AA | K22: Hayworth | L22: C | N22: Mero | O22: E | P22: 2800
B23: Dino | C23: D | E23: Sasha | F23: B | H23: Dalia | I23: AA | K23: Hanson | L23: E | N23: Rosso | O23: C | P23: 2800
B24: Diva | C24: B | E24: Scope | F24: A | H24: Fiesta | I24: AA | K24: Henlow | L24: C | N24: Tela | O24: E | P24: 2800
B25: Dollie | C25: D | E25: Semana | F25: C | H25: Java | I25: AA | K25: Isla | L25: B | N25: Hoxton | O25: D | P25: 2800
B26: Ducato | C26: E | E26: Sento | F26: D | H26: Kira | I26: AA | K26: Kobe | L26: D
B27: Ella | C27: C | E27: Sephora | F27: D | H27: Fitz | I27: A | K27: Legacy | L27: B
B28: Ella Blackout | C28: D | E28: Sephora Blackout | F28: D | H28: Lana | I28: AA | K28: Luxari | L28: B
B29: Ennis | C29: C | E29: Serena | F29: B | H29: Lucca BO | I29: A | K29: Linden | L29: D
B30: Estella | C30: C | E30: Serra | F30: C | H30: Malimo | I30: AA | K30: Renzo | L30: C
B31: Flock | C31: C | E31: Shima | F31: B | H31: Mia | I31: AA | K31: Medina | L31: B
B32: Focal (Not available) | C32: F | E32: Sio | F32: C | H32: Monarch | I32: AA | K32: Metz | L32: B
B33: Glimpse | C33: D | E33: Sirocco | F33: B | H33: Opus | I33: AA | K33: Mood | L33: B
B34: Halo | C34: A | E34: Sisi | F34: C | H34: Rossini | I34: AA | K34: Myth | L34: C
B35: Hanson | C35: D | E35: Solice | F35: C | H35: Senna | I35: AA | K35: Nera | L35: B
B36: Hayden | C36: C | E36: Soma | F36: D | H36: Zara | I36: AA | K36: Odin | L36: D
B37: Hayworth | C37: D | E37: Sora | F37: C | H37: Verona | I37: AA | K37: Orissa | L37: D
B38: Henlow | C38: C | E38: Sorenza | F38: C | K38: Plaza | L38: B
B39: Honor | C39: C | E39: Splash | F39: A | H39: PVC 89mm | K39: Renzo | L39: C
B40: Isla | C40: B | E40: Splash 3m width | F40: A | K40: Rocha | L40: D
B41: Kashi | C41: C | E41: Staten | F41: B | H41: Fabric | I41: Band | K41: Sahara | L41: B
B42: Kelso | C42: C | E42: Tansy | F42: C | H42: Diva | I42: B | K42: Samba | L42: B
B43: Kelso Blackout | C43: D | E43: Tallulah | F43: B | H43: Isla PVC | I43: B | K43: Scope | L43: AA
B44: Kona | C44: C | E44: Tallulah Blackout | F44: D | H44: Luxari PVC | I44: B | K44: Soma | L44: D
B45: Lacuna | C45: C | E45: Treviso | F45: C | H45: Metz | I45: B | K45: Sirocco | L45: C
B46: Leighton | C46: D | E46: Tropic | F46: C | H46: Plaza BO FR | I46: B | K46: Shima | L46: C
B47: Lennox | C47: D | E47: Unicolour (ANY WIDTH) | F47: B | H47: Sahara | I47: B | K47: Sio | L47: D
B48: Lia | C48: D | E48: Unilux (ANY WIDTH) | F48: B | H48: Samba | I48: B | K48: Sisi | L48: C
B49: Liberte | C49: C | E49: Unishade (ANY WIDTH) | F49: C | H49: Sirocco | I49: B | K49: Splash 89 OR 127 | L49: A
B50: Lissa | C50: C | E50: Uniview 1100 (ANY WIDTH) | F50: E | H50: Staten | I50: B | K50: Staten | L50: B
B51: Logan | C51: E | E51: Uniview 1300 (ANY WIDTH) | F51: E | H51: Unilux | I51: A | K51: Tobin | L51: B
B52: Lola | C52: D | E52: Uniview 3000 (ANY WIDTH) | F52: D | K52: Unilux | L52: A
B53: Lottie | C53: C | E53: Uniview 3100 (ANY WIDTH) | F53: D | K53: Unicolour 89 OR 127 | L53: B
B54: Mallory | C54: C | E54: Uniview 3200 (ANY WIDTH) | F54: D | K54: Unishade 89 OR 127 | L54: C
B55: Marlow | C55: D | E55: Uniview 3000 ECO | F55: E | K55: Uniview 3200 superfine | L55: D
B56: Memento | C56: C | E56: Uniview Zero | F56: E | K56: VivI | L56: E
B57: Memento Blackout | C57: D | E57: Vivi | F57: D
B58: Messina | C58: C | E58: Zafira | F58: C
B59: Metz | C59: B

Sheet Arena 2026
B1: ARENA FABRIC BANDS 2026
B2: Vertical | C2: Band | E2: Roller | F2: Band | H2: Roller | I2: Band
B3: Ada | C3: A | E3: Ada | F3: B | H3: Monte Blackout | I3: E
B4: Aspen | C4: C | E4: Alta | F4: C | H4: Nordic asc | I4: D
B5: Astratto | C5: A | E5: Alta Blackout | F5: E | H5: Oakley | I5: B
B6: Atlantex | C6: B | E6: Artisan | F6: E | H6: Ocean Crmson or Taupe | I6: E
B7: Bamboo | C7: A | E7: Aspen | F7: D | H7: Odessa | I7: B
B8: Banlight Duo Fr | C8: C | E8: Athena | F8: D | H8: Odin | I8: D
B9: Bliss | C9: B | E9: Atlantex | F9: B | H9: Ombre | I9: D
B10: Boston Fr | C10: C | E10: Atlantex asc | F10: C | H10: Paige | I10: B
B11: Bounce | C11: E | E11: Autumn | F11: C | H11: Palette Fr | I11: B
B12: Caspian | C12: A | E12: Bamboo | F12: A | H12: Panama Deco 3% | I12: F+15%
B13: Clarice | C13: E | E13: Banlight Duo FR | F13: B | H13: Paris | I13: D
... B51: Shantung | C51: A | E51: Linenweave | F51: B | H51: Zayn | I51: E
B52: Shona | C52: E | E52: Linenweave Blackout | F52: E
B53: Sian | C53: A | E53: Mabel | F53: E
B54: Sisi | C54: E | E54: Maeve | F54: D
B55: Sprigs | C55: E | E55: Maggie | F55: D
B56: Stella fr | C56: B | E56: Magical | F56: E
B57: Stratford | C57: A | E57: Marea | F57: A
B58: Topaz | C58: B | E58: Mariella | F58: C
B59: Traze | C59: B | E59: Maverick | F59: E
B60: Tree of life | C60: E | E60: Melody | F60: E
B61: Urban FR | C61: C | E61: Molina | F61: C
B62: Vinne | C62: C | E62: Monte | F62: C

Sheet Alutrade
B2: Alutrade Fabric Bands 2026
B3: VERTICAL 89mm | E3: VERTICAL 89mm
B4: NAME | C4: Band | E4: NAME | F4: Band
B5: Amberley | C5: AA | E5: Ariel | F5: B
B6: Ariel | C6: B | E6: Atlas | F6: A
B7: Atlas | C7: A | E7: Callisto | F7: B
B8: Breedon | C8: AA | E8: Classic Blackout | F8: A
B9: Broadwell | C9: AA | E9: Classic Dimout | F9: AA
B10: Callisto | C10: B | E10: Europa | F10: B
B11: Campden | C11: AA | E11: Hydra | F11: B
B12: Chilson | C12: AA | E12: Larissa | F12: B
B13: Classic Blackout | C13: A | E13: Metis | F13: B
B14: Classic Dimout | C14: AA | E14: Rhea | F14: B
B15: Derwent | C15: AA | E15: Signature Blackout | F15: A
... B19: Kineton | C19: AA | E19: Triton | F19: B
B20: Kingham | C20: AA
B21: Larissa | C21: B | E21: Name | F21: 127 Band
B22: Leafield | C22: AA | E22: Broadwell | F22: AA
B23: Metis | C23: B | E23: Kineton | F23: AA
B24: Morten | C24: AA | E24: Somerton | F24: AA
B25: Pebworth | C25: AA | E25: Windrush | F25: A
B26: Rhea | C26: B
B27: Rissington | C27: AA
B28: Saintbury | C28: AA
B29: Signature Blackout | C29: A
B30: Signature Dimout | C30: AA
B31: Signature FR Blackout | C31: B
B32: Signature FR Dimout | C32: A
B33: Somerton | C33: AA
B34: Stretton | C34: AA
B35: Taynton | C35: AA
B36: Triton | C36: B
B37: Windrush | C37: AA

Sheet Louvolite 2026
B1: LOUVOLITE 2026
B2: N/A Fabrics are not available
B3: Vertical | E3: Roller | H3: Roller | K3: VISION | O3: ALLUSION
B4: Name | C4: Band | E4: Name | F4: Band | H4: Name | I4: Band | K4: Design | L4: Width | M4: Band | O4: Design | P4: Band
B5: Argent N/A | C5: F | E5: Acacia | F5: C | H5: Monet (Sheer) | I5: C | K5: Albero | L5: 2800 | M5: D | O5: Horizon | P5: A
B6: Bamboo | C6: C | E6: Argent N/A | F6: E | H6: Montego | I6: D | K6: Allegria | L6: 2800 | M6: C | O6: Natural | P6: B
B7: Bora | C7: A | E7: Azalea Blackout | F7: C | H7: Monterey | I7: E | K7: Arrezzo | L7: 2800 | M7: B | O7: Shadow | P7: C
B8: Carnival | C8: C | E8: Bahama | F8: C | H8: Mosiac Blackout | I8: D | K8: Bella | L8: 2800 | M8: D | O8: Vista | P8: B
B9: Carnival Blackout | C9: D | E9: Bamboo | F9: B | H9: Night Night Blackout | I9: E | K9: Boucle | L9: 2800 | M9: D
B10: Chatsworth | C10: C | E10: Birdsong | F10: C | H10: Night Safari Blackout | I10: E | K10: Capri | L10: 2800 | M10: A
B11: Collina Blackout N/A | C11: F+20% | E11: Boleyn Blackout | F11: C | H11: Nordic | I11: C | K11: Ferrara | L11: 2800 | M11: C
B12: Como | C12: D | E12: Bora | F12: A | H12: Nordic Blackout | I12: D | K12: Firenze | L12: 2800 | M12: B
B13: Como Blackout | C13: E | E13: Brighton Stripe BO | F13: C | H13: Ophelia | I13: D | K13: Floreale | L13: 2800 | M13: D
B14: Cotton Flower | C14: E | E14: Bubbles | F14: C | H14: Orchard Blackout N/A | I14: F | K14: Lusso | L14: 2800 | M14: C
B15: Crush BO N/A | C15: F+20% | E15: Bugs Blackout | F15: D | H15: Oslo | I15: F | K15: Modella | L15: 2800 | M15: B
B16: Dapple SPC+ | C16: D | E16: Carnival | F16: B | H16: Oxford | I16: B | K16: Modina | L16: 2800 | M16: C
B17: Daybreak | C17: B | E17: Carnival Blackout | F17: C | H17: Oxford Blackout | I17: C | K17: Naples | L17: 2800 | M17: B
B18: Didsbury Blackout N/A | C18: D | E18: Chatsworth | F18: C | H18: Paradise Palm Blackout | I18: C | K18: Nola | L18: 2800 | M18: B
B19: Dune | C19: C | E19: Cherry Blossom | F19: D | H19: Perspective 1% | I19: C | K19: Nuvola | L19: 2800 | M19: B
B20: Ex Lite | C20: D | E20: Clearguard | F20: B | H20: Perspective 3% | I20: C | K20: Rimini | L20: 2800 | M20: C
... B23: Haven | C23: C | E23: Como Blackout | F23: D | H23: Perspective Aluview | I23: E | K23: Trento | L23: 2800 | M23: B
B24: Haven Blackout | C24: E | E24: Cotton Flower | F24: C | H24: Perspective Blackout | I24: E
B25: Kona | C25: AA | E25: Crush BO N/A | F25: E | H25: Perspective Pureview | I25: C
B26: Kumano Blackout N/A | C26: F | E26: Dhalia Blackout | F26: C | H26: Petal | I26: C
B27: Marble Blackout | C27: E | E27: Daisy Blackout | F27: C | H27: Petal Blackout | I27: C
B28: Matrix Blackout | C28: E | E28: Damask Blackout | F28: E | H28: Planetarium | I28: E | K28: Supplier | L28: Name | M28: 127 Band
B29: Mistral | C29: A | E29: Dapple SPC+ | F29: C | H29: Pop | I29: A | K29: Louvolite | L29: Carnival | M29: C
B30: Monterey N/A | C30: D | E30: Daybreak | F30: A | H30: Pop Blackout | I30: B | K30: Louvolite | L30: Chatsworth | M30: C
B31: Nordic | C31: C | E31: Didsbury Blackout | F31: D | H31: Reverie Blackout | I31: D | K31: Louvolite | L31: Dapple SPC+ | M31: D
B32: Nordic Blackout N/A | C32: E | E32: Dinosaurs | F32: E | H32: Ribble | I32: A | K32: Louvolite | L32: Daybreak | M32: B
B33: Oslo | C33: D | E33: Draper | F33: C | H33: Ribble Blackout | I33: C | K33: Louvolite | L33: Ex-Lite BO | M33: D
B34: Oxford | C34: C | E34: Dune | F34: C | H34: Ritz | I34: C | K34: Louvolite | L34: Guradian | M34: B
B35: Oxford Blackout | C35: D | E35: Dunham Blackout | F35: D | H35: River | I35: A | K35: Louvolite | L35: Hampton | M35: E
B36: Perspective 1% | C36: C | E36: Ex Lite | F36: C | H36: Romany Blackout | I36: D | K36: Louvolite | L36: Monterey | M36: NA
B37: Perspective 3% | C37: C | E37: Fiji | F37: C | H37: Shot Silk Blackout | I37: F | K37: Louvolite | L37: Oslo | M37: D
B38: Perspective 3% White Back | C38: C | E38: Florence Blackout | F38: C | H38: Sirocco | I38: A | K38: Louvolite | L38: Perspective 1% | M38: D
B39: Perspective 5% | C39: C | E39: Flores | F39: C | H39: Stargazer Blackout | I39: C | K39: Louvolite | L39: Perspective 3% | M39: D
... B48: Ribble | C48: C | E48: Kona | F48: A | H48: Voile White | I48: C | K48: Louvolite | L48: Voile | M48: B
B49: Ribble Dimout | C49: D | E49: Kumano Blackout | F49: E | H49: Wild Garden | I49: C
B50: Ritz | C50: C | E50: Lily | F50: D | H50: Willow BO | I50: E
B51: Romany Blackout | C51: F | E51: Little Friends Blackout | F51: E | H51: Windsor Blackout | I51: D
B52: Savana Dimout | C52: D | E52: Lomond Blackout | F52: C | H52: Zen | I52: B
B53: Shot Silk Blackout N/A | C53: F | E53: Magnolia Blackout | F53: F | H53: Zen Blackout | I53: D
B54: Sirocco | C54: A | E54: Marble Blackout | F54: D | H54: Zephyr | I54: A
B55: Vermont | C55: C | E55: Matrix Blackout | F55: D | H55: Ziggy | I55: C
B56: Voile | C56: B | E56: Mistral | F56: A
B57: Windsor Dimout | C57: D | E57: Monet | F57: C
B58: Zephyr | C58: A

Sheet United
A1: UNITED
B4: VERTICAL | E4: VERTICAL | H4: Roller
B5: Budget
B6: Design | C6: Band | E6: Design | F6: Band | H6: Design | I6: Width | J6: Band
B7: Alabama | C7: AA | E7: Aqualush (discontinued) | F7: B | H7: Alexandria | I7: 2500 | J7: D
B8: Atlantic | C8: AA | E8: Aquamar | F8: B | H8: Aqualush (Discontinued) | I8: 1830 | J8: B
B9: Badar | C9: AA | E9: Cairo | F9: B | H9: Aquamar | I9: 1830 | J9: B
B10: Bond | C10: AA | E10: Elena | F10: B | H10: Aspin | I10: 2400 | J10: E
B11: California | C11: AA | E11: Elm | F11: B | H11: Atlantic | I11: 2000 | J11: A
B12: Cloud | C12: AA | E12: Fabian | F12: A | H12: Berry | I12: 2000 | J12: E
B13: Cross Stich | C13: AA | E13: Fiesta | F13: B | H13: Blossom | I13: 2000 | J13: F
B14: Daisy | C14: AA | E14: Gravity | F14: B | H14: Cairo | I14: 2000 | J14: C
B15: Dolphin | C15: AA | E15: Havana | F15: B | H15: California | I15: 2000 | J15: A
B16: Everest | C16: AA | E16: Jaguar | F16: B | H16: Dolphin | I16: 2000 | J16: A
B17: Feather Weave | C17: AA | E17: Jupiter | F17: B | H17: Elena | I17: 1830 | J17: B
B18: Hambook | C18: AA | E18: kia | F18: C | H18: Elm | I18: 2400 | J18: C
... B31: Swallow | C31: AA | E31: Venus | F31: A | H31: Lahore | I31: 1830 | J31: B
B32: Sweet | C32: AA | H32: Lyon | I32: 2500 | J32: D
B33: Unity | C33: AA | H33: Marina | I33: 2000 | J33: A
H34: Milano | I34: 1830 | J34: B
H35: Oasis | I35: 2600 | J35: D
H36: Opera | I36: 2800 | J36: C
H37: Optimum Standard | I37: 2400 | J37: A
H38: Quin | I38: 2400 | J38: F
H39: Radiance | I39: 2400 | J39: E
H40: Rita | I40: 2500 | J40: D
H41: Sweet Blackout | I41: 2300 | J41: E
H42: Sunrise | I42: 2000 | J42: A
H43: Symphony | I43: 2800 | J43: D
H44: Tango | I44: 1830 | J44: B
H45: Unity | I45: 2000 | J45: AA
... H47: Yacht | I47: 2400 | J47: D

Sheet Eclipse 2026
A1: ECLIPSE 2026
B4: VERTICAL | E4: VERTICAL - MARKET COLLECTION | H4: Roller | K4: Roller | N4: ROLLER - MARKET COLLECTION | R4: MIRAGE
B5: NAME | C5: Band | E5: Design | F5: Band | H5: NAME | I5: Band | K5: NAME | L5: Band | N5: Design | O5: Roller Width | P5: Band | R5: Design | S5: Width | T5: Band
B6: ADA | C6: A | E6: Ariana | F6: A | H6: ADA | I6: B | K6: MAGICAL | L6: E | N6: Ariana | O6: 200cm | P6: A | R6: Allure | S6: 280cm | T6: D
B7: ASPEN | C7: C | E7: Astratto | F7: A | H7: ALGARVE | I7: E | K7: MAREA | L7: A | N7: Astratto | O7: 200cm | P7: A | R7: Aura | S7: 270cm | T7: E
B8: ASTRATTO | C8: A | E8: Bamboo | F8: A | H8: ALTA | I8: C | K8: MARIELLA | L8: C | N8: Bamboo | O8: 200cm | P8: A | R8: Balance | S8: 280cm | T8: E + 5%
B9: ATLANTEX | C9: B | E9: Caspian | F9: A | H9: ALTA B/OUT | I9: E | K9: MIYA | L9: B | N9: Blend | O9: 230cm | P9: A | R9: Beam | S9: 270cm | T9: D
B10: ATLANTEX ASC | C10: B | E10: Castilla | F10: A | H10: ASPEN | I10: D | K10: MOLINA | L10: C | N10: Blend BO | O10: 230cm | P10: B | R10: Crackle | S10: 278cm | T10: D
B11: AVELINE | C11: C | E11: Chevron | F11: A | H11: ATLANTEX | I11: B | K11: MONTE | L11: C | N11: Caspian | O11: 200cm | P11: A | R11: Demure | S11: 270cm | T11: E + 10%
B12: BAMBOO | C12: A | E12: Cypress | F12: A | H12: ATLANTEX ASC | I12: C | K12: MONTE B/OUT | L12: E | N12: Castilla | O12: 200cm | P12: A | R12: Desire | S12: 240cm | T12: C
B13: BANLIGHT DUO | C13: C | E13: Deco | F13: AA | H13: AUTUMN | I13: E | K13: NORDIC ASC | L13: D | N13: Chelsea | O13: 198cm | P13: C | R13: Entwine | S13: 240cm | T13: E +20%
B14: BLISS | C14: B | E14: Evita | F14: A | H14: AVELINE | I14: D | K14: OAKLEY | L14: B | N14: Cypress | O14: 200cm | P14: A | R14: Essence | S14: 280cm | T14: A
B15: BOSTON | C15: D | E15: Jordan | F15: A | H15: AXEL | I15: E | K15: ODESSA | L15: B | N15: Evita | O15: 200cm | P15: A | R15: Illume | S15: 280cm | T15: C
B16: BURST | C16: E | E16: Katrine | F16: A | H16: BAMBOO | I16: A | K16: PALETTE | L16: B | N16: Jordan | O16: 200cm | P16: A | R16: Lustre | S16: 240cm | T16: C
... B24: FLORENCE | C24: A | E24: Sienna | F24: A | H24: CHARM | I24: B | K24: PITCH | L24: E | N24: Origin BO | O24: 200cm | P24: A | R24: Winnow | S24: 280cm | T24: E + 10%
B25: FUSE | C25: C | E25: Surface | F25: AA | H25: CHARM B/OUT | I25: E | K25: POLARIS | L25: A | N25: Polaris | O25: 200cm | P25: B | R25: Note: All Mirage blinds will be made using Louvolite system
B26: GLITZ | C26: C | E26: Vapour | F26: A | H26: CHESTER | I26: E | K26: POLARIS B/OUT | L26: B | N26: Polaris BO | O26: 200cm | P26: C
B27: GRAYSON | C27: A | E27: Wave | F27: AA | H27: CHINDI B/OUT | I27: E | K27: RADIANCE ASC | L27: E | N27: Rannoch | O27: 200cm | P27: B
B28: IMPASTO | C28: E | H28: CORSICA | I28: B | K28: REFLECTION | L28: B | N28: Shannon | O28: 200cm | P28: A
B29: JUDE | C29: A | H29: COURTNEY | I29: C | K29: RIBBONS ASC | L29: D | N29: Sienna | O29: 200cm | P29: A
B30: LAGAN ASC | C30: C | H30: CUBIK | I30: C | K30: RONDA | L30: E | N30: Soho | O30: 198cm | P30: C
B31: LINENWEAVE | C31: B | H31: DREAMY | I31: E | K31: RONNIE | L31: E | N31: Soho BO | O31: 198cm | P31: D
B32: LIVIA ASC | C32: C | H32: ELEGANCE | I32: E | K32: RUMIE | L32: E | N32: Tay | O32: 200cm | P32: B
B33: LOTUS | C33: A | H33: ELEGANCE B/OUT | I33: E | K33: RUPERT | L33: E | N33: Tribeca | O33: 198cm | P33: C
B34: MAREA | C34: A | H34: ELLIOT | I34: E | K34: SHANTUNG | L34: B | N34: Vapour | O34: 200cm | P34: A
B35: MIYA | C35: A | H35: ELSIE | I35: E | K35: SHONA | L35: E
B36: NORDIC ASC | C36: C | H36: EMELINA | I36: E | K36: STELLA | L36: B
B37: OAKLEY | C37: A | H37: EUAN | I37: E | K37: STRATA ASC | L37: D
B38: ODESSA | C38: A | H38: EVITA | I38: A | K38: STRATFORD | L38: A
B39: PALETTE | C39: B | H39: FELIX ASC | I39: E | K39: TENNESSEE | L39: E
B40: PANACHE | C40: C | H40: FLORENCE | I40: A | K40: TESSA B/OUT | L40: E
B41: PANIER ASC | C41: B | H41: FLORENCE B/OUT | I41: D | K41: TOPAZ | L41: C
B42: PARIS | C42: D | H42: FUSCHIA SWINGTIME B/OUT | I42: E | K42: TOPSY | L42: E
B43: PERRIE | C43: A | H43: FUSE | I43: E | K43: URBAN | L43: B
B44: PIPER | C44: C | H44: GLITZ | I44: D | K44: VALIZE | L44: E
B45: POLARIS | C45: A | H45: IMPASTO | I45: E | K45: VAULT | L45: E
B46: POLARIS BLACKOUT | C46: B | H46: JAX | I46: E | K46: VERA | L46: D
... B51: RONDA | C51: D | H51: KENT | I51: F + 10% | K51: ZENITH | L51: E
B52: SHANTUNG | C52: A | H52: KYLEN | I52: C
B53: SHONA | C53: E | H53: LAGAN ASC | I53: D
B54: SIAN | C54: A | H54: LAYLA | I54: D
B55: STELLA | C55: D | H55: LINENWEAVE | I55: B
B56: STRATFORD | C56: A | H56: LINENWEAVE B/OUT | I56: E
B57: TOPAZ | C57: B | H57: LIVIA ASC | I57: C
B58: URBAN | C58: C | H58: MAEVE | I58: D

Sheet Pleated Fabric
B2: Pleated - Cellular Ranges 2026
B3: AP - CELLEX | F3: LINESCH
B4: Range | C4: Width | D4: Band | F4: Range | G4: Width | H4: Band
B5: Daylight | C5: 3000 | D5: A | F5: Ivrea | G5: 2500 | H5: A
B6: Blackout | C6: 3000 | D6: B | F6: Ivrea Blackout | G6: 2500 | H6: B
B7: Waterproof Daylight | C7: 3000 | D7: C
B8: Waterproof Blackout | C8: 3000 | D8: C
B9: Pattern Daylight Deco | C9: 3000 | D9: B
B10: Pattern Daylight Premier | C10: 3000 | D10: B
B11: Pattern Blackout Deco | C11: 3000 | D11: B
B12: Pattern Blackout Premier | C12: 3000 | D12: B

Sheet Vertical
BB1: VERTICAL BLINDS TRADE PRICE LIST 2026 EX VAT - DISCOUNTED PRICE
B2: VERTICAL BLINDS TRADE PRICE LIST 2026 EX VAT - LIST PRICE
AZ4: Discount | BA4: ='Master Control'!C11 -> 0.35
B6: AA | C6: mm | D6: 500 | E6: 600 | F6: 700 | G6: 800 | H6: 900 | I6: 1000 | J6: 1100 | K6: 1200 | L6: 1300 | M6: 1400 | N6: 1500 | O6: 1600 | P6: 1700 | Q6: 1800 | R6: 1900 | S6: 2000 | T6: 2100 | U6: 2200 | V6: 2300 | W6: 2400 | X6: 2500 | Y6: 2600 | Z6: 2700 | AA6: 2800 | AB6: 2900 | AC6: 3000 | AD6: 3100 | AE6: 3200 | AF6: 3300 | AG6: 3400 | AH6: 3500 | AI6: 3600 | AJ6: 3700 | AK6: 3800 | AL6: 3900 | AM6: 4000 | AN6: 4100 | AO6: 4200 | AP6: 4300 | AQ6: 4400 | AR6: 4500 | AS6: 4600 | AT6: 4700 | AU6: 4800 | AV6: 4900 | AW6: 5000 | AZ6: AA | BA6: mm | BB6: 500 | BC6: 600 | BD6: 700 | BE6: 800 | BF6: 900 | BG6: 1000 | BH6: 1100 | BI6: 1200 | BJ6: 1300 | BK6: 1400 | BL6: 1500 | BM6: 1600 | BN6: 1700 | BO6: 1800 | BP6: 1900 | BQ6: 2000 | BR6: 2100 | BS6: 2200 | BT6: 2300 | BU6: 2400 | BV6: 2500 | BW6: 2600 | BX6: 2700 | BY6: 2800 | BZ6: 2900 | CA6: 3000 | CB6: 3100 | CC6: 3200 | CD6: 3300 | CE6: 3400 | CF6: 3500 | CG6: 3600 | CH6: 3700 | CI6: 3800 | CJ6: 3900 | CK6: 4000 | CL6: 4100 | CM6: 4200 | CN6: 4300 | CO6: 4400 | CP6: 4500 | CQ6: 4600 | CR6: 4700 | CS6: 4800 | CT6: 4900 | CU6: 5000
B7: mm | C7: inch | D7: 19 5/8 | E7: 23 5/8 | F7: 27 1/2 | G7: 31 1/2 | H7: 35 3/8 | I7: 39 3/8 | J7: 43 1/4 | K7: 47 1/4 | L7: 51 1/8 | M7: 55 1/8 | N7: 59 | O7: 63 | P7: 66 7/8 | Q7: 70 7/8 | R7: 74 3/4 | S7: 78 3/4 | T7: 82 5/8 | U7: 86 5/8 | V7: 90 1/2 | W7: 94 1/2 | X7: 98 3/8 | Y7: 102 3/8 | Z7: 106 1/4 | AA7: 110 1/4 | AB7: 114 1/8 | AC7: 118 1/8 | AD7: 122 | AE7: 126 | AF7: 129 7/8 | AG7: 133 7/8 | AH7: 137 3/4 | AI7: 141 3/4 | AJ7: 145 5/8 | AK7: 149 5/8 | AL7: 153 1/2 | AM7: 157 1/2 | AN7: 161 3/8 | AO7: 165 3/8 | AP7: 169 1/4 | AQ7: 173 1/4 | AR7: 177 1/8 | AS7: 181 1/8 | AT7: 185 | AU7: 189 | AV7: 192 7/8 | AW7: 196 7/8 | AZ7: mm | BA7: inch | BB7: 19 5/8 | BC7: 23 5/8 | BD7: 27 1/2 | BE7: 31 1/2 | BF7: 35 3/8 | BG7: 39 3/8 | BH7: 43 1/4 | BI7: 47 1/4 | BJ7: 51 1/8 | BK7: 55 1/8 | BL7: 59 | BM7: 63 | BN7: 66 7/8 | BO7: 70 7/8 | BP7: 74 3/4 | BQ7: 78 3/4 | BR7: 82 5/8 | BS7: 86 5/8 | BT7: 90 1/2 | BU7: 94 1/2 | BV7: 98 3/8 | BW7: 102 3/8 | BX7: 106 1/4 | BY7: 110 1/4 | BZ7: 114 1/8 | CA7: 118 1/8 | CB7: 122 | CC7: 126 | CD7: 129 7/8 | CE7: 133 7/8 | CF7: 137 3/4 | CG7: 141 3/4 | CH7: 145 5/8 | CI7: 149 5/8 | CJ7: 153 1/2 | CK7: 157 1/2 | CL7: 161 3/8 | CM7: 165 3/8 | CN7: 169 1/4 | CO7: 173 1/4 | CP7: 177 1/8 | CQ7: 181 1/8 | CR7: 185 | CS7: 189 | CT7: 192 7/8 | CU7: 196 7/8
B8: 600 | C8: 23 5/8 | D8: 15.3375 | E8: 15.3375 | F8: 15.35 | G8: 15.4875 | H8: 15.75 | I8: 16.025 | J8: 17.2625 | K8: 18.5 | L8: 19.825 | M8: 21.2375 | N8: 22.6375 | O8: 23.65 | P8: 24.6625 | Q8: 25.6875 | R8: 26.7 | S8: 27.7125 | T8: 28.5875 | U8: 29.45 | V8: 30.375 | W8: 31.3625 | X8: 32.35 | Y8: 33.7125 | Z8: 35.075 | AA8: 36.25 | AB8: 37.2375 | AC8: 38.225 | AD8: 39.425 | AE8: 40.625 | AF8: 41.7125 | AG8: 42.7 | AH8: 43.675 | AI8: 44.4625 | AJ8: 45.25 | AK8: 46.325 | AL8: 47.6875 | AM8: 49.0375 | AN8: 50.225 | AO8: 51.4125 | AP8: 52.5 | AQ8: 53.4625 | AR8: 54.4375 | AS8: 55.4125 | AT8: 56.3875 | AU8: 57.3625 | AV8: 58.325 | AW8: 59.3 | AZ8: 600 | BA8: 23 5/8 | BB8: =D8*(1-$BA$4) -> 9.969375 | BC8: =E8*(1-$BA$4) -> 9.969375 | BD8: =F8*(1-$BA$4) -> 9.9775 | BE8: =G8*(1-$BA$4) -> 10.066875 | BF8: =H8*(1-$BA$4) -> 10.2375 | BG8: =I8*(1-$BA$4) -> 10.41625 | BH8: =J8*(1-$BA$4) -> 11.220625 | BI8: =K8*(1-$BA$4) -> 12.025 | ... CU8: =AW8*(1-$BA$4) -> 38.545
B9: 700 | C9: 27 1/2 | D9: 15.3375 | E9: 15.3375 | F9: 15.35 | G9: 15.5625 | H9: 16 | I9: 16.425 | J9: 17.7 | K9: 18.975 | L9: 20.3375 | M9: 21.8 | N9: 23.2625 | O9: 24.3125 | P9: 25.3625 | Q9: 26.4125 | R9: 27.4625 | S9: 28.5125 | T9: 29.4 | U9: 30.3 | V9: 31.25 | W9: 32.275 | X9: 33.2875 | Y9: 34.7 | Z9: 36.125 | AA9: 37.3375 | AB9: 38.3625 | AC9: 39.3875 | AD9: 40.6125 | AE9: 41.85 | AF9: 42.975 | AG9: 43.9875 | AH9: 45.0125 | AI9: 45.825 | AJ9: 46.65 | AK9: 47.7625 | AL9: 49.1625 | AM9: 50.575 | AN9: 51.7875 | AO9: 53.0125 | AP9: 54.125 | AQ9: 55.1375 | AR9: 56.1375 | AS9: 57.15 | AT9: 58.15 | AU9: 59.1625 | AV9: 60.1625 | AW9: 61.175 | AZ9: 700 | BA9: 27 1/2 | BB9: =D9*(1-$BA$4) -> 9.969375 | BC9: =E9*(1-$BA$4) -> 9.969375 | BD9: =F9*(1-$BA$4) -> 9.9775 | BE9: =G9*(1-$BA$4) -> 10.115625 | BF9: =H9*(1-$BA$4) -> 10.4 | BG9: =I9*(1-$BA$4) -> 10.67625 | BH9: =J9*(1-$BA$4) -> 11.505 | BI9: =K9*(1-$BA$4) -> 12.33375 | ... CU9: =AW9*(1-$BA$4) -> 39.76375
B10: 800 | C10: 31 1/2 | D10: 15.3375 | E10: 15.3375 | F10: 15.35 | G10: 15.65 | H10: 16.2375 | I10: 16.825 | J10: 18.1375 | K10: 19.45 | L10: 20.8625 | M10: 22.375 | N10: 23.8875 | O10: 24.9625 | P10: 26.05 | Q10: 27.1375 | R10: 28.225 | S10: 29.3125 | T10: 30.225 | U10: 31.1375 | V10: 32.125 | W10: 33.175 | X10: 34.225 | Y10: 35.7 | Z10: 37.1625 | AA10: 38.425 | AB10: 39.4875 | AC10: 40.5375 | AD10: 41.8 | AE10: 43.0625 | AF10: 44.225 | AG10: 45.2875 | AH10: 46.3375 | AI10: 47.1875 | AJ10: 48.0375 | AK10: 49.1875 | AL10: 50.65 | AM10: 52.1 | AN10: 53.35 | AO10: 54.6125 | AP10: 55.7625 | AQ10: 56.8 | AR10: 57.8375 | AS10: 58.875 | AT10: 59.9125 | AU10: 60.9625 | AV10: 62 | AW10: 63.05 | AZ10: 800 | BA10: 31 1/2 | BB10: =D10*(1-$BA$4) -> 9.969375 | BC10: =E10*(1-$BA$4) -> 9.969375 | BD10: =F10*(1-$BA$4) -> 9.9775 | BE10: =G10*(1-$BA$4) -> 10.1725 | BF10: =H10*(1-$BA$4) -> 10.554375 | BG10: =I10*(1-$BA$4) -> 10.93625 | BH10: =J10*(1-$BA$4) -> 11.789375 | BI10: =K10*(1-$BA$4) -> 12.6425 | ... CU10: =AW10*(1-$BA$4) -> 40.9825
B11: 900 | C11: 35 3/8 | D11: 15.3375 | E11: 15.3375 | F11: 15.35 | G11: 15.725 | H11: 16.475 | I11: 17.225 | J11: 18.575 | K11: 19.9125 | L11: 21.375 | M11: 22.9375 | N11: 24.5125 | O11: 25.625 | P11: 26.7375 | Q11: 27.8625 | R11: 28.9875 | S11: 30.1125 | T11: 31.05 | U11: 31.9875 | V11: 33 | W11: 34.0875 | X11: 35.175 | Y11: 36.7 | Z11: 38.225 | AA11: 39.525 | AB11: 40.6125 | AC11: 41.7 | AD11: 43 | AE11: 44.3 | AF11: 45.5 | AG11: 46.5875 | AH11: 47.675 | AI11: 48.55 | AJ11: 49.425 | AK11: 50.6125 | AL11: 52.125 | AM11: 53.6375 | AN11: 54.925 | AO11: 56.2125 | AP11: 57.4 | AQ11: 58.475 | AR11: 59.55 | AS11: 60.6125 | AT11: 61.6875 | AU11: 62.7625 | AV11: 63.8375 | AW11: 64.9125 | AZ11: 900 | BA11: 35 3/8 | BB11: =D11*(1-$BA$4) -> 9.969375 | BC11: =E11*(1-$BA$4) -> 9.969375 | BD11: =F11*(1-$BA$4) -> 9.9775 | BE11: =G11*(1-$BA$4) -> 10.22125 | BF11: =H11*(1-$BA$4) -> 10.70875 | BG11: =I11*(1-$BA$4) -> 11.19625 | BH11: =J11*(1-$BA$4) -> 12.07375 | BI11: =K11*(1-$BA$4) -> 12.943125 | ... CU11: =AW11*(1-$BA$4) -> 42.193125
B12: 1000 | C12: 39 3/8 | D12: 15.3375 | E12: 15.3375 | F12: 15.35 | G12: 15.8 | H12: 16.7125 | I12: 17.625 | J12: 19 | K12: 20.3875 | L12: 21.8875 | M12: 23.5 | N12: 25.125 | O12: 26.275 | P12: 27.4375 | Q12: 28.5875 | R12: 29.75 | S12: 30.9 | T12: 31.875 | U12: 32.8375 | V12: 33.8875 | W12: 35 | X12: 36.125 | Y12: 37.7 | Z12: 39.275 | AA12: 40.625 | AB12: 41.7375 | AC12: 42.85 | AD12: 44.2 | AE12: 45.5375 | AF12: 46.775 | AG12: 47.8875 | AH12: 49 | AI12: 49.9 | AJ12: 50.8 | AK12: 52.0375 | AL12: 53.6 | AM12: 55.1625 | AN12: 56.4875 | AO12: 57.8125 | AP12: 59.025 | AQ12: 60.1375 | AR12: 61.25 | AS12: 62.35 | AT12: 63.4625 | AU12: 64.5625 | AV12: 65.675 | AW12: 66.775 | AZ12: 1000 | BA12: 39 3/8 | BB12: =D12*(1-$BA$4) -> 9.969375 | BC12: =E12*(1-$BA$4) -> 9.969375 | BD12: =F12*(1-$BA$4) -> 9.9775 | BE12: =G12*(1-$BA$4) -> 10.27 | BF12: =H12*(1-$BA$4) -> 10.863125 | BG12: =I12*(1-$BA$4) -> 11.45625 | BH12: =J12*(1-$BA$4) -> 12.35 | BI12: =K12*(1-$BA$4) -> 13.251875 | ... CU12: =AW12*(1-$BA$4) -> 43.40375
B13: 1100 | C13: 43 1/4 | D13: 15.3375 | E13: 15.3375 | F13: 15.35 | G13: 15.8875 | H13: 16.95 | I13: 18.025 | J13: 19.4375 | K13: 20.85 | L13: 22.4 | M13: 24.075 | N13: 25.75 | O13: 26.9375 | P13: 28.125 | Q13: 29.3125 | R13: 30.5125 | S13: 31.7 | T13: 32.6875 | U13: 33.6875 | V13: 34.7625 | W13: 35.9125 | X13: 37.0625 | Y13: 38.6875 | Z13: 40.3125 | AA13: 41.7125 | AB13: 42.8625 | AC13: 44.0125 | AD13: 45.3875 | AE13: 46.7625 | AF13: 48.025 | AG13: 49.175 | AH13: 50.3375 | AI13: 51.2625 | AJ13: 52.2 | AK13: 53.475 | AL13: 55.0875 | AM13: 56.7 | AN13: 58.05 | AO13: 59.4125 | AP13: 60.6625 | AQ13: 61.8 | AR13: 62.95 | AS13: 64.0875 | AT13: 65.225 | AU13: 66.3625 | AV13: 67.5125 | AW13: 68.65 | AZ13: 1100 | BA13: 43 1/4 | BB13: =D13*(1-$BA$4) -> 9.969375 | BC13: =E13*(1-$BA$4) -> 9.969375 | BD13: =F13*(1-$BA$4) -> 9.9775 | BE13: =G13*(1-$BA$4) -> 10.326875 | BF13: =H13*(1-$BA$4) -> 11.0175 | BG13: =I13*(1-$BA$4) -> 11.71625 | BH13: =J13*(1-$BA$4) -> 12.634375 | BI13: =K13*(1-$BA$4) -> 13.5525 | ... CU13: =AW13*(1-$BA$4) -> 44.6225
B14: 1200 | C14: 47 1/4 | D14: 15.3375 | E14: 15.3375 | F14: 15.35 | G14: 15.9625 | H14: 17.2 | I14: 18.425 | J14: 19.875 | K14: 21.325 | L14: 22.9125 | M14: 24.65 | N14: 26.375 | O14: 27.6 | P14: 28.8125 | Q14: 30.0375 | R14: 31.275 | S14: 32.5 | T14: 33.5125 | U14: 34.525 | V14: 35.625 | W14: 36.8125 | X14: 38 | Y14: 39.675 | Z14: 41.3625 | AA14: 42.8 | AB14: 43.9875 | AC14: 45.175 | AD14: 46.575 | AE14: 47.9875 | AF14: 49.2875 | AG14: 50.475 | AH14: 51.6625 | AI14: 52.625 | AJ14: 53.5875 | AK14: 54.9 | AL14: 56.5625 | AM14: 58.225 | AN14: 59.6125 | AO14: 61 | AP14: 62.2875 | AQ14: 63.4625 | AR14: 64.6375 | AS14: 65.8125 | AT14: 66.9875 | AU14: 68.1625 | AV14: 69.35 | AW14: 70.525 | AZ14: 1200 | BA14: 47 1/4 | BB14: =D14*(1-$BA$4) -> 9.969375 | BC14: =E14*(1-$BA$4) -> 9.969375 | BD14: =F14*(1-$BA$4) -> 9.9775 | BE14: =G14*(1-$BA$4) -> 10.375625 | BF14: =H14*(1-$BA$4) -> 11.18 | BG14: =I14*(1-$BA$4) -> 11.97625 | BH14: =J14*(1-$BA$4) -> 12.91875 | BI14: =K14*(1-$BA$4) -> 13.86125 | ... CU14: =AW14*(1-$BA$4) -> 45.84125
B15: 1300 | C15: 51 1/8 | D15: 15.3375 | E15: 15.5375 | F15: 15.7375 | G15: 16.475 | H15: 17.75 | I15: 19.0125 | J15: 20.5 | K15: 21.9875 | L15: 23.6125 | M15: 25.4 | N15: 27.1875 | O15: 28.4375 | P15: 29.6875 | Q15: 30.95 | R15: 32.225 | S15: 33.4875 | T15: 34.525 | U15: 35.5625 | V15: 36.6875 | W15: 37.9125 | X15: 39.1375 | Y15: 40.8625 | Z15: 42.5875 | AA15: 44.075 | AB15: 45.3 | AC15: 46.525 | AD15: 47.9625 | AE15: 49.4 | AF15: 50.725 | AG15: 51.95 | AH15: 53.175 | AI15: 54.1625 | AJ15: 55.1625 | AK15: 56.5125 | AL15: 58.225 | AM15: 59.9375 | AN15: 61.3625 | AO15: 62.7875 | AP15: 64.1 | AQ15: 65.3125 | AR15: 66.525 | AS15: 67.725 | AT15: 68.9375 | AU15: 70.15 | AV15: 71.3625 | AW15: 72.575 | AZ15: 1300 | BA15: 51 1/8 | BB15: =D15*(1-$BA$4) -> 9.969375 | BC15: =E15*(1-$BA$4) -> 10.099375 | BD15: =F15*(1-$BA$4) -> 10.229375 | BE15: =G15*(1-$BA$4) -> 10.70875 | BF15: =H15*(1-$BA$4) -> 11.5375 | BG15: =I15*(1-$BA$4) -> 12.358125 | BH15: =J15*(1-$BA$4) -> 13.325 | BI15: =K15*(1-$BA$4) -> 14.291875 | ... CU15: =AW15*(1-$BA$4) -> 47.17375
B16: 1400 | C16: 55 1/8 | D16: 15.3375 | E16: 15.7375 | F16: 16.1375 | G16: 16.9875 | H16: 18.3 | I16: 19.6 | J16: 21.125 | K16: 22.6375 | L16: 24.3125 | M16: 26.15 | N16: 27.9875 | O16: 29.275 | P16: 30.5625 | Q16: 31.8625 | R16: 33.175 | S16: 34.475 | T16: 35.525 | U16: 36.5875 | V16: 37.7375 | W16: 39 | X16: 40.2625 | Y16: 42.0375 | Z16: 43.825 | AA16: 45.3375 | AB16: 46.6 | AC16: 47.8625 | AD16: 49.3375 | AE16: 50.8125 | AF16: 52.175 | AG16: 53.425 | AH16: 54.675 | AI16: 55.7 | AJ16: 56.725 | AK16: 58.1125 | AL16: 59.875 | AM16: 61.6375 | AN16: 63.1 | AO16: 64.5625 | AP16: 65.9125 | AQ16: 67.15 | AR16: 68.4 | AS16: 69.65 | AT16: 70.8875 | AU16: 72.1375 | AV16: 73.375 | AW16: 74.625 | AZ16: 1400 | BA16: 55 1/8 | BB16: =D16*(1-$BA$4) -> 9.969375 | BC16: =E16*(1-$BA$4) -> 10.229375 | BD16: =F16*(1-$BA$4) -> 10.489375 | BE16: =G16*(1-$BA$4) -> 11.041875 | BF16: =H16*(1-$BA$4) -> 11.895 | BG16: =I16*(1-$BA$4) -> 12.74 | BH16: =J16*(1-$BA$4) -> 13.73125 | BI16: =K16*(1-$BA$4) -> 14.714375 | ... CU16: =AW16*(1-$BA$4) -> 48.50625
B17: 1500 | C17: 59 | D17: 15.3375 | E17: 15.8625 | F17: 16.3875 | G17: 17.325 | H17: 18.6625 | I17: 20 | J17: 21.55 | K17: 23.1125 | L17: 24.825 | M17: 26.7125 | N17: 28.6 | O17: 29.925 | P17: 31.25 | Q17: 32.5875 | R17: 33.925 | S17: 35.275 | T17: 36.35 | U17: 37.4375 | V17: 38.625 | W17: 39.9125 | X17: 41.2125 | Y17: 43.0375 | Z17: 44.875 | AA17: 46.4375 | AB17: 47.725 | AC17: 49.025 | AD17: 50.525 | AE17: 52.0375 | AF17: 53.4375 | AG17: 54.725 | AH17: 56.0125 | AI17: 57.0625 | AJ17: 58.1125 | AK17: 59.55 | AL17: 61.3625 | AM17: 63.175 | AN17: 64.6625 | AO17: 66.15 | AP17: 67.5375 | AQ17: 68.825 | AR17: 70.1125 | AS17: 71.3875 | AT17: 72.6625 | AU17: 73.95 | AV17: 75.225 | AW17: 76.5 | AZ17: 1500 | BA17: 59 | BB17: =D17*(1-$BA$4) -> 9.969375 | BC17: =E17*(1-$BA$4) -> 10.310625 | BD17: =F17*(1-$BA$4) -> 10.651875 | BE17: =G17*(1-$BA$4) -> 11.26125 | BF17: =H17*(1-$BA$4) -> 12.130625 | BG17: =I17*(1-$BA$4) -> 13 | BH17: =J17*(1-$BA$4) -> 14.0075 | BI17: =K17*(1-$BA$4) -> 15.023125 | ... CU17: =AW17*(1-$BA$4) -> 49.725
B18: 1600 | C18: 63 | D18: 15.3375 | E18: 15.9875 | F18: 16.65 | G18: 17.6625 | H18: 19.025 | I18: 20.3875 | J18: 21.9875 | K18: 23.575 | L18: 25.3375 | M18: 27.275 | N18: 29.2125 | O18: 30.575 | P18: 31.9375 | Q18: 33.3125 | R18: 34.6875 | S18: 36.0625 | T18: 37.175 | U18: 38.2875 | V18: 39.5 | W18: 40.8375 | X18: 42.1625 | Y18: 44.0375 | Z18: 45.925 | AA18: 47.525 | AB18: 48.85 | AC18: 50.175 | AD18: 51.7125 | AE18: 53.25 | AF18: 54.6875 | AG18: 56.025 | AH18: 57.35 | AI18: 58.425 | AJ18: 59.5125 | AK18: 60.975 | AL18: 62.8375 | AM18: 64.7 | AN18: 66.225 | AO18: 67.75 | AP18: 69.175 | AQ18: 70.4875 | AR18: 71.8125 | AS18: 73.125 | AT18: 74.4375 | AU18: 75.75 | AV18: 77.0625 | AW18: 78.375 | AZ18: 1600 | BA18: 63 | BB18: =D18*(1-$BA$4) -> 9.969375 | BC18: =E18*(1-$BA$4) -> 10.391875 | BD18: =F18*(1-$BA$4) -> 10.8225 | BE18: =G18*(1-$BA$4) -> 11.480625 | BF18: =H18*(1-$BA$4) -> 12.36625 | BG18: =I18*(1-$BA$4) -> 13.251875 | BH18: =J18*(1-$BA$4) -> 14.291875 | BI18: =K18*(1-$BA$4) -> 15.32375 | ... CU18: =AW18*(1-$BA$4) -> 50.94375
B19: 1700 | C19: 66 7/8 | D19: 15.975 | E19: 16.3875 | F19: 16.8125 | G19: 17.7125 | H19: 19.0875 | I19: 20.4625 | J19: 22.075 | K19: 23.675 | L19: 25.4625 | M19: 27.425 | N19: 29.3875 | O19: 30.7625 | P19: 32.1375 | Q19: 33.525 | R19: 34.9125 | S19: 36.3 | T19: 37.6625 | U19: 39.025 | V19: 40.3875 | W19: 41.75 | X19: 43.1125 | Y19: 45.0375 | Z19: 46.975 | AA19: 48.6125 | AB19: 49.975 | AC19: 51.3375 | AD19: 52.9125 | AE19: 54.4875 | AF19: 55.9625 | AG19: 57.325 | AH19: 58.6875 | AI19: 59.7875 | AJ19: 60.9 | AK19: 62.4125 | AL19: 64.325 | AM19: 66.2375 | AN19: 67.8 | AO19: 69.3625 | AP19: 70.8125 | AQ19: 72.1625 | AR19: 73.5125 | AS19: 74.8625 | AT19: 76.2125 | AU19: 77.55 | AV19: 78.9 | AW19: 80.25 | AZ19: 1700 | BA19: 66 7/8 | BB19: =D19*(1-$BA$4) -> 10.38375 | BC19: =E19*(1-$BA$4) -> 10.651875 | BD19: =F19*(1-$BA$4) -> 10.928125 | BE19: =G19*(1-$BA$4) -> 11.513125 | BF19: =H19*(1-$BA$4) -> 12.406875 | BG19: =I19*(1-$BA$4) -> 13.300625 | BH19: =J19*(1-$BA$4) -> 14.34875 | BI19: =K19*(1-$BA$4) -> 15.38875 | ... CU19: =AW19*(1-$BA$4) -> 52.1625
B20: 1800 | C20: 70 7/8 | D20: 16.6125 | E20: 16.7875 | F20: 16.975 | G20: 17.7625 | H20: 19.15 | I20: 20.5375 | J20: 22.1625 | K20: 23.775 | L20: 25.575 | M20: 27.5625 | N20: 29.55 | O20: 30.95 | P20: 32.3375 | Q20: 33.7375 | R20: 35.1375 | S20: 36.5375 | T20: 38.15 | U20: 39.7625 | V20: 41.2625 | W20: 42.65 | X20: 44.05 | Y20: 46.0375 | Z20: 48.025 | AA20: 49.7125 | AB20: 51.1 | AC20: 52.5 | AD20: 54.1125 | AE20: 55.725 | AF20: 57.2375 | AG20: 58.625 | AH20: 60.0125 | AI20: 61.15 | AJ20: 62.2875 | AK20: 63.8375 | AL20: 65.8 | AM20: 67.7625 | AN20: 69.3625 | AO20: 70.9625 | AP20: 72.45 | AQ20: 73.8375 | AR20: 75.2125 | AS20: 76.5875 | AT20: 77.975 | AU20: 79.35 | AV20: 80.7375 | AW20: 82.1125 | AZ20: 1800 | BA20: 70 7/8 | BB20: =D20*(1-$BA$4) -> 10.798125 | BC20: =E20*(1-$BA$4) -> 10.911875 | BD20: =F20*(1-$BA$4) -> 11.03375 | BE20: =G20*(1-$BA$4) -> 11.545625 | BF20: =H20*(1-$BA$4) -> 12.4475 | BG20: =I20*(1-$BA$4) -> 13.349375 | BH20: =J20*(1-$BA$4) -> 14.405625 | BI20: =K20*(1-$BA$4) -> 15.45375 | ... CU20: =AW20*(1-$BA$4) -> 53.373125
B21: 1900 | C21: 74 3/4 | D21: 16.6125 | E21: 16.9125 | F21: 17.2125 | G21: 18.075 | H21: 19.5 | I21: 20.9375 | J21: 22.5875 | K21: 24.2375 | L21: 26.075 | M21: 28.1125 | N21: 30.1625 | O21: 31.5875 | P21: 33.0125 | Q21: 34.4375 | R21: 35.875 | S21: 37.3 | T21: 38.95 | U21: 40.6 | V21: 42.1375 | W21: 43.5625 | X21: 45 | Y21: 47.025 | Z21: 49.0625 | AA21: 50.8 | AB21: 52.225 | AC21: 53.6625 | AD21: 55.3125 | AE21: 56.9625 | AF21: 58.4875 | AG21: 59.9125 | AH21: 61.3375 | AI21: 62.5 | AJ21: 63.675 | AK21: 65.2625 | AL21: 67.2875 | AM21: 69.3 | AN21: 70.9375 | AO21: 72.5625 | AP21: 74.0875 | AQ21: 75.5 | AR21: 76.9125 | AS21: 78.325 | AT21: 79.7375 | AU21: 81.15 | AV21: 82.575 | AW21: 83.9875 | AZ21: 1900 | BA21: 74 3/4 | BB21: =D21*(1-$BA$4) -> 10.798125 | BC21: =E21*(1-$BA$4) -> 10.993125 | BD21: =F21*(1-$BA$4) -> 11.188125 | BE21: =G21*(1-$BA$4) -> 11.74875 | BF21: =H21*(1-$BA$4) -> 12.675 | BG21: =I21*(1-$BA$4) -> 13.609375 | BH21: =J21*(1-$BA$4) -> 14.681875 | BI21: =K21*(1-$BA$4) -> 15.754375 | ... CU21: =AW21*(1-$BA$4) -> 54.591875
B22: 2000 | C22: 78 3/4 | D22: 16.6125 | E22: 17.0375 | F22: 17.45 | G22: 18.4 | H22: 19.8625 | I22: 21.325 | J22: 23 | K22: 24.6875 | L22: 26.575 | M22: 28.6625 | N22: 30.7625 | O22: 32.225 | P22: 33.6875 | Q22: 35.1375 | R22: 36.6 | S22: 38.0625 | T22: 39.75 | U22: 41.4375 | V22: 43.0125 | W22: 44.475 | X22: 45.9375 | Y22: 48.025 | Z22: 50.1125 | AA22: 51.8875 | AB22: 53.35 | AC22: 54.8125 | AD22: 56.5 | AE22: 58.1875 | AF22: 59.75 | AG22: 61.2125 | AH22: 62.6625 | AI22: 63.8625 | AJ22: 65.0625 | AK22: 66.7 | AL22: 68.7625 | AM22: 70.8375 | AN22: 72.5 | AO22: 74.1625 | AP22: 75.725 | AQ22: 77.1625 | AR22: 78.6125 | AS22: 80.0625 | AT22: 81.5 | AU22: 82.95 | AV22: 84.4125 | AW22: 85.8625 | AZ22: 2000 | BA22: 78 3/4 | BB22: =D22*(1-$BA$4) -> 10.798125 | BC22: =E22*(1-$BA$4) -> 11.074375 | BD22: =F22*(1-$BA$4) -> 11.3425 | BE22: =G22*(1-$BA$4) -> 11.96 | BF22: =H22*(1-$BA$4) -> 12.910625 | BG22: =I22*(1-$BA$4) -> 13.86125 | BH22: =J22*(1-$BA$4) -> 14.95 | BI22: =K22*(1-$BA$4) -> 16.046875 | ... CU22: =AW22*(1-$BA$4) -> 55.810625
B23: 2100 | C23: 82 5/8 | D23: 17.2625 | E23: 17.6875 | F23: 18.1125 | G23: 19.075 | H23: 20.575 | I23: 22.075 | J23: 23.7875 | K23: 25.5125 | L23: 27.4375 | M23: 29.5875 | N23: 31.725 | O23: 33.225 | P23: 34.725 | Q23: 36.2125 | R23: 37.7125 | S23: 39.2125 | T23: 40.925 | U23: 42.6375 | V23: 44.25 | W23: 45.75 | X23: 47.25 | Y23: 49.3875 | Z23: 51.525 | AA23: 53.3375 | AB23: 54.8375 | AC23: 56.3375 | AD23: 58.05 | AE23: 59.775 | AF23: 61.375 | AG23: 62.875 | AH23: 64.375 | AI23: 65.5875 | AJ23: 66.8125 | AK23: 68.475 | AL23: 70.6 | AM23: 72.725 | AN23: 74.425 | AO23: 76.125 | AP23: 77.7125 | AQ23: 79.1875 | AR23: 80.675 | AS23: 82.15 | AT23: 83.6375 | AU23: 85.125 | AV23: 86.6125 | AW23: 88.1 | AZ23: 2100 | BA23: 82 5/8 | BB23: =D23*(1-$BA$4) -> 11.220625 | BC23: =E23*(1-$BA$4) -> 11.496875 | BD23: =F23*(1-$BA$4) -> 11.773125 | BE23: =G23*(1-$BA$4) -> 12.39875 | BF23: =H23*(1-$BA$4) -> 13.37375 | BG23: =I23*(1-$BA$4) -> 14.34875 | BH23: =J23*(1-$BA$4) -> 15.461875 | BI23: =K23*(1-$BA$4) -> 16.583125 | ... CU23: =AW23*(1-$BA$4) -> 57.265
B24: 2200 | C24: 86 5/8 | D24: 17.9 | E24: 18.3375 | F24: 18.775 | G24: 19.75 | H24: 21.2875 | I24: 22.825 | J24: 24.575 | K24: 26.3375 | L24: 28.3125 | M24: 30.5 | N24: 32.6875 | O24: 34.225 | P24: 35.7625 | Q24: 37.2875 | R24: 38.825 | S24: 40.35 | T24: 42.1 | U24: 43.8375 | V24: 45.475 | W24: 47.0125 | X24: 48.55 | Y24: 50.7375 | Z24: 52.925 | AA24: 54.7875 | AB24: 56.325 | AC24: 57.8625 | AD24: 59.6125 | AE24: 61.3625 | AF24: 63 | AG24: 64.5375 | AH24: 66.075 | AI24: 67.3125 | AJ24: 68.55 | AK24: 70.2625 | AL24: 72.425 | AM24: 74.6 | AN24: 76.3375 | AO24: 78.075 | AP24: 79.7 | AQ24: 81.2125 | AR24: 82.7375 | AS24: 84.25 | AT24: 85.7625 | AU24: 87.2875 | AV24: 88.8 | AW24: 90.325 | AZ24: 2200 | BA24: 86 5/8 | BB24: =D24*(1-$BA$4) -> 11.635 | BC24: =E24*(1-$BA$4) -> 11.919375 | BD24: =F24*(1-$BA$4) -> 12.20375 | BE24: =G24*(1-$BA$4) -> 12.8375 | BF24: =H24*(1-$BA$4) -> 13.836875 | BG24: =I24*(1-$BA$4) -> 14.83625 | BH24: =J24*(1-$BA$4) -> 15.97375 | BI24: =K24*(1-$BA$4) -> 17.119375 | ... CU24: =AW24*(1-$BA$4) -> 58.71125
B25: 2300 | C25: 90 1/2 | D25: 17.9 | E25: 18.4625 | F25: 19.0125 | G25: 20.075 | H25: 21.65 | I25: 23.2125 | J25: 25 | K25: 26.7875 | L25: 28.8 | M25: 31.0375 | N25: 33.2875 | O25: 34.85 | P25: 36.425 | Q25: 37.9875 | R25: 39.55 | S25: 41.125 | T25: 42.9 | U25: 44.6875 | V25: 46.3625 | W25: 47.925 | X25: 49.5 | Y25: 51.75 | Z25: 53.9875 | AA25: 55.9 | AB25: 57.4625 | AC25: 59.025 | AD25: 60.8125 | AE25: 62.6 | AF25: 64.275 | AG25: 65.8375 | AH25: 67.4 | AI25: 68.675 | AJ25: 69.95 | AK25: 71.6875 | AL25: 73.9125 | AM25: 76.1375 | AN25: 77.9 | AO25: 79.6625 | AP25: 81.325 | AQ25: 82.8875 | AR25: 84.45 | AS25: 85.9875 | AT25: 87.5375 | AU25: 89.0875 | AV25: 90.6375 | AW25: 92.1875 | AZ25: 2300 | BA25: 90 1/2 | BB25: =D25*(1-$BA$4) -> 11.635 | BC25: =E25*(1-$BA$4) -> 12.000625 | BD25: =F25*(1-$BA$4) -> 12.358125 | BE25: =G25*(1-$BA$4) -> 13.04875 | BF25: =H25*(1-$BA$4) -> 14.0725 | BG25: =I25*(1-$BA$4) -> 15.088125 | BH25: =J25*(1-$BA$4) -> 16.25 | BI25: =K25*(1-$BA$4) -> 17.411875 | ... CU25: =AW25*(1-$BA$4) -> 59.921875
B26: 2400 | C26: 94 1/2 | D26: 17.9 | E26: 18.575 | F26: 19.2625 | G26: 20.4 | H26: 22 | I26: 23.6 | J26: 25.425 | K26: 27.2375 | L26: 29.3 | M26: 31.5875 | N26: 33.875 | O26: 35.475 | P26: 37.0875 | Q26: 38.6875 | R26: 40.2875 | S26: 41.8875 | T26: 43.7125 | U26: 45.525 | V26: 47.2375 | W26: 48.85 | X26: 50.45 | Y26: 52.75 | Z26: 55.05 | AA26: 57 | AB26: 58.5875 | AC26: 60.175 | AD26: 62 | AE26: 63.825 | AF26: 65.5375 | AG26: 67.125 | AH26: 68.725 | AI26: 70.025 | AJ26: 71.3375 | AK26: 73.125 | AL26: 75.3875 | AM26: 77.6625 | AN26: 79.4625 | AO26: 81.2625 | AP26: 82.9625 | AQ26: 84.55 | AR26: 86.15 | AS26: 87.725 | AT26: 89.3125 | AU26: 90.8875 | AV26: 92.475 | AW26: 94.05 | AZ26: 2400 | BA26: 94 1/2 | BB26: =D26*(1-$BA$4) -> 11.635 | BC26: =E26*(1-$BA$4) -> 12.07375 | BD26: =F26*(1-$BA$4) -> 12.520625 | BE26: =G26*(1-$BA$4) -> 13.26 | BF26: =H26*(1-$BA$4) -> 14.3 | BG26: =I26*(1-$BA$4) -> 15.34 | BH26: =J26*(1-$BA$4) -> 16.52625 | BI26: =K26*(1-$BA$4) -> 17.704375 | ... CU26: =AW26*(1-$BA$4) -> 61.1325
B27: 2500 | C27: 98 3/8 | D27: 18.5375 | E27: 19.0375 | F27: 19.5375 | G27: 20.6125 | H27: 22.2375 | I27: 23.8625 | J27: 25.7 | K27: 27.55 | L27: 29.6375 | M27: 31.975 | N27: 34.3 | O27: 35.925 | P27: 37.5625 | Q27: 39.1875 | R27: 40.8125 | S27: 42.4375 | T27: 44.275 | U27: 46.125 | V27: 47.8625 | W27: 49.4875 | X27: 51.125 | Y27: 53.4625 | Z27: 55.8 | AA27: 57.775 | AB27: 59.4 | AC27: 61.025 | AD27: 62.8625 | AE27: 64.7125 | AF27: 66.45 | AG27: 68.075 | AH27: 69.7 | AI27: 71.175 | AJ27: 72.65 | AK27: 74.55 | AL27: 76.875 | AM27: 79.2 | AN27: 81.0375 | AO27: 82.8625 | AP27: 84.5875 | AQ27: 86.2125 | AR27: 87.8375 | AS27: 89.45 | AT27: 91.075 | AU27: 92.6875 | AV27: 94.3125 | AW27: 95.925 | AZ27: 2500 | BA27: 98 3/8 | BB27: =D27*(1-$BA$4) -> 12.049375 | BC27: =E27*(1-$BA$4) -> 12.374375 | BD27: =F27*(1-$BA$4) -> 12.699375 | BE27: =G27*(1-$BA$4) -> 13.398125 | BF27: =H27*(1-$BA$4) -> 14.454375 | BG27: =I27*(1-$BA$4) -> 15.510625 | BH27: =J27*(1-$BA$4) -> 16.705 | BI27: =K27*(1-$BA$4) -> 17.9075 | ... CU27: =AW27*(1-$BA$4) -> 62.35125
B28: 2600 | C28: 102 3/8 | D28: 19.175 | E28: 19.5 | F28: 19.825 | G28: 20.8125 | H28: 22.4625 | I28: 24.1125 | J28: 25.9875 | K28: 27.8625 | L28: 29.9875 | M28: 32.35 | N28: 34.725 | O28: 36.375 | P28: 38.0375 | Q28: 39.6875 | R28: 41.3375 | S28: 42.9875 | T28: 44.85 | U28: 46.7125 | V28: 48.475 | W28: 50.1375 | X28: 51.7875 | Y28: 54.1625 | Z28: 56.5375 | AA28: 58.55 | AB28: 60.2125 | AC28: 61.8625 | AD28: 63.7375 | AE28: 65.6 | AF28: 67.3625 | AG28: 69.0125 | AH28: 70.6625 | AI28: 72.3125 | AJ28: 73.975 | AK28: 75.9875 | AL28: 78.3625 | AM28: 80.7375 | AN28: 82.6 | AO28: 84.4625 | AP28: 86.225 | AQ28: 87.875 | AR28: 89.525 | AS28: 91.175 | AT28: 92.8375 | AU28: 94.4875 | AV28: 96.15 | AW28: 97.8 | AZ28: 2600 | BA28: 102 3/8 | BB28: =D28*(1-$BA$4) -> 12.46375 | BC28: =E28*(1-$BA$4) -> 12.675 | BD28: =F28*(1-$BA$4) -> 12.88625 | BE28: =G28*(1-$BA$4) -> 13.528125 | BF28: =H28*(1-$BA$4) -> 14.600625 | BG28: =I28*(1-$BA$4) -> 15.673125 | BH28: =J28*(1-$BA$4) -> 16.891875 | BI28: =K28*(1-$BA$4) -> 18.110625 | ... CU28: =AW28*(1-$BA$4) -> 63.57
B29: 2700 | C29: 106 1/4 | D29: 19.175 | E29: 19.6125 | F29: 20.0625 | G29: 21.125 | H29: 22.8125 | I29: 24.5 | J29: 26.4 | K29: 28.3125 | L29: 30.475 | M29: 32.9 | N29: 35.325 | O29: 37.0125 | P29: 38.7 | Q29: 40.3875 | R29: 42.075 | S29: 43.7625 | T29: 45.6625 | U29: 47.5625 | V29: 49.35 | W29: 51.0375 | X29: 52.7375 | Y29: 55.15 | Z29: 57.575 | AA29: 59.6375 | AB29: 61.325 | AC29: 63.0125 | AD29: 64.9125 | AE29: 66.8125 | AF29: 68.6125 | AG29: 70.3 | AH29: 71.9875 | AI29: 73.675 | AJ29: 75.3625 | AK29: 77.425 | AL29: 79.85 | AM29: 82.275 | AN29: 84.175 | AO29: 86.075 | AP29: 87.8625 | AQ29: 89.5375 | AR29: 91.225 | AS29: 92.9125 | AT29: 94.6125 | AU29: 96.3 | AV29: 97.975 | AW29: 99.6625 | AZ29: 2700 | BA29: 106 1/4 | BB29: =D29*(1-$BA$4) -> 12.46375 | BC29: =E29*(1-$BA$4) -> 12.748125 | BD29: =F29*(1-$BA$4) -> 13.040625 | BE29: =G29*(1-$BA$4) -> 13.73125 | BF29: =H29*(1-$BA$4) -> 14.828125 | BG29: =I29*(1-$BA$4) -> 15.925 | BH29: =J29*(1-$BA$4) -> 17.16 | BI29: =K29*(1-$BA$4) -> 18.403125 | ... CU29: =AW29*(1-$BA$4) -> 64.780625
B30: 2800 | C30: 110 1/4 | D30: 19.175 | E30: 19.7375 | F30: 20.3 | G30: 21.4375 | H30: 23.1625 | I30: 24.8875 | J30: 26.825 | K30: 28.7625 | L30: 30.9625 | M30: 33.4375 | N30: 35.9125 | O30: 37.6375 | P30: 39.3625 | Q30: 41.0875 | R30: 42.8 | S30: 44.525 | T30: 46.4625 | U30: 48.4 | V30: 50.225 | W30: 51.95 | X30: 53.675 | Y30: 56.15 | Z30: 58.6125 | AA30: 60.7125 | AB30: 62.425 | AC30: 64.15 | AD30: 66.0875 | AE30: 68.025 | AF30: 69.85 | AG30: 71.575 | AH30: 73.3 | AI30: 75.025 | AJ30: 76.75 | AK30: 78.85 | AL30: 81.325 | AM30: 83.8 | AN30: 85.7375 | AO30: 87.675 | AP30: 89.5 | AQ30: 91.2125 | AR30: 92.925 | AS30: 94.65 | AT30: 96.3875 | AU30: 98.1 | AV30: 99.8125 | AW30: 101.525 | AZ30: 2800 | BA30: 110 1/4 | BB30: =D30*(1-$BA$4) -> 12.46375 | BC30: =E30*(1-$BA$4) -> 12.829375 | BD30: =F30*(1-$BA$4) -> 13.195 | BE30: =G30*(1-$BA$4) -> 13.934375 | BF30: =H30*(1-$BA$4) -> 15.055625 | BG30: =I30*(1-$BA$4) -> 16.176875 | BH30: =J30*(1-$BA$4) -> 17.43625 | BI30: =K30*(1-$BA$4) -> 18.695625 | ... CU30: =AW30*(1-$BA$4) -> 65.99125
... B32: 3000 | C32: 118 1/8 | D32: 20.45 | E32: 20.75 | F32: 21.0375 | G32: 22.075 | H32: 23.8625 | I32: 25.65 | J32: 27.65 | K32: 29.65 | L32: 31.9375 | M32: 34.5125 | N32: 37.0875 | O32: 38.8875 | P32: 40.675 | Q32: 42.475 | R32: 44.2625 | S32: 46.05 | T32: 48.05 | U32: 50.0625 | V32: 51.95 | W32: 53.7375 | X32: 55.525 | Y32: 58.1125 | Z32: 60.7 | AA32: 62.8875 | AB32: 64.675 | AC32: 66.4625 | AD32: 68.4625 | AE32: 70.4625 | AF32: 72.3625 | AG32: 74.15 | AH32: 75.9375 | AI32: 77.725 | AJ32: 79.5125 | AK32: 81.7 | AL32: 84.275 | AM32: 86.85 | AN32: 88.85 | AO32: 90.8625 | AP32: 92.7625 | AQ32: 94.55 | AR32: 96.3375 | AS32: 98.125 | AT32: 99.9125 | AU32: 101.7 | AV32: 103.4875 | AW32: 105.275 | AZ32: 3000 | BA32: 118 1/8 | BB32: =D32*(1-$BA$4) -> 13.2925 | BC32: =E32*(1-$BA$4) -> 13.4875 | BD32: =F32*(1-$BA$4) -> 13.674375 | BE32: =G32*(1-$BA$4) -> 14.34875 | BF32: =H32*(1-$BA$4) -> 15.510625 | BG32: =I32*(1-$BA$4) -> 16.6725 | BH32: =J32*(1-$BA$4) -> 17.9725 | BI32: =K32*(1-$BA$4) -> 19.2725 | ... CU32: =AW32*(1-$BA$4) -> 68.42875
B33: 3100 | C33: 122 | D33: 20.45 | E33: 20.8625 | F33: 21.275 | G33: 22.3875 | H33: 24.2125 | I33: 26.0375 | J33: 28.075 | K33: 30.1125 | L33: 32.4375 | M33: 35.0625 | N33: 37.6875 | O33: 39.5125 | P33: 41.35 | Q33: 43.175 | R33: 45 | S33: 46.825 | T33: 48.8625 | U33: 50.9 | V33: 52.825 | W33: 54.65 | X33: 56.475 | Y33: 59.1 | Z33: 61.7375 | AA33: 63.9625 | AB33: 65.7875 | AC33: 67.6125 | AD33: 69.65 | AE33: 71.6875 | AF33: 73.6125 | AG33: 75.4375 | AH33: 77.2625 | AI33: 79.075 | AJ33: 80.9 | AK33: 83.125 | AL33: 85.75 | AM33: 88.3875 | AN33: 90.425 | AO33: 92.4625 | AP33: 94.3875 | AQ33: 96.2125 | AR33: 98.0375 | AS33: 99.8625 | AT33: 101.6875 | AU33: 103.5 | AV33: 105.325 | AW33: 107.15 | AZ33: 3100 | BA33: 122 | BB33: =D33*(1-$BA$4) -> 13.2925 | BC33: =E33*(1-$BA$4) -> 13.560625 | BD33: =F33*(1-$BA$4) -> 13.82875 | BE33: =G33*(1-$BA$4) -> 14.551875 | BF33: =H33*(1-$BA$4) -> 15.738125 | BG33: =I33*(1-$BA$4) -> 16.924375 | BH33: =J33*(1-$BA$4) -> 18.24875 | BI33: =K33*(1-$BA$4) -> 19.573125 | ... CU33: =AW33*(1-$BA$4) -> 69.6475
B34: 3200 | C34: 126 | D34: 20.45 | E34: 20.975 | F34: 21.5125 | G34: 22.7 | H34: 24.5625 | I34: 26.4125 | J34: 28.4875 | K34: 30.5625 | L34: 32.9375 | M34: 35.6 | N34: 38.275 | O34: 40.15 | P34: 42.0125 | Q34: 43.875 | R34: 45.7375 | S34: 47.5875 | T34: 49.6625 | U34: 51.725 | V34: 53.6875 | W34: 55.55 | X34: 57.4125 | Y34: 60.0875 | Z34: 62.775 | AA34: 65.0375 | AB34: 66.9 | AC34: 68.75 | AD34: 70.825 | AE34: 72.9 | AF34: 74.8625 | AG34: 76.725 | AH34: 78.575 | AI34: 80.425 | AJ34: 82.2875 | AK34: 84.55 | AL34: 87.2375 | AM34: 89.9125 | AN34: 91.9875 | AO34: 94.05 | AP34: 96.0125 | AQ34: 97.875 | AR34: 99.7375 | AS34: 101.6 | AT34: 103.4625 | AU34: 105.3125 | AV34: 107.1625 | AW34: 109.0125 | AZ34: 3200 | BA34: 126 | BB34: =D34*(1-$BA$4) -> 13.2925 | BC34: =E34*(1-$BA$4) -> 13.63375 | BD34: =F34*(1-$BA$4) -> 13.983125 | BE34: =G34*(1-$BA$4) -> 14.755 | BF34: =H34*(1-$BA$4) -> 15.965625 | BG34: =I34*(1-$BA$4) -> 17.168125 | BH34: =J34*(1-$BA$4) -> 18.516875 | BI34: =K34*(1-$BA$4) -> 19.865625 | ... CU34: =AW34*(1-$BA$4) -> 70.858125
B37: A | C37: mm | D37: 500 | E37: 600 | F37: 700 | G37: 800 | H37: 900 | I37: 1000 | J37: 1100 | K37: 1200 | L37: 1300 | M37: 1400 | N37: 1500 | O37: 1600 | P37: 1700 | Q37: 1800 | R37: 1900 | S37: 2000 | T37: 2100 | U37: 2200 | V37: 2300 | W37: 2400 | X37: 2500 | Y37: 2600 | Z37: 2700 | AA37: 2800 | AB37: 2900 | AC37: 3000 | AD37: 3100 | AE37: 3200 | AF37: 3300 | AG37: 3400 | AH37: 3500 | AI37: 3600 | AJ37: 3700 | AK37: 3800 | AL37: 3900 | AM37: 4000 | AN37: 4100 | AO37: 4200 | AP37: 4300 | AQ37: 4400 | AR37: 4500 | AS37: 4600 | AT37: 4700 | AU37: 4800 | AV37: 4900 | AW37: 5000 | AZ37: A | BA37: mm | BB37: 500 | BC37: 600 | BD37: 700 | BE37: 800 | BF37: 900 | BG37: 1000 | BH37: 1100 | BI37: 1200 | BJ37: 1300 | BK37: 1400 | BL37: 1500 | BM37: 1600 | BN37: 1700 | BO37: 1800 | BP37: 1900 | BQ37: 2000 | BR37: 2100 | BS37: 2200 | BT37: 2300 | BU37: 2400 | BV37: 2500 | BW37: 2600 | BX37: 2700 | BY37: 2800 | BZ37: 2900 | CA37: 3000 | CB37: 3100 | CC37: 3200 | CD37: 3300 | CE37: 3400 | CF37: 3500 | CG37: 3600 | CH37: 3700 | CI37: 3800 | CJ37: 3900 | CK37: 4000 | CL37: 4100 | CM37: 4200 | CN37: 4300 | CO37: 4400 | CP37: 4500 | CQ37: 4600 | CR37: 4700 | CS37: 4800 | CT37: 4900 | CU37: 5000
B38: mm | C38: inch | D38: 19 5/8 | E38: 23 5/8 | F38: 27 1/2 | G38: 31 1/2 | H38: 35 3/8 | I38: 39 3/8 | J38: 43 1/4 | K38: 47 1/4 | L38: 51 1/8 | M38: 55 1/8 | N38: 59 | O38: 63 | P38: 66 7/8 | Q38: 70 7/8 | R38: 74 3/4 | S38: 78 3/4 | T38: 82 5/8 | U38: 86 5/8 | V38: 90 1/2 | W38: 94 1/2 | X38: 98 3/8 | Y38: 102 3/8 | Z38: 106 1/4 | AA38: 110 1/4 | AB38: 114 1/8 | AC38: 118 1/8 | AD38: 122 | AE38: 126 | AF38: 129 7/8 | AG38: 133 7/8 | AH38: 137 3/4 | AI38: 141 3/4 | AJ38: 145 5/8 | AK38: 149 5/8 | AL38: 153 1/2 | AM38: 157 1/2 | AN38: 161 3/8 | AO38: 165 3/8 | AP38: 169 1/4 | AQ38: 173 1/4 | AR38: 177 1/8 | AS38: 181 1/8 | AT38: 185 | AU38: 189 | AV38: 192 7/8 | AW38: 196 7/8 | AZ38: mm | BA38: inch | BB38: 19 5/8 | BC38: 23 5/8 | BD38: 27 1/2 | BE38: 31 1/2 | BF38: 35 3/8 | BG38: 39 3/8 | BH38: 43 1/4 | BI38: 47 1/4 | BJ38: 51 1/8 | BK38: 55 1/8 | BL38: 59 | BM38: 63 | BN38: 66 7/8 | BO38: 70 7/8 | BP38: 74 3/4 | BQ38: 78 3/4 | BR38: 82 5/8 | BS38: 86 5/8 | BT38: 90 1/2 | BU38: 94 1/2 | BV38: 98 3/8 | BW38: 102 3/8 | BX38: 106 1/4 | BY38: 110 1/4 | BZ38: 114 1/8 | CA38: 118 1/8 | CB38: 122 | CC38: 126 | CD38: 129 7/8 | CE38: 133 7/8 | CF38: 137 3/4 | CG38: 141 3/4 | CH38: 145 5/8 | CI38: 149 5/8 | CJ38: 153 1/2 | CK38: 157 1/2 | CL38: 161 3/8 | CM38: 165 3/8 | CN38: 169 1/4 | CO38: 173 1/4 | CP38: 177 1/8 | CQ38: 181 1/8 | CR38: 185 | CS38: 189 | CT38: 192 7/8 | CU38: 196 7/8
B39: 600 | C39: 23 5/8 | D39: 16.7875 | E39: 16.7875 | F39: 16.7875 | G39: 16.9875 | H39: 17.375 | I39: 17.7625 | J39: 19.1375 | K39: 20.5 | L39: 21.9625 | M39: 23.525 | N39: 25.075 | O39: 26.2 | P39: 27.3375 | Q39: 28.4625 | R39: 29.575 | S39: 30.7 | T39: 31.6625 | U39: 32.625 | V39: 33.65 | W39: 34.7375 | X39: 35.825 | Y39: 37.3375 | Z39: 38.85 | AA39: 40.1625 | AB39: 41.25 | AC39: 42.3375 | AD39: 43.6625 | AE39: 45 | AF39: 46.2125 | AG39: 47.3 | AH39: 48.3875 | AI39: 49.2625 | AJ39: 50.125 | AK39: 51.3125 | AL39: 52.825 | AM39: 54.325 | AN39: 55.6375 | AO39: 56.95 | AP39: 58.15 | AQ39: 59.2375 | AR39: 60.3125 | AS39: 61.3875 | AT39: 62.4625 | AU39: 63.5375 | AV39: 64.6125 | AW39: 65.6875 | AZ39: 600 | BA39: 23 5/8 | BB39: =D39*(1-$BA$4) -> 10.911875 | BC39: =E39*(1-$BA$4) -> 10.911875 | BD39: =F39*(1-$BA$4) -> 10.911875 | BE39: =G39*(1-$BA$4) -> 11.041875 | BF39: =H39*(1-$BA$4) -> 11.29375 | BG39: =I39*(1-$BA$4) -> 11.545625 | BH39: =J39*(1-$BA$4) -> 12.439375 | BI39: =K39*(1-$BA$4) -> 13.325 | ... CU39: =AW39*(1-$BA$4) -> 42.696875
B40: 700 | C40: 27 1/2 | D40: 16.7875 | E40: 16.7875 | F40: 16.7875 | G40: 17.075 | H40: 17.6375 | I40: 18.2 | J40: 19.6125 | K40: 21.025 | L40: 22.5375 | M40: 24.15 | N40: 25.775 | O40: 26.9375 | P40: 28.1 | Q40: 29.2625 | R40: 30.425 | S40: 31.5875 | T40: 32.575 | U40: 33.5625 | V40: 34.625 | W40: 35.75 | X40: 36.875 | Y40: 38.4375 | Z40: 40.0125 | AA40: 41.3625 | AB40: 42.4875 | AC40: 43.625 | AD40: 44.9875 | AE40: 46.35 | AF40: 47.6 | AG40: 48.725 | AH40: 49.8625 | AI40: 50.7625 | AJ40: 51.6625 | AK40: 52.9 | AL40: 54.4625 | AM40: 56.025 | AN40: 57.375 | AO40: 58.725 | AP40: 59.9625 | AQ40: 61.075 | AR40: 62.2 | AS40: 63.3125 | AT40: 64.425 | AU40: 65.5375 | AV40: 66.65 | AW40: 67.7625 | AZ40: 700 | BA40: 27 1/2 | BB40: =D40*(1-$BA$4) -> 10.911875 | BC40: =E40*(1-$BA$4) -> 10.911875 | BD40: =F40*(1-$BA$4) -> 10.911875 | BE40: =G40*(1-$BA$4) -> 11.09875 | BF40: =H40*(1-$BA$4) -> 11.464375 | BG40: =I40*(1-$BA$4) -> 11.83 | BH40: =J40*(1-$BA$4) -> 12.748125 | BI40: =K40*(1-$BA$4) -> 13.66625 | ... CU40: =AW40*(1-$BA$4) -> 44.045625
B41: 800 | C41: 31 1/2 | D41: 16.7875 | E41: 16.7875 | F41: 16.7875 | G41: 17.1625 | H41: 17.9 | I41: 18.6375 | J41: 20.0875 | K41: 21.5375 | L41: 23.1 | M41: 24.7875 | N41: 26.4625 | O41: 27.6625 | P41: 28.8625 | Q41: 30.0625 | R41: 31.275 | S41: 32.475 | T41: 33.4875 | U41: 34.5 | V41: 35.5875 | W41: 36.75 | X41: 37.9125 | Y41: 39.5375 | Z41: 41.175 | AA41: 42.575 | AB41: 43.7375 | AC41: 44.9 | AD41: 46.3 | AE41: 47.7125 | AF41: 49 | AG41: 50.1625 | AH41: 51.325 | AI41: 52.2625 | AJ41: 53.2 | AK41: 54.4875 | AL41: 56.1 | AM41: 57.725 | AN41: 59.1125 | AO41: 60.5 | AP41: 61.7625 | AQ41: 62.925 | AR41: 64.075 | AS41: 65.225 | AT41: 66.3875 | AU41: 67.5375 | AV41: 68.6875 | AW41: 69.8375 | AZ41: 800 | BA41: 31 1/2 | BB41: =D41*(1-$BA$4) -> 10.911875 | BC41: =E41*(1-$BA$4) -> 10.911875 | BD41: =F41*(1-$BA$4) -> 10.911875 | BE41: =G41*(1-$BA$4) -> 11.155625 | BF41: =H41*(1-$BA$4) -> 11.635 | BG41: =I41*(1-$BA$4) -> 12.114375 | BH41: =J41*(1-$BA$4) -> 13.056875 | BI41: =K41*(1-$BA$4) -> 13.999375 | ... CU41: =AW41*(1-$BA$4) -> 45.394375
B42: 900 | C42: 35 3/8 | D42: 16.7875 | E42: 16.7 | F42: 16.6 | G42: 17.0625 | H42: 18.075 | I42: 19.0875 | J42: 20.575 | K42: 22.0625 | L42: 23.675 | M42: 25.4125 | N42: 27.15 | O42: 28.3875 | P42: 29.625 | Q42: 30.8625 | R42: 32.1125 | S42: 33.35 | T42: 34.3875 | U42: 35.4375 | V42: 36.5625 | W42: 37.7625 | X42: 38.975 | Y42: 40.65 | Z42: 42.3375 | AA42: 43.7875 | AB42: 44.9875 | AC42: 46.1875 | AD42: 47.6375 | AE42: 49.075 | AF42: 50.4 | AG42: 51.6 | AH42: 52.8 | AI42: 53.775 | AJ42: 54.75 | AK42: 56.0625 | AL42: 57.7375 | AM42: 59.4125 | AN42: 60.8375 | AO42: 62.275 | AP42: 63.5875 | AQ42: 64.775 | AR42: 65.975 | AS42: 67.1625 | AT42: 68.35 | AU42: 69.525 | AV42: 70.7125 | AW42: 71.9 | AZ42: 900 | BA42: 35 3/8 | BB42: =D42*(1-$BA$4) -> 10.911875 | BC42: =E42*(1-$BA$4) -> 10.855 | BD42: =F42*(1-$BA$4) -> 10.79 | BE42: =G42*(1-$BA$4) -> 11.090625 | BF42: =H42*(1-$BA$4) -> 11.74875 | BG42: =I42*(1-$BA$4) -> 12.406875 | BH42: =J42*(1-$BA$4) -> 13.37375 | BI42: =K42*(1-$BA$4) -> 14.340625 | ... CU42: =AW42*(1-$BA$4) -> 46.735
B43: 1000 | C43: 39 3/8 | D43: 16.7875 | E43: 16.6 | F43: 16.4125 | G43: 16.9625 | H43: 18.25 | I43: 19.5375 | J43: 21.0625 | K43: 22.5875 | L43: 24.25 | M43: 26.0375 | N43: 27.825 | O43: 29.1 | P43: 30.3875 | Q43: 31.6625 | R43: 32.95 | S43: 34.225 | T43: 35.3 | U43: 36.375 | V43: 37.5375 | W43: 38.775 | X43: 40.025 | Y43: 41.7625 | Z43: 43.5 | AA43: 45 | AB43: 46.2375 | AC43: 47.475 | AD43: 48.9625 | AE43: 50.45 | AF43: 51.8 | AG43: 53.0375 | AH43: 54.275 | AI43: 55.275 | AJ43: 56.2875 | AK43: 57.65 | AL43: 59.375 | AM43: 61.1 | AN43: 62.575 | AO43: 64.05 | AP43: 65.4 | AQ43: 66.6375 | AR43: 67.8625 | AS43: 69.0875 | AT43: 70.3 | AU43: 71.525 | AV43: 72.7375 | AW43: 73.9625 | AZ43: 1000 | BA43: 39 3/8 | BB43: =D43*(1-$BA$4) -> 10.911875 | BC43: =E43*(1-$BA$4) -> 10.79 | BD43: =F43*(1-$BA$4) -> 10.668125 | BE43: =G43*(1-$BA$4) -> 11.025625 | BF43: =H43*(1-$BA$4) -> 11.8625 | BG43: =I43*(1-$BA$4) -> 12.699375 | BH43: =J43*(1-$BA$4) -> 13.690625 | BI43: =K43*(1-$BA$4) -> 14.681875 | ... CU43: =AW43*(1-$BA$4) -> 48.075625
B44: 1100 | C44: 43 1/4 | D44: 16.7875 | E44: 16.7375 | F44: 16.6875 | G44: 17.325 | H44: 18.65 | I44: 19.975 | J44: 21.5375 | K44: 23.1 | L44: 24.8125 | M44: 26.6625 | N44: 28.525 | O44: 29.8375 | P44: 31.15 | Q44: 32.475 | R44: 33.8 | S44: 35.125 | T44: 36.2125 | U44: 37.3125 | V44: 38.5 | W44: 39.7875 | X44: 41.0625 | Y44: 42.8625 | Z44: 44.6625 | AA44: 46.2 | AB44: 47.475 | AC44: 48.7625 | AD44: 50.275 | AE44: 51.8 | AF44: 53.2 | AG44: 54.475 | AH44: 55.7625 | AI44: 56.7875 | AJ44: 57.825 | AK44: 59.2375 | AL44: 61.0125 | AM44: 62.8 | AN44: 64.3125 | AO44: 65.8125 | AP44: 67.2 | AQ44: 68.4625 | AR44: 69.7375 | AS44: 71 | AT44: 72.2625 | AU44: 73.525 | AV44: 74.7875 | AW44: 76.05 | AZ44: 1100 | BA44: 43 1/4 | BB44: =D44*(1-$BA$4) -> 10.911875 | BC44: =E44*(1-$BA$4) -> 10.879375 | BD44: =F44*(1-$BA$4) -> 10.846875 | BE44: =G44*(1-$BA$4) -> 11.26125 | BF44: =H44*(1-$BA$4) -> 12.1225 | BG44: =I44*(1-$BA$4) -> 12.98375 | BH44: =J44*(1-$BA$4) -> 13.999375 | BI44: =K44*(1-$BA$4) -> 15.015 | ... CU44: =AW44*(1-$BA$4) -> 49.4325
B45: 1200 | C45: 47 1/4 | D45: 16.7875 | E45: 16.875 | F45: 16.9625 | G45: 17.675 | H45: 19.0375 | I45: 20.4 | J45: 22.0125 | K45: 23.625 | L45: 25.3875 | M45: 27.3 | N45: 29.2125 | O45: 30.5625 | P45: 31.925 | Q45: 33.2875 | R45: 34.65 | S45: 36.0125 | T45: 37.1375 | U45: 38.25 | V45: 39.475 | W45: 40.7875 | X45: 42.1 | Y45: 43.9625 | Z45: 45.825 | AA45: 47.4125 | AB45: 48.725 | AC45: 50.0375 | AD45: 51.6 | AE45: 53.1625 | AF45: 54.6 | AG45: 55.9125 | AH45: 57.2375 | AI45: 58.3 | AJ45: 59.3625 | AK45: 60.825 | AL45: 62.6625 | AM45: 64.5 | AN45: 66.0375 | AO45: 67.575 | AP45: 69 | AQ45: 70.3 | AR45: 71.6 | AS45: 72.9 | AT45: 74.2125 | AU45: 75.5125 | AV45: 76.825 | AW45: 78.125 | AZ45: 1200 | BA45: 47 1/4 | BB45: =D45*(1-$BA$4) -> 10.911875 | BC45: =E45*(1-$BA$4) -> 10.96875 | BD45: =F45*(1-$BA$4) -> 11.025625 | BE45: =G45*(1-$BA$4) -> 11.48875 | BF45: =H45*(1-$BA$4) -> 12.374375 | BG45: =I45*(1-$BA$4) -> 13.26 | BH45: =J45*(1-$BA$4) -> 14.308125 | BI45: =K45*(1-$BA$4) -> 15.35625 | ... CU45: =AW45*(1-$BA$4) -> 50.78125
B46: 1300 | C46: 51 1/8 | D46: 16.8875 | E46: 17.15 | F46: 17.425 | G46: 18.25 | H46: 19.65 | I46: 21.05 | J46: 22.7 | K46: 24.35 | L46: 26.15 | M46: 28.125 | N46: 30.1 | O46: 31.5 | P46: 32.8875 | Q46: 34.2875 | R46: 35.7 | S46: 37.1 | T46: 38.25 | U46: 39.4 | V46: 40.65 | W46: 42 | X46: 43.35 | Y46: 45.2625 | Z46: 47.1875 | AA46: 48.825 | AB46: 50.175 | AC46: 51.5375 | AD46: 53.125 | AE46: 54.725 | AF46: 56.2 | AG46: 57.55 | AH46: 58.9125 | AI46: 60 | AJ46: 61.1 | AK46: 62.6 | AL46: 64.5 | AM46: 66.4 | AN46: 67.975 | AO46: 69.55 | AP46: 71.0125 | AQ46: 72.35 | AR46: 73.6875 | AS46: 75.025 | AT46: 76.375 | AU46: 77.7125 | AV46: 79.05 | AW46: 80.4 | AZ46: 1300 | BA46: 51 1/8 | BB46: =D46*(1-$BA$4) -> 10.976875 | BC46: =E46*(1-$BA$4) -> 11.1475 | BD46: =F46*(1-$BA$4) -> 11.32625 | BE46: =G46*(1-$BA$4) -> 11.8625 | BF46: =H46*(1-$BA$4) -> 12.7725 | BG46: =I46*(1-$BA$4) -> 13.6825 | BH46: =J46*(1-$BA$4) -> 14.755 | BI46: =K46*(1-$BA$4) -> 15.8275 | ... CU46: =AW46*(1-$BA$4) -> 52.26
B47: 1400 | C47: 55 1/8 | D47: 16.9875 | E47: 17.4375 | F47: 17.8875 | G47: 18.825 | H47: 20.2625 | I47: 21.7 | J47: 23.3875 | K47: 25.075 | L47: 26.925 | M47: 28.9625 | N47: 30.9875 | O47: 32.425 | P47: 33.8625 | Q47: 35.3 | R47: 36.7375 | S47: 38.1875 | T47: 39.3625 | U47: 40.5375 | V47: 41.825 | W47: 43.2125 | X47: 44.6 | Y47: 46.575 | Z47: 48.55 | AA47: 50.2375 | AB47: 51.625 | AC47: 53.025 | AD47: 54.65 | AE47: 56.2875 | AF47: 57.8 | AG47: 59.1875 | AH47: 60.575 | AI47: 61.7 | AJ47: 62.8375 | AK47: 64.375 | AL47: 66.3375 | AM47: 68.2875 | AN47: 69.9 | AO47: 71.5125 | AP47: 73.0125 | AQ47: 74.4 | AR47: 75.775 | AS47: 77.15 | AT47: 78.5375 | AU47: 79.9125 | AV47: 81.2875 | AW47: 82.6625 | AZ47: 1400 | BA47: 55 1/8 | BB47: =D47*(1-$BA$4) -> 11.041875 | BC47: =E47*(1-$BA$4) -> 11.334375 | BD47: =F47*(1-$BA$4) -> 11.626875 | BE47: =G47*(1-$BA$4) -> 12.23625 | BF47: =H47*(1-$BA$4) -> 13.170625 | BG47: =I47*(1-$BA$4) -> 14.105 | BH47: =J47*(1-$BA$4) -> 15.201875 | BI47: =K47*(1-$BA$4) -> 16.29875 | ... CU47: =AW47*(1-$BA$4) -> 53.730625
B48: 1500 | C48: 59 | D48: 16.9875 | E48: 17.575 | F48: 18.1625 | G48: 19.1875 | H48: 20.6625 | I48: 22.1375 | J48: 23.8625 | K48: 25.5875 | L48: 27.5 | M48: 29.5875 | N48: 31.6875 | O48: 33.1625 | P48: 34.6375 | Q48: 36.1125 | R48: 37.5875 | S48: 39.075 | T48: 40.275 | U48: 41.475 | V48: 42.7875 | W48: 44.225 | X48: 45.65 | Y48: 47.675 | Z48: 49.7125 | AA48: 51.4375 | AB48: 52.875 | AC48: 54.3125 | AD48: 55.975 | AE48: 57.65 | AF48: 59.2 | AG48: 60.625 | AH48: 62.0625 | AI48: 63.225 | AJ48: 64.3875 | AK48: 65.9625 | AL48: 67.975 | AM48: 69.9875 | AN48: 71.6375 | AO48: 73.2875 | AP48: 74.8125 | AQ48: 76.2375 | AR48: 77.6625 | AS48: 79.0875 | AT48: 80.5 | AU48: 81.9125 | AV48: 83.325 | AW48: 84.7375 | AZ48: 1500 | BA48: 59 | BB48: =D48*(1-$BA$4) -> 11.041875 | BC48: =E48*(1-$BA$4) -> 11.42375 | BD48: =F48*(1-$BA$4) -> 11.805625 | BE48: =G48*(1-$BA$4) -> 12.471875 | BF48: =H48*(1-$BA$4) -> 13.430625 | BG48: =I48*(1-$BA$4) -> 14.389375 | BH48: =J48*(1-$BA$4) -> 15.510625 | BI48: =K48*(1-$BA$4) -> 16.631875 | ... CU48: =AW48*(1-$BA$4) -> 55.079375
B49: 1600 | C49: 63 | D49: 16.9875 | E49: 17.7125 | F49: 18.4375 | G49: 19.55 | H49: 21.0625 | I49: 22.575 | J49: 24.35 | K49: 26.1125 | L49: 28.075 | M49: 30.225 | N49: 32.375 | O49: 33.8875 | P49: 35.4 | Q49: 36.925 | R49: 38.4375 | S49: 39.95 | T49: 41.175 | U49: 42.4125 | V49: 43.7625 | W49: 45.225 | X49: 46.7 | Y49: 48.7875 | Z49: 50.875 | AA49: 52.65 | AB49: 54.1125 | AC49: 55.5875 | AD49: 57.3 | AE49: 59.0125 | AF49: 60.6 | AG49: 62.0625 | AH49: 63.5375 | AI49: 64.7375 | AJ49: 65.925 | AK49: 67.55 | AL49: 69.6125 | AM49: 71.675 | AN49: 73.3625 | AO49: 75.05 | AP49: 76.625 | AQ49: 78.0875 | AR49: 79.55 | AS49: 81.0125 | AT49: 82.475 | AU49: 83.925 | AV49: 85.3625 | AW49: 86.8125 | AZ49: 1600 | BA49: 63 | BB49: =D49*(1-$BA$4) -> 11.041875 | BC49: =E49*(1-$BA$4) -> 11.513125 | BD49: =F49*(1-$BA$4) -> 11.984375 | BE49: =G49*(1-$BA$4) -> 12.7075 | BF49: =H49*(1-$BA$4) -> 13.690625 | BG49: =I49*(1-$BA$4) -> 14.67375 | BH49: =J49*(1-$BA$4) -> 15.8275 | BI49: =K49*(1-$BA$4) -> 16.973125 | ... CU49: =AW49*(1-$BA$4) -> 56.428125
B50: 1700 | C50: 66 7/8 | D50: 17.7 | E50: 18.1625 | F50: 18.625 | G50: 19.6125 | H50: 21.1375 | I50: 22.675 | J50: 24.45 | K50: 26.225 | L50: 28.2125 | M50: 30.3875 | N50: 32.5625 | O50: 34.0875 | P50: 35.6125 | Q50: 37.15 | R50: 38.675 | S50: 40.2125 | T50: 41.725 | U50: 43.225 | V50: 44.7375 | W50: 46.2375 | X50: 47.75 | Y50: 49.8875 | Z50: 52.025 | AA50: 53.85 | AB50: 55.3625 | AC50: 56.875 | AD50: 58.625 | AE50: 60.375 | AF50: 62 | AG50: 63.5 | AH50: 65.0125 | AI50: 66.2375 | AJ50: 67.4625 | AK50: 69.1375 | AL50: 71.25 | AM50: 73.375 | AN50: 75.1 | AO50: 76.825 | AP50: 78.4375 | AQ50: 79.9375 | AR50: 81.4375 | AS50: 82.925 | AT50: 84.425 | AU50: 85.9125 | AV50: 87.4 | AW50: 88.9 | AZ50: 1700 | BA50: 66 7/8 | BB50: =D50*(1-$BA$4) -> 11.505 | BC50: =E50*(1-$BA$4) -> 11.805625 | BD50: =F50*(1-$BA$4) -> 12.10625 | BE50: =G50*(1-$BA$4) -> 12.748125 | BF50: =H50*(1-$BA$4) -> 13.739375 | BG50: =I50*(1-$BA$4) -> 14.73875 | BH50: =J50*(1-$BA$4) -> 15.8925 | BI50: =K50*(1-$BA$4) -> 17.04625 | ... CU50: =AW50*(1-$BA$4) -> 57.785
B51: 1800 | C51: 70 7/8 | D51: 18.4125 | E51: 18.6125 | F51: 18.8 | G51: 19.675 | H51: 21.2125 | I51: 22.7625 | J51: 24.55 | K51: 26.3375 | L51: 28.3375 | M51: 30.5375 | N51: 32.7375 | O51: 34.2875 | P51: 35.825 | Q51: 37.375 | R51: 38.925 | S51: 40.475 | T51: 42.2625 | U51: 44.05 | V51: 45.7125 | W51: 47.25 | X51: 48.8 | Y51: 51 | Z51: 53.1875 | AA51: 55.0625 | AB51: 56.6125 | AC51: 58.1625 | AD51: 59.95 | AE51: 61.7375 | AF51: 63.4 | AG51: 64.9375 | AH51: 66.475 | AI51: 67.7375 | AJ51: 69 | AK51: 70.7125 | AL51: 72.8875 | AM51: 75.0625 | AN51: 76.8375 | AO51: 78.6125 | AP51: 80.2625 | AQ51: 81.7875 | AR51: 83.3125 | AS51: 84.8375 | AT51: 86.375 | AU51: 87.9 | AV51: 89.4375 | AW51: 90.975 | AZ51: 1800 | BA51: 70 7/8 | BB51: =D51*(1-$BA$4) -> 11.968125 | BC51: =E51*(1-$BA$4) -> 12.098125 | BD51: =F51*(1-$BA$4) -> 12.22 | BE51: =G51*(1-$BA$4) -> 12.78875 | BF51: =H51*(1-$BA$4) -> 13.788125 | BG51: =I51*(1-$BA$4) -> 14.795625 | BH51: =J51*(1-$BA$4) -> 15.9575 | BI51: =K51*(1-$BA$4) -> 17.119375 | ... CU51: =AW51*(1-$BA$4) -> 59.13375
B52: 1900 | C52: 74 3/4 | D52: 18.4125 | E52: 18.7375 | F52: 19.0625 | G52: 20.025 | H52: 21.6125 | I52: 23.2 | J52: 25.025 | K52: 26.85 | L52: 28.8875 | M52: 31.1375 | N52: 33.4 | O52: 34.9875 | P52: 36.5625 | Q52: 38.15 | R52: 39.7375 | S52: 41.325 | T52: 43.15 | U52: 44.975 | V52: 46.675 | W52: 48.2625 | X52: 49.85 | Y52: 52.1 | Z52: 54.35 | AA52: 56.275 | AB52: 57.8625 | AC52: 59.45 | AD52: 61.275 | AE52: 63.1 | AF52: 64.8 | AG52: 66.375 | AH52: 67.95 | AI52: 69.2375 | AJ52: 70.5375 | AK52: 72.3 | AL52: 74.5375 | AM52: 76.775 | AN52: 78.575 | AO52: 80.3875 | AP52: 82.075 | AQ52: 83.6375 | AR52: 85.2 | AS52: 86.7625 | AT52: 88.325 | AU52: 89.9 | AV52: 91.475 | AW52: 93.05 | AZ52: 1900 | BA52: 74 3/4 | BB52: =D52*(1-$BA$4) -> 11.968125 | BC52: =E52*(1-$BA$4) -> 12.179375 | BD52: =F52*(1-$BA$4) -> 12.390625 | BE52: =G52*(1-$BA$4) -> 13.01625 | BF52: =H52*(1-$BA$4) -> 14.048125 | BG52: =I52*(1-$BA$4) -> 15.08 | BH52: =J52*(1-$BA$4) -> 16.26625 | BI52: =K52*(1-$BA$4) -> 17.4525 | ... CU52: =AW52*(1-$BA$4) -> 60.4825
B53: 2000 | C53: 78 3/4 | D53: 18.4125 | E53: 18.875 | F53: 19.3375 | G53: 20.375 | H53: 22 | I53: 23.625 | J53: 25.4875 | K53: 27.35 | L53: 29.4375 | M53: 31.75 | N53: 34.0625 | O53: 35.6875 | P53: 37.3 | Q53: 38.925 | R53: 40.55 | S53: 42.175 | T53: 44.0375 | U53: 45.9 | V53: 47.6375 | W53: 49.2625 | X53: 50.8875 | Y53: 53.2 | Z53: 55.5125 | AA53: 57.475 | AB53: 59.1 | AC53: 60.725 | AD53: 62.5875 | AE53: 64.45 | AF53: 66.2 | AG53: 67.8125 | AH53: 69.425 | AI53: 70.75 | AJ53: 72.075 | AK53: 73.8875 | AL53: 76.175 | AM53: 78.475 | AN53: 80.3125 | AO53: 82.15 | AP53: 83.875 | AQ53: 85.4875 | AR53: 87.0875 | AS53: 88.6875 | AT53: 90.2875 | AU53: 91.8875 | AV53: 93.5 | AW53: 95.1125 | AZ53: 2000 | BA53: 78 3/4 | BB53: =D53*(1-$BA$4) -> 11.968125 | BC53: =E53*(1-$BA$4) -> 12.26875 | BD53: =F53*(1-$BA$4) -> 12.569375 | BE53: =G53*(1-$BA$4) -> 13.24375 | BF53: =H53*(1-$BA$4) -> 14.3 | BG53: =I53*(1-$BA$4) -> 15.35625 | BH53: =J53*(1-$BA$4) -> 16.566875 | BI53: =K53*(1-$BA$4) -> 17.7775 | ... CU53: =AW53*(1-$BA$4) -> 61.823125
B54: 2100 | C54: 82 5/8 | D54: 19.125 | E54: 19.6 | F54: 20.075 | G54: 21.1375 | H54: 22.8 | I54: 24.4625 | J54: 26.3625 | K54: 28.2625 | L54: 30.3875 | M54: 32.7625 | N54: 35.1375 | O54: 36.8 | P54: 38.4625 | Q54: 40.1125 | R54: 41.775 | S54: 43.4375 | T54: 45.3375 | U54: 47.2375 | V54: 49.0125 | W54: 50.675 | X54: 52.3375 | Y54: 54.7125 | Z54: 57.075 | AA54: 59.0875 | AB54: 60.75 | AC54: 62.4125 | AD54: 64.3125 | AE54: 66.2125 | AF54: 68 | AG54: 69.65 | AH54: 71.3125 | AI54: 72.6625 | AJ54: 74.0125 | AK54: 75.8625 | AL54: 78.2125 | AM54: 80.5625 | AN54: 82.4375 | AO54: 84.325 | AP54: 86.0875 | AQ54: 87.725 | AR54: 89.3625 | AS54: 91 | AT54: 92.65 | AU54: 94.2875 | AV54: 95.9375 | AW54: 97.5875 | AZ54: 2100 | BA54: 82 5/8 | BB54: =D54*(1-$BA$4) -> 12.43125 | BC54: =E54*(1-$BA$4) -> 12.74 | BD54: =F54*(1-$BA$4) -> 13.04875 | BE54: =G54*(1-$BA$4) -> 13.739375 | BF54: =H54*(1-$BA$4) -> 14.82 | BG54: =I54*(1-$BA$4) -> 15.900625 | BH54: =J54*(1-$BA$4) -> 17.135625 | BI54: =K54*(1-$BA$4) -> 18.370625 | ... CU54: =AW54*(1-$BA$4) -> 63.431875
B55: 2200 | C55: 86 5/8 | D55: 19.825 | E55: 20.3125 | F55: 20.8 | G55: 21.9 | H55: 23.5875 | I55: 25.2875 | J55: 27.225 | K55: 29.1625 | L55: 31.35 | M55: 33.775 | N55: 36.2 | O55: 37.9 | P55: 39.6125 | Q55: 41.3125 | R55: 43 | S55: 44.6875 | T55: 46.625 | U55: 48.5625 | V55: 50.3875 | W55: 52.0875 | X55: 53.7875 | Y55: 56.2125 | Z55: 58.65 | AA55: 60.7125 | AB55: 62.4 | AC55: 64.1 | AD55: 66.0375 | AE55: 67.975 | AF55: 69.8 | AG55: 71.5 | AH55: 73.2 | AI55: 74.575 | AJ55: 75.95 | AK55: 77.8375 | AL55: 80.2375 | AM55: 82.6375 | AN55: 84.5625 | AO55: 86.4875 | AP55: 88.2875 | AQ55: 89.9625 | AR55: 91.6375 | AS55: 93.325 | AT55: 95.0125 | AU55: 96.6875 | AV55: 98.375 | AW55: 100.05 | AZ55: 2200 | BA55: 86 5/8 | BB55: =D55*(1-$BA$4) -> 12.88625 | BC55: =E55*(1-$BA$4) -> 13.203125 | BD55: =F55*(1-$BA$4) -> 13.52 | BE55: =G55*(1-$BA$4) -> 14.235 | BF55: =H55*(1-$BA$4) -> 15.331875 | BG55: =I55*(1-$BA$4) -> 16.436875 | BH55: =J55*(1-$BA$4) -> 17.69625 | BI55: =K55*(1-$BA$4) -> 18.955625 | ... CU55: =AW55*(1-$BA$4) -> 65.0325
B56: 2300 | C56: 90 1/2 | D56: 19.825 | E56: 20.45 | F56: 21.0625 | G56: 22.2375 | H56: 23.975 | I56: 25.7125 | J56: 27.6875 | K56: 29.675 | L56: 31.9 | M56: 34.3875 | N56: 36.8625 | O56: 38.6 | P56: 40.35 | Q56: 42.0875 | R56: 43.8125 | S56: 45.55 | T56: 47.525 | U56: 49.5 | V56: 51.3625 | W56: 53.1 | X56: 54.8375 | Y56: 57.325 | Z56: 59.8125 | AA56: 61.925 | AB56: 63.65 | AC56: 65.3875 | AD56: 67.3625 | AE56: 69.3375 | AF56: 71.2 | AG56: 72.9375 | AH56: 74.675 | AI56: 76.075 | AJ56: 77.4875 | AK56: 79.425 | AL56: 81.875 | AM56: 84.3375 | AN56: 86.2875 | AO56: 88.25 | AP56: 90.0875 | AQ56: 91.8125 | AR56: 93.5375 | AS56: 95.25 | AT56: 96.975 | AU56: 98.7 | AV56: 100.4125 | AW56: 102.125 | AZ56: 2300 | BA56: 90 1/2 | BB56: =D56*(1-$BA$4) -> 12.88625 | BC56: =E56*(1-$BA$4) -> 13.2925 | BD56: =F56*(1-$BA$4) -> 13.690625 | BE56: =G56*(1-$BA$4) -> 14.454375 | BF56: =H56*(1-$BA$4) -> 15.58375 | BG56: =I56*(1-$BA$4) -> 16.713125 | BH56: =J56*(1-$BA$4) -> 17.996875 | BI56: =K56*(1-$BA$4) -> 19.28875 | ... CU56: =AW56*(1-$BA$4) -> 66.38125
B57: 2400 | C57: 94 1/2 | D57: 19.825 | E57: 20.575 | F57: 21.325 | G57: 22.5875 | H57: 24.3625 | I57: 26.1375 | J57: 28.1625 | K57: 30.175 | L57: 32.45 | M57: 34.9875 | N57: 37.525 | O57: 39.3 | P57: 41.0875 | Q57: 42.8625 | R57: 44.625 | S57: 46.4 | T57: 48.425 | U57: 50.4375 | V57: 52.3375 | W57: 54.1 | X57: 55.875 | Y57: 58.425 | Z57: 60.975 | AA57: 63.1375 | AB57: 64.9 | AC57: 66.6625 | AD57: 68.6875 | AE57: 70.7 | AF57: 72.6 | AG57: 74.3625 | AH57: 76.1375 | AI57: 77.5875 | AJ57: 79.025 | AK57: 81 | AL57: 83.5125 | AM57: 86.025 | AN57: 88.025 | AO57: 90.0125 | AP57: 91.9 | AQ57: 93.6625 | AR57: 95.425 | AS57: 97.1875 | AT57: 98.95 | AU57: 100.7 | AV57: 102.4375 | AW57: 104.1875 | AZ57: 2400 | BA57: 94 1/2 | BB57: =D57*(1-$BA$4) -> 12.88625 | BC57: =E57*(1-$BA$4) -> 13.37375 | BD57: =F57*(1-$BA$4) -> 13.86125 | BE57: =G57*(1-$BA$4) -> 14.681875 | BF57: =H57*(1-$BA$4) -> 15.835625 | BG57: =I57*(1-$BA$4) -> 16.989375 | BH57: =J57*(1-$BA$4) -> 18.305625 | BI57: =K57*(1-$BA$4) -> 19.61375 | ... CU57: =AW57*(1-$BA$4) -> 67.721875
B58: 2500 | C58: 98 3/8 | D58: 20.5375 | E58: 21.0875 | F58: 21.6375 | G58: 22.8125 | H58: 24.625 | I58: 26.425 | J58: 28.475 | K58: 30.525 | L58: 32.8375 | M58: 35.4125 | N58: 38 | O58: 39.8 | P58: 41.6125 | Q58: 43.4125 | R58: 45.2125 | S58: 47.0125 | T58: 49.05 | U58: 51.1 | V58: 53.025 | W58: 54.825 | X58: 56.625 | Y58: 59.2125 | Z58: 61.8 | AA58: 64 | AB58: 65.8 | AC58: 67.6 | AD58: 69.6375 | AE58: 71.6875 | AF58: 73.6125 | AG58: 75.4125 | AH58: 77.2125 | AI58: 78.85 | AJ58: 80.4875 | AK58: 82.5875 | AL58: 85.1625 | AM58: 87.7375 | AN58: 89.7625 | AO58: 91.8 | AP58: 93.7125 | AQ58: 95.5125 | AR58: 97.3125 | AS58: 99.1 | AT58: 100.9 | AU58: 102.6875 | AV58: 104.475 | AW58: 106.2625 | AZ58: 2500 | BA58: 98 3/8 | BB58: =D58*(1-$BA$4) -> 13.349375 | BC58: =E58*(1-$BA$4) -> 13.706875 | BD58: =F58*(1-$BA$4) -> 14.064375 | BE58: =G58*(1-$BA$4) -> 14.828125 | BF58: =H58*(1-$BA$4) -> 16.00625 | BG58: =I58*(1-$BA$4) -> 17.17625 | BH58: =J58*(1-$BA$4) -> 18.50875 | BI58: =K58*(1-$BA$4) -> 19.84125 | ... CU58: =AW58*(1-$BA$4) -> 69.070625
B59: 2600 | C59: 102 3/8 | D59: 21.25 | E59: 21.6 | F59: 21.95 | G59: 23.0375 | H59: 24.875 | I59: 26.7125 | J59: 28.7875 | K59: 30.8625 | L59: 33.2125 | M59: 35.85 | N59: 38.475 | O59: 40.3 | P59: 42.1375 | Q59: 43.9625 | R59: 45.7875 | S59: 47.6125 | T59: 49.6875 | U59: 51.75 | V59: 53.7 | W59: 55.5375 | X59: 57.375 | Y59: 60 | Z59: 62.6375 | AA59: 64.8625 | AB59: 66.7 | AC59: 68.525 | AD59: 70.6 | AE59: 72.675 | AF59: 74.625 | AG59: 76.45 | AH59: 78.275 | AI59: 80.1125 | AJ59: 81.95 | AK59: 84.175 | AL59: 86.8125 | AM59: 89.4375 | AN59: 91.5125 | AO59: 93.575 | AP59: 95.525 | AQ59: 97.3625 | AR59: 99.1875 | AS59: 101.0125 | AT59: 102.85 | AU59: 104.675 | AV59: 106.5125 | AW59: 108.3375 | AZ59: 2600 | BA59: 102 3/8 | BB59: =D59*(1-$BA$4) -> 13.8125 | BC59: =E59*(1-$BA$4) -> 14.04 | BD59: =F59*(1-$BA$4) -> 14.2675 | BE59: =G59*(1-$BA$4) -> 14.974375 | BF59: =H59*(1-$BA$4) -> 16.16875 | BG59: =I59*(1-$BA$4) -> 17.363125 | BH59: =J59*(1-$BA$4) -> 18.711875 | BI59: =K59*(1-$BA$4) -> 20.060625 | ... CU59: =AW59*(1-$BA$4) -> 70.419375
B60: 2700 | C60: 106 1/4 | D60: 21.25 | E60: 21.7375 | F60: 22.2125 | G60: 23.3875 | H60: 25.2625 | I60: 27.1375 | J60: 29.25 | K60: 31.3625 | L60: 33.7625 | M60: 36.45 | N60: 39.1375 | O60: 41 | P60: 42.875 | Q60: 44.7375 | R60: 46.6 | S60: 48.475 | T60: 50.575 | U60: 52.6875 | V60: 54.675 | W60: 56.55 | X60: 58.425 | Y60: 61.1 | Z60: 63.7875 | AA60: 66.0625 | AB60: 67.925 | AC60: 69.8 | AD60: 71.9125 | AE60: 74.0125 | AF60: 76 | AG60: 77.875 | AH60: 79.75 | AI60: 81.6125 | AJ60: 83.475 | AK60: 85.7625 | AL60: 88.45 | AM60: 91.1375 | AN60: 93.2375 | AO60: 95.35 | AP60: 97.3375 | AQ60: 99.2 | AR60: 101.0625 | AS60: 102.9375 | AT60: 104.8125 | AU60: 106.675 | AV60: 108.5375 | AW60: 110.4125 | AZ60: 2700 | BA60: 106 1/4 | BB60: =D60*(1-$BA$4) -> 13.8125 | BC60: =E60*(1-$BA$4) -> 14.129375 | BD60: =F60*(1-$BA$4) -> 14.438125 | BE60: =G60*(1-$BA$4) -> 15.201875 | BF60: =H60*(1-$BA$4) -> 16.420625 | BG60: =I60*(1-$BA$4) -> 17.639375 | BH60: =J60*(1-$BA$4) -> 19.0125 | BI60: =K60*(1-$BA$4) -> 20.385625 | ... CU60: =AW60*(1-$BA$4) -> 71.768125
B61: 2800 | C61: 110 1/4 | D61: 21.25 | E61: 21.8625 | F61: 22.475 | G61: 23.7375 | H61: 25.65 | I61: 27.5625 | J61: 29.7125 | K61: 31.85 | L61: 34.3 | M61: 37.05 | N61: 39.8 | O61: 41.7 | P61: 43.6125 | Q61: 45.5125 | R61: 47.425 | S61: 49.325 | T61: 51.475 | U61: 53.6125 | V61: 55.6375 | W61: 57.55 | X61: 59.4625 | Y61: 62.2 | Z61: 64.9375 | AA61: 67.25 | AB61: 69.1625 | AC61: 71.075 | AD61: 73.2125 | AE61: 75.35 | AF61: 77.3875 | AG61: 79.3 | AH61: 81.2125 | AI61: 83.1125 | AJ61: 85.0125 | AK61: 87.3375 | AL61: 90.075 | AM61: 92.825 | AN61: 94.975 | AO61: 97.1125 | AP61: 99.1375 | AQ61: 101.0375 | AR61: 102.9375 | AS61: 104.85 | AT61: 106.7625 | AU61: 108.675 | AV61: 110.575 | AW61: 112.475 | AZ61: 2800 | BA61: 110 1/4 | BB61: =D61*(1-$BA$4) -> 13.8125 | BC61: =E61*(1-$BA$4) -> 14.210625 | BD61: =F61*(1-$BA$4) -> 14.60875 | BE61: =G61*(1-$BA$4) -> 15.429375 | BF61: =H61*(1-$BA$4) -> 16.6725 | BG61: =I61*(1-$BA$4) -> 17.915625 | BH61: =J61*(1-$BA$4) -> 19.313125 | BI61: =K61*(1-$BA$4) -> 20.7025 | ... CU61: =AW61*(1-$BA$4) -> 73.10875
... B63: 3000 | C63: 118 1/8 | D63: 22.65 | E63: 22.975 | F63: 23.3 | G63: 24.45 | H63: 26.425 | I63: 28.4 | J63: 30.625 | K63: 32.85 | L63: 35.3875 | M63: 38.25 | N63: 41.1 | O63: 43.0875 | P63: 45.075 | Q63: 47.05 | R63: 49.0375 | S63: 51.025 | T63: 53.25 | U63: 55.4625 | V63: 57.5625 | W63: 59.5375 | X63: 61.5125 | Y63: 64.375 | Z63: 67.2375 | AA63: 69.65 | AB63: 71.6375 | AC63: 73.6125 | AD63: 75.8375 | AE63: 78.05 | AF63: 80.15 | AG63: 82.1375 | AH63: 84.125 | AI63: 86.1 | AJ63: 88.0875 | AK63: 90.5 | AL63: 93.3625 | AM63: 96.2125 | AN63: 98.4375 | AO63: 100.6625 | AP63: 102.7625 | AQ63: 104.75 | AR63: 106.725 | AS63: 108.7 | AT63: 110.6875 | AU63: 112.6625 | AV63: 114.65 | AW63: 116.625 | AZ63: 3000 | BA63: 118 1/8 | BB63: =D63*(1-$BA$4) -> 14.7225 | BC63: =E63*(1-$BA$4) -> 14.93375 | BD63: =F63*(1-$BA$4) -> 15.145 | BE63: =G63*(1-$BA$4) -> 15.8925 | BF63: =H63*(1-$BA$4) -> 17.17625 | BG63: =I63*(1-$BA$4) -> 18.46 | BH63: =J63*(1-$BA$4) -> 19.90625 | BI63: =K63*(1-$BA$4) -> 21.3525 | ... CU63: =AW63*(1-$BA$4) -> 75.80625
B64: 3100 | C64: 122 | D64: 22.65 | E64: 23.1125 | F64: 23.5625 | G64: 24.8 | H64: 26.8125 | I64: 28.825 | J64: 31.0875 | K64: 33.35 | L64: 35.9375 | M64: 38.85 | N64: 41.7625 | O64: 43.7875 | P64: 45.8125 | Q64: 47.8375 | R64: 49.85 | S64: 51.875 | T64: 54.125 | U64: 56.3875 | V64: 58.525 | W64: 60.5375 | X64: 62.55 | Y64: 65.4625 | Z64: 68.375 | AA64: 70.85 | AB64: 72.8625 | AC64: 74.8875 | AD64: 77.15 | AE64: 79.4125 | AF64: 81.55 | AG64: 83.5625 | AH64: 85.5875 | AI64: 87.6 | AJ64: 89.625 | AK64: 92.0875 | AL64: 95 | AM64: 97.9125 | AN64: 100.175 | AO64: 102.425 | AP64: 104.5625 | AQ64: 106.5875 | AR64: 108.6125 | AS64: 110.625 | AT64: 112.6375 | AU64: 114.6625 | AV64: 116.675 | AW64: 118.7 | AZ64: 3100 | BA64: 122 | BB64: =D64*(1-$BA$4) -> 14.7225 | BC64: =E64*(1-$BA$4) -> 15.023125 | BD64: =F64*(1-$BA$4) -> 15.315625 | BE64: =G64*(1-$BA$4) -> 16.12 | BF64: =H64*(1-$BA$4) -> 17.428125 | BG64: =I64*(1-$BA$4) -> 18.73625 | BH64: =J64*(1-$BA$4) -> 20.206875 | BI64: =K64*(1-$BA$4) -> 21.6775 | ... CU64: =AW64*(1-$BA$4) -> 77.155
B65: 3200 | C65: 126 | D65: 22.65 | E65: 23.2375 | F65: 23.825 | G65: 25.15 | H65: 27.2 | I65: 29.25 | J65: 31.55 | K65: 33.85 | L65: 36.4875 | M65: 39.45 | N65: 42.4125 | O65: 44.4875 | P65: 46.55 | Q65: 48.6125 | R65: 50.675 | S65: 52.725 | T65: 55.0125 | U65: 57.3 | V65: 59.475 | W65: 61.5375 | X65: 63.5875 | Y65: 66.5625 | Z65: 69.525 | AA65: 72.0375 | AB65: 74.1 | AC65: 76.1625 | AD65: 78.4625 | AE65: 80.7625 | AF65: 82.9375 | AG65: 85 | AH65: 87.05 | AI65: 89.1 | AJ65: 91.1625 | AK65: 93.675 | AL65: 96.6375 | AM65: 99.6125 | AN65: 101.9 | AO65: 104.1875 | AP65: 106.3625 | AQ65: 108.425 | AR65: 110.4875 | AS65: 112.5375 | AT65: 114.6 | AU65: 116.65 | AV65: 118.7125 | AW65: 120.775 | AZ65: 3200 | BA65: 126 | BB65: =D65*(1-$BA$4) -> 14.7225 | BC65: =E65*(1-$BA$4) -> 15.104375 | BD65: =F65*(1-$BA$4) -> 15.48625 | BE65: =G65*(1-$BA$4) -> 16.3475 | BF65: =H65*(1-$BA$4) -> 17.68 | BG65: =I65*(1-$BA$4) -> 19.0125 | BH65: =J65*(1-$BA$4) -> 20.5075 | BI65: =K65*(1-$BA$4) -> 22.0025 | ... CU65: =AW65*(1-$BA$4) -> 78.50375
B68: B | C68: mm | D68: 500 | E68: 600 | F68: 700 | G68: 800 | H68: 900 | I68: 1000 | J68: 1100 | K68: 1200 | L68: 1300 | M68: 1400 | N68: 1500 | O68: 1600 | P68: 1700 | Q68: 1800 | R68: 1900 | S68: 2000 | T68: 2100 | U68: 2200 | V68: 2300 | W68: 2400 | X68: 2500 | Y68: 2600 | Z68: 2700 | AA68: 2800 | AB68: 2900 | AC68: 3000 | AD68: 3100 | AE68: 3200 | AF68: 3300 | AG68: 3400 | AH68: 3500 | AI68: 3600 | AJ68: 3700 | AK68: 3800 | AL68: 3900 | AM68: 4000 | AN68: 4100 | AO68: 4200 | AP68: 4300 | AQ68: 4400 | AR68: 4500 | AS68: 4600 | AT68: 4700 | AU68: 4800 | AV68: 4900 | AW68: 5000 | AZ68: B | BA68: mm | BB68: 500 | BC68: 600 | BD68: 700 | BE68: 800 | BF68: 900 | BG68: 1000 | BH68: 1100 | BI68: 1200 | BJ68: 1300 | BK68: 1400 | BL68: 1500 | BM68: 1600 | BN68: 1700 | BO68: 1800 | BP68: 1900 | BQ68: 2000 | BR68: 2100 | BS68: 2200 | BT68: 2300 | BU68: 2400 | BV68: 2500 | BW68: 2600 | BX68: 2700 | BY68: 2800 | BZ68: 2900 | CA68: 3000 | CB68: 3100 | CC68: 3200 | CD68: 3300 | CE68: 3400 | CF68: 3500 | CG68: 3600 | CH68: 3700 | CI68: 3800 | CJ68: 3900 | CK68: 4000 | CL68: 4100 | CM68: 4200 | CN68: 4300 | CO68: 4400 | CP68: 4500 | CQ68: 4600 | CR68: 4700 | CS68: 4800 | CT68: 4900 | CU68: 5000
B69: mm | C69: inch | D69: 19 5/8 | E69: 23 5/8 | F69: 27 1/2 | G69: 31 1/2 | H69: 35 3/8 | I69: 39 3/8 | J69: 43 1/4 | K69: 47 1/4 | L69: 51 1/8 | M69: 55 1/8 | N69: 59 | O69: 63 | P69: 66 7/8 | Q69: 70 7/8 | R69: 74 3/4 | S69: 78 3/4 | T69: 82 5/8 | U69: 86 5/8 | V69: 90 1/2 | W69: 94 1/2 | X69: 98 3/8 | Y69: 102 3/8 | Z69: 106 1/4 | AA69: 110 1/4 | AB69: 114 1/8 | AC69: 118 1/8 | AD69: 122 | AE69: 126 | AF69: 129 7/8 | AG69: 133 7/8 | AH69: 137 3/4 | AI69: 141 3/4 | AJ69: 145 5/8 | AK69: 149 5/8 | AL69: 153 1/2 | AM69: 157 1/2 | AN69: 161 3/8 | AO69: 165 3/8 | AP69: 169 1/4 | AQ69: 173 1/4 | AR69: 177 1/8 | AS69: 181 1/8 | AT69: 185 | AU69: 189 | AV69: 192 7/8 | AW69: 196 7/8 | AZ69: mm | BA69: inch | BB69: 19 5/8 | BC69: 23 5/8 | BD69: 27 1/2 | BE69: 31 1/2 | BF69: 35 3/8 | BG69: 39 3/8 | BH69: 43 1/4 | BI69: 47 1/4 | BJ69: 51 1/8 | BK69: 55 1/8 | BL69: 59 | BM69: 63 | BN69: 66 7/8 | BO69: 70 7/8 | BP69: 74 3/4 | BQ69: 78 3/4 | BR69: 82 5/8 | BS69: 86 5/8 | BT69: 90 1/2 | BU69: 94 1/2 | BV69: 98 3/8 | BW69: 102 3/8 | BX69: 106 1/4 | BY69: 110 1/4 | BZ69: 114 1/8 | CA69: 118 1/8 | CB69: 122 | CC69: 126 | CD69: 129 7/8 | CE69: 133 7/8 | CF69: 137 3/4 | CG69: 141 3/4 | CH69: 145 5/8 | CI69: 149 5/8 | CJ69: 153 1/2 | CK69: 157 1/2 | CL69: 161 3/8 | CM69: 165 3/8 | CN69: 169 1/4 | CO69: 173 1/4 | CP69: 177 1/8 | CQ69: 181 1/8 | CR69: 185 | CS69: 189 | CT69: 192 7/8 | CU69: 196 7/8
B70: 600 | C70: 23 5/8 | D70: 19.3875 | E70: 19.3875 | F70: 19.3875 | G70: 19.7125 | H70: 20.35 | I70: 21 | J70: 21.925 | K70: 22.8375 | L70: 24.2 | M70: 25.9875 | N70: 27.775 | O70: 29.0625 | P70: 30.35 | Q70: 31.625 | R70: 32.9 | S70: 34.175 | T70: 35.7 | U70: 37.225 | V70: 38.625 | W70: 39.8875 | X70: 41.1625 | Y70: 42.95 | Z70: 44.7375 | AA70: 46.2625 | AB70: 47.55 | AC70: 48.825 | AD70: 50.35 | AE70: 51.8625 | AF70: 53.2625 | AG70: 54.55 | AH70: 55.825 | AI70: 57.1 | AJ70: 58.3875 | AK70: 59.925 | AL70: 61.7125 | AM70: 63.5 | AN70: 65.025 | AO70: 66.55 | AP70: 67.95 | AQ70: 69.225 | AR70: 70.5 | AS70: 71.775 | AT70: 73.0375 | AU70: 74.3125 | AV70: 75.6 | AW70: 76.875 | AZ70: 600 | BA70: 23 5/8 | BB70: =D70*(1-$BA$4) -> 12.601875 | BC70: =E70*(1-$BA$4) -> 12.601875 | BD70: =F70*(1-$BA$4) -> 12.601875 | BE70: =G70*(1-$BA$4) -> 12.813125 | BF70: =H70*(1-$BA$4) -> 13.2275 | BG70: =I70*(1-$BA$4) -> 13.65 | BH70: =J70*(1-$BA$4) -> 14.25125 | BI70: =K70*(1-$BA$4) -> 14.844375 | ... CU70: =AW70*(1-$BA$4) -> 49.96875
B71: 700 | C71: 27 1/2 | D71: 19.3875 | E71: 19.3875 | F71: 19.3875 | G71: 19.85 | H71: 20.7625 | I71: 21.6875 | J71: 22.6625 | K71: 23.65 | L71: 25.0875 | M71: 26.9625 | N71: 28.85 | O71: 30.1875 | P71: 31.525 | Q71: 32.8625 | R71: 34.2 | S71: 35.5375 | T71: 37.1125 | U71: 38.7 | V71: 40.1625 | W71: 41.4875 | X71: 42.825 | Y71: 44.7 | Z71: 46.5875 | AA71: 48.2 | AB71: 49.5375 | AC71: 50.875 | AD71: 52.45 | AE71: 54.0375 | AF71: 55.5 | AG71: 56.8375 | AH71: 58.175 | AI71: 59.5125 | AJ71: 60.85 | AK71: 62.4625 | AL71: 64.3375 | AM71: 66.225 | AN71: 67.8125 | AO71: 69.3875 | AP71: 70.85 | AQ71: 72.1875 | AR71: 73.525 | AS71: 74.8625 | AT71: 76.1875 | AU71: 77.525 | AV71: 78.8625 | AW71: 80.2 | AZ71: 700 | BA71: 27 1/2 | BB71: =D71*(1-$BA$4) -> 12.601875 | BC71: =E71*(1-$BA$4) -> 12.601875 | BD71: =F71*(1-$BA$4) -> 12.601875 | BE71: =G71*(1-$BA$4) -> 12.9025 | BF71: =H71*(1-$BA$4) -> 13.495625 | BG71: =I71*(1-$BA$4) -> 14.096875 | BH71: =J71*(1-$BA$4) -> 14.730625 | BI71: =K71*(1-$BA$4) -> 15.3725 | ... CU71: =AW71*(1-$BA$4) -> 52.13
B72: 800 | C72: 31 1/2 | D72: 19.3875 | E72: 19.3875 | F72: 19.3875 | G72: 19.9875 | H72: 21.175 | I72: 22.3625 | J72: 23.4125 | K72: 24.4625 | L72: 25.975 | M72: 27.95 | N72: 29.925 | O72: 31.325 | P72: 32.7125 | Q72: 34.1125 | R72: 35.5 | S72: 36.8875 | T72: 38.5375 | U72: 40.175 | V72: 41.7 | W72: 43.0875 | X72: 44.4875 | Y72: 46.4625 | Z72: 48.4375 | AA72: 50.125 | AB72: 51.5125 | AC72: 52.9125 | AD72: 54.5625 | AE72: 56.2125 | AF72: 57.7375 | AG72: 59.125 | AH72: 60.525 | AI72: 61.925 | AJ72: 63.3125 | AK72: 65 | AL72: 66.975 | AM72: 68.95 | AN72: 70.5875 | AO72: 72.225 | AP72: 73.75 | AQ72: 75.15 | AR72: 76.55 | AS72: 77.95 | AT72: 79.3375 | AU72: 80.7375 | AV72: 82.125 | AW72: 83.525 | AZ72: 800 | BA72: 31 1/2 | BB72: =D72*(1-$BA$4) -> 12.601875 | BC72: =E72*(1-$BA$4) -> 12.601875 | BD72: =F72*(1-$BA$4) -> 12.601875 | BE72: =G72*(1-$BA$4) -> 12.991875 | BF72: =H72*(1-$BA$4) -> 13.76375 | BG72: =I72*(1-$BA$4) -> 14.535625 | BH72: =J72*(1-$BA$4) -> 15.218125 | BI72: =K72*(1-$BA$4) -> 15.900625 | ... CU72: =AW72*(1-$BA$4) -> 54.29125
B73: 900 | C73: 35 3/8 | D73: 19.3875 | E73: 19.3875 | F73: 19.3875 | G73: 19.9875 | H73: 21.175 | I73: 22.375 | J73: 23.75 | K73: 25.125 | L73: 26.85 | M73: 28.9125 | N73: 30.975 | O73: 32.4375 | P73: 33.8875 | Q73: 35.35 | R73: 36.8 | S73: 38.25 | T73: 39.9625 | U73: 41.6625 | V73: 43.25 | W73: 44.7 | X73: 46.1625 | Y73: 48.225 | Z73: 50.2875 | AA73: 52.05 | AB73: 53.5 | AC73: 54.9625 | AD73: 56.675 | AE73: 58.3875 | AF73: 59.9625 | AG73: 61.4125 | AH73: 62.875 | AI73: 64.325 | AJ73: 65.7875 | AK73: 67.55 | AL73: 69.6125 | AM73: 71.675 | AN73: 73.375 | AO73: 75.075 | AP73: 76.6625 | AQ73: 78.125 | AR73: 79.5875 | AS73: 81.0375 | AT73: 82.4875 | AU73: 83.95 | AV73: 85.4 | AW73: 86.8625 | AZ73: 900 | BA73: 35 3/8 | BB73: =D73*(1-$BA$4) -> 12.601875 | BC73: =E73*(1-$BA$4) -> 12.601875 | BD73: =F73*(1-$BA$4) -> 12.601875 | BE73: =G73*(1-$BA$4) -> 12.991875 | BF73: =H73*(1-$BA$4) -> 13.76375 | BG73: =I73*(1-$BA$4) -> 14.54375 | BH73: =J73*(1-$BA$4) -> 15.4375 | BI73: =K73*(1-$BA$4) -> 16.33125 | ... CU73: =AW73*(1-$BA$4) -> 56.460625
B74: 1000 | C74: 39 3/8 | D74: 19.3875 | E74: 19.3875 | F74: 19.3875 | G74: 19.9875 | H74: 21.175 | I74: 22.375 | J74: 24.0875 | K74: 25.8 | L74: 27.725 | M74: 29.875 | N74: 32.025 | O74: 33.55 | P74: 35.0625 | Q74: 36.5875 | R74: 38.1 | S74: 39.6125 | T74: 41.3875 | U74: 43.15 | V74: 44.8 | W74: 46.3125 | X74: 47.8375 | Y74: 49.9875 | Z74: 52.1375 | AA74: 53.975 | AB74: 55.4875 | AC74: 57.0125 | AD74: 58.7875 | AE74: 60.55 | AF74: 62.1875 | AG74: 63.7 | AH74: 65.2125 | AI74: 66.7375 | AJ74: 68.25 | AK74: 70.0875 | AL74: 72.2375 | AM74: 74.3875 | AN74: 76.1625 | AO74: 77.925 | AP74: 79.575 | AQ74: 81.0875 | AR74: 82.6125 | AS74: 84.125 | AT74: 85.6375 | AU74: 87.1625 | AV74: 88.675 | AW74: 90.1875 | AZ74: 1000 | BA74: 39 3/8 | BB74: =D74*(1-$BA$4) -> 12.601875 | BC74: =E74*(1-$BA$4) -> 12.601875 | BD74: =F74*(1-$BA$4) -> 12.601875 | BE74: =G74*(1-$BA$4) -> 12.991875 | BF74: =H74*(1-$BA$4) -> 13.76375 | BG74: =I74*(1-$BA$4) -> 14.54375 | BH74: =J74*(1-$BA$4) -> 15.656875 | BI74: =K74*(1-$BA$4) -> 16.77 | ... CU74: =AW74*(1-$BA$4) -> 58.621875
B75: 1100 | C75: 43 1/4 | D75: 19.3875 | E75: 19.8375 | F75: 20.2875 | G75: 21 | H75: 21.9875 | I75: 22.9875 | J75: 24.7875 | K75: 26.5875 | L75: 28.6125 | M75: 30.85 | N75: 33.0875 | O75: 34.675 | P75: 36.25 | Q75: 37.8375 | R75: 39.4125 | S75: 40.9875 | T75: 42.8125 | U75: 44.6375 | V75: 46.3375 | W75: 47.925 | X75: 49.5125 | Y75: 51.75 | Z75: 53.9875 | AA75: 55.9 | AB75: 57.475 | AC75: 59.0625 | AD75: 60.8875 | AE75: 62.7125 | AF75: 64.4125 | AG75: 65.9875 | AH75: 67.5625 | AI75: 69.1375 | AJ75: 70.725 | AK75: 72.6375 | AL75: 74.875 | AM75: 77.125 | AN75: 78.95 | AO75: 80.775 | AP75: 82.475 | AQ75: 84.0625 | AR75: 85.65 | AS75: 87.225 | AT75: 88.8 | AU75: 90.375 | AV75: 91.95 | AW75: 93.525 | AZ75: 1100 | BA75: 43 1/4 | BB75: =D75*(1-$BA$4) -> 12.601875 | BC75: =E75*(1-$BA$4) -> 12.894375 | BD75: =F75*(1-$BA$4) -> 13.186875 | BE75: =G75*(1-$BA$4) -> 13.65 | BF75: =H75*(1-$BA$4) -> 14.291875 | BG75: =I75*(1-$BA$4) -> 14.941875 | BH75: =J75*(1-$BA$4) -> 16.111875 | BI75: =K75*(1-$BA$4) -> 17.281875 | ... CU75: =AW75*(1-$BA$4) -> 60.79125
B76: 1200 | C76: 47 1/4 | D76: 19.3875 | E76: 20.2875 | F76: 21.175 | G76: 22.0125 | H76: 22.8 | I76: 23.5875 | J76: 25.4875 | K76: 27.375 | L76: 29.4875 | M76: 31.825 | N76: 34.15 | O76: 35.8 | P76: 37.4375 | Q76: 39.075 | R76: 40.7125 | S76: 42.35 | T76: 44.2375 | U76: 46.125 | V76: 47.8875 | W76: 49.525 | X76: 51.175 | Y76: 53.5 | Z76: 55.8375 | AA76: 57.825 | AB76: 59.4625 | AC76: 61.1125 | AD76: 62.9875 | AE76: 64.8625 | AF76: 66.625 | AG76: 68.2625 | AH76: 69.9125 | AI76: 71.55 | AJ76: 73.1875 | AK76: 75.175 | AL76: 77.5125 | AM76: 79.85 | AN76: 81.7375 | AO76: 83.625 | AP76: 85.3875 | AQ76: 87.025 | AR76: 88.675 | AS76: 90.3125 | AT76: 91.95 | AU76: 93.5875 | AV76: 95.225 | AW76: 96.8625 | AZ76: 1200 | BA76: 47 1/4 | BB76: =D76*(1-$BA$4) -> 12.601875 | BC76: =E76*(1-$BA$4) -> 13.186875 | BD76: =F76*(1-$BA$4) -> 13.76375 | BE76: =G76*(1-$BA$4) -> 14.308125 | BF76: =H76*(1-$BA$4) -> 14.82 | BG76: =I76*(1-$BA$4) -> 15.331875 | BH76: =J76*(1-$BA$4) -> 16.566875 | BI76: =K76*(1-$BA$4) -> 17.79375 | ... CU76: =AW76*(1-$BA$4) -> 62.960625
B77: 1300 | C77: 51 1/8 | D77: 19.3875 | E77: 20.2875 | F77: 21.175 | G77: 22.2 | H77: 23.3375 | I77: 24.475 | J77: 26.425 | K77: 28.3875 | L77: 30.575 | M77: 33 | N77: 35.425 | O77: 37.125 | P77: 38.825 | Q77: 40.525 | R77: 42.225 | S77: 43.9375 | T77: 45.875 | U77: 47.8125 | V77: 49.6375 | W77: 51.3375 | X77: 53.05 | Y77: 55.475 | Z77: 57.9 | AA77: 59.9625 | AB77: 61.6625 | AC77: 63.3625 | AD77: 65.3 | AE77: 67.2375 | AF77: 69.0625 | AG77: 70.775 | AH77: 72.475 | AI77: 74.175 | AJ77: 75.875 | AK77: 77.9375 | AL77: 80.3625 | AM77: 82.7875 | AN77: 84.7375 | AO77: 86.6875 | AP77: 88.5125 | AQ77: 90.2125 | AR77: 91.9125 | AS77: 93.6125 | AT77: 95.3125 | AU77: 97.0125 | AV77: 98.7125 | AW77: 100.4125 | AZ77: 1300 | BA77: 51 1/8 | BB77: =D77*(1-$BA$4) -> 12.601875 | BC77: =E77*(1-$BA$4) -> 13.186875 | BD77: =F77*(1-$BA$4) -> 13.76375 | BE77: =G77*(1-$BA$4) -> 14.43 | BF77: =H77*(1-$BA$4) -> 15.169375 | BG77: =I77*(1-$BA$4) -> 15.90875 | BH77: =J77*(1-$BA$4) -> 17.17625 | BI77: =K77*(1-$BA$4) -> 18.451875 | ... CU77: =AW77*(1-$BA$4) -> 65.268125
B78: 1400 | C78: 55 1/8 | D78: 19.3875 | E78: 20.2875 | F78: 21.175 | G78: 22.375 | H78: 23.8625 | I78: 25.3625 | J78: 27.375 | K78: 29.3875 | L78: 31.6625 | M78: 34.175 | N78: 36.6875 | O78: 38.45 | P78: 40.2125 | Q78: 41.975 | R78: 43.7375 | S78: 45.5125 | T78: 47.5125 | U78: 49.5125 | V78: 51.3875 | W78: 53.15 | X78: 54.9125 | Y78: 57.4375 | Z78: 59.95 | AA78: 62.0875 | AB78: 63.85 | AC78: 65.6125 | AD78: 67.6125 | AE78: 69.625 | AF78: 71.5125 | AG78: 73.275 | AH78: 75.0375 | AI78: 76.8 | AJ78: 78.5625 | AK78: 80.7 | AL78: 83.2125 | AM78: 85.725 | AN78: 87.7375 | AO78: 89.75 | AP78: 91.6375 | AQ78: 93.3875 | AR78: 95.1375 | AS78: 96.9 | AT78: 98.6625 | AU78: 100.425 | AV78: 102.1875 | AW78: 103.9625 | AZ78: 1400 | BA78: 55 1/8 | BB78: =D78*(1-$BA$4) -> 12.601875 | BC78: =E78*(1-$BA$4) -> 13.186875 | BD78: =F78*(1-$BA$4) -> 13.76375 | BE78: =G78*(1-$BA$4) -> 14.54375 | BF78: =H78*(1-$BA$4) -> 15.510625 | BG78: =I78*(1-$BA$4) -> 16.485625 | BH78: =J78*(1-$BA$4) -> 17.79375 | BI78: =K78*(1-$BA$4) -> 19.101875 | ... CU78: =AW78*(1-$BA$4) -> 67.575625
B79: 1500 | C79: 59 | D79: 19.3875 | E79: 20.3625 | F79: 21.3375 | G79: 22.675 | H79: 24.3625 | I79: 26.05 | J79: 28.125 | K79: 30.2 | L79: 32.5375 | M79: 35.1375 | N79: 37.75 | O79: 39.575 | P79: 41.4 | Q79: 43.225 | R79: 45.05 | S79: 46.875 | T79: 48.9375 | U79: 51 | V79: 52.9375 | W79: 54.7625 | X79: 56.5875 | Y79: 59.2 | Z79: 61.8 | AA79: 64.0125 | AB79: 65.8375 | AC79: 67.6625 | AD79: 69.725 | AE79: 71.8 | AF79: 73.7375 | AG79: 75.5625 | AH79: 77.3875 | AI79: 79.2 | AJ79: 81.025 | AK79: 83.2375 | AL79: 85.85 | AM79: 88.4625 | AN79: 90.525 | AO79: 92.6 | AP79: 94.55 | AQ79: 96.3625 | AR79: 98.175 | AS79: 100 | AT79: 101.8125 | AU79: 103.6375 | AV79: 105.4625 | AW79: 107.2875 | AZ79: 1500 | BA79: 59 | BB79: =D79*(1-$BA$4) -> 12.601875 | BC79: =E79*(1-$BA$4) -> 13.235625 | BD79: =F79*(1-$BA$4) -> 13.869375 | BE79: =G79*(1-$BA$4) -> 14.73875 | BF79: =H79*(1-$BA$4) -> 15.835625 | BG79: =I79*(1-$BA$4) -> 16.9325 | BH79: =J79*(1-$BA$4) -> 18.28125 | BI79: =K79*(1-$BA$4) -> 19.63 | ... CU79: =AW79*(1-$BA$4) -> 69.736875
B80: 1600 | C80: 63 | D80: 19.3875 | E80: 20.45 | F80: 21.5125 | G80: 22.975 | H80: 24.8625 | I80: 26.7375 | J80: 28.8625 | K80: 31 | L80: 33.4125 | M80: 36.1125 | N80: 38.8125 | O80: 40.7 | P80: 42.5875 | Q80: 44.4625 | R80: 46.35 | S80: 48.225 | T80: 50.35 | U80: 52.475 | V80: 54.4875 | W80: 56.375 | X80: 58.2625 | Y80: 60.9625 | Z80: 63.65 | AA80: 65.9375 | AB80: 67.825 | AC80: 69.7 | AD80: 71.8375 | AE80: 73.975 | AF80: 75.975 | AG80: 77.85 | AH80: 79.725 | AI80: 81.6 | AJ80: 83.4875 | AK80: 85.775 | AL80: 88.4875 | AM80: 91.1875 | AN80: 93.3125 | AO80: 95.45 | AP80: 97.45 | AQ80: 99.3375 | AR80: 101.2125 | AS80: 103.0875 | AT80: 104.975 | AU80: 106.85 | AV80: 108.725 | AW80: 110.6 | AZ80: 1600 | BA80: 63 | BB80: =D80*(1-$BA$4) -> 12.601875 | BC80: =E80*(1-$BA$4) -> 13.2925 | BD80: =F80*(1-$BA$4) -> 13.983125 | BE80: =G80*(1-$BA$4) -> 14.93375 | BF80: =H80*(1-$BA$4) -> 16.160625 | BG80: =I80*(1-$BA$4) -> 17.379375 | BH80: =J80*(1-$BA$4) -> 18.760625 | BI80: =K80*(1-$BA$4) -> 20.15 | ... CU80: =AW80*(1-$BA$4) -> 71.89
B81: 1700 | C81: 66 7/8 | D81: 19.3875 | E81: 20.6625 | F81: 21.9375 | G81: 23.5375 | H81: 25.475 | I81: 27.425 | J81: 29.6125 | K81: 31.8 | L81: 34.2875 | M81: 37.0875 | N81: 39.8875 | O81: 41.825 | P81: 43.7625 | Q81: 45.7125 | R81: 47.65 | S81: 49.5875 | T81: 51.775 | U81: 53.9625 | V81: 56.0375 | W81: 57.975 | X81: 59.925 | Y81: 62.7125 | Z81: 65.5 | AA81: 67.8625 | AB81: 69.8 | AC81: 71.75 | AD81: 73.9375 | AE81: 76.1375 | AF81: 78.2 | AG81: 80.1375 | AH81: 82.075 | AI81: 84.0125 | AJ81: 85.95 | AK81: 88.325 | AL81: 91.1125 | AM81: 93.9125 | AN81: 96.1 | AO81: 98.3 | AP81: 100.3625 | AQ81: 102.3125 | AR81: 104.25 | AS81: 106.1875 | AT81: 108.125 | AU81: 110.0625 | AV81: 112.0125 | AW81: 113.95 | AZ81: 1700 | BA81: 66 7/8 | BB81: =D81*(1-$BA$4) -> 12.601875 | BC81: =E81*(1-$BA$4) -> 13.430625 | BD81: =F81*(1-$BA$4) -> 14.259375 | BE81: =G81*(1-$BA$4) -> 15.299375 | BF81: =H81*(1-$BA$4) -> 16.55875 | BG81: =I81*(1-$BA$4) -> 17.82625 | BH81: =J81*(1-$BA$4) -> 19.248125 | BI81: =K81*(1-$BA$4) -> 20.67 | ... CU81: =AW81*(1-$BA$4) -> 74.0675
B82: 1800 | C82: 70 7/8 | D82: 19.3875 | E82: 20.875 | F82: 22.3625 | G82: 24.1 | H82: 26.1 | I82: 28.1 | J82: 30.35 | K82: 32.6 | L82: 35.175 | M82: 38.0625 | N82: 40.95 | O82: 42.95 | P82: 44.95 | Q82: 46.95 | R82: 48.9375 | S82: 50.9375 | T82: 53.2 | U82: 55.4625 | V82: 57.5875 | W82: 59.5875 | X82: 61.5875 | Y82: 64.4625 | Z82: 67.35 | AA82: 69.7875 | AB82: 71.7875 | AC82: 73.7875 | AD82: 76.05 | AE82: 78.3125 | AF82: 80.4375 | AG82: 82.425 | AH82: 84.425 | AI82: 86.425 | AJ82: 88.425 | AK82: 90.8625 | AL82: 93.75 | AM82: 96.6375 | AN82: 98.8875 | AO82: 101.15 | AP82: 103.275 | AQ82: 105.2875 | AR82: 107.2875 | AS82: 109.2875 | AT82: 111.275 | AU82: 113.275 | AV82: 115.2875 | AW82: 117.3 | AZ82: 1800 | BA82: 70 7/8 | BB82: =D82*(1-$BA$4) -> 12.601875 | BC82: =E82*(1-$BA$4) -> 13.56875 | BD82: =F82*(1-$BA$4) -> 14.535625 | BE82: =G82*(1-$BA$4) -> 15.665 | BF82: =H82*(1-$BA$4) -> 16.965 | BG82: =I82*(1-$BA$4) -> 18.265 | BH82: =J82*(1-$BA$4) -> 19.7275 | BI82: =K82*(1-$BA$4) -> 21.19 | ... CU82: =AW82*(1-$BA$4) -> 76.245
B83: 1900 | C83: 74 3/4 | D83: 20.1375 | E83: 21.5375 | F83: 22.9375 | G83: 24.6625 | H83: 26.7125 | I83: 28.775 | J83: 31.0875 | K83: 33.4 | L83: 36.05 | M83: 39.025 | N83: 42.0125 | O83: 44.0625 | P83: 46.125 | Q83: 48.1875 | R83: 50.25 | S83: 52.3125 | T83: 54.625 | U83: 56.95 | V83: 59.1375 | W83: 61.2 | X83: 63.2625 | Y83: 66.225 | Z83: 69.2 | AA83: 71.7125 | AB83: 73.7625 | AC83: 75.825 | AD83: 78.15 | AE83: 80.4625 | AF83: 82.65 | AG83: 84.7125 | AH83: 86.775 | AI83: 88.8375 | AJ83: 90.9 | AK83: 93.425 | AL83: 96.4 | AM83: 99.375 | AN83: 101.6875 | AO83: 104 | AP83: 106.1875 | AQ83: 108.25 | AR83: 110.3125 | AS83: 112.3625 | AT83: 114.425 | AU83: 116.4875 | AV83: 118.5625 | AW83: 120.6375 | AZ83: 1900 | BA83: 74 3/4 | BB83: =D83*(1-$BA$4) -> 13.089375 | BC83: =E83*(1-$BA$4) -> 13.999375 | BD83: =F83*(1-$BA$4) -> 14.909375 | BE83: =G83*(1-$BA$4) -> 16.030625 | BF83: =H83*(1-$BA$4) -> 17.363125 | BG83: =I83*(1-$BA$4) -> 18.70375 | BH83: =J83*(1-$BA$4) -> 20.206875 | BI83: =K83*(1-$BA$4) -> 21.71 | ... CU83: =AW83*(1-$BA$4) -> 78.414375
B84: 2000 | C84: 78 3/4 | D84: 20.875 | E84: 22.1875 | F84: 23.5 | G84: 25.225 | H84: 27.3375 | I84: 29.45 | J84: 31.825 | K84: 34.2 | L84: 36.925 | M84: 39.9875 | N84: 43.0625 | O84: 45.1875 | P84: 47.3 | Q84: 49.425 | R84: 51.55 | S84: 53.675 | T84: 56.05 | U84: 58.4375 | V84: 60.6875 | W84: 62.8 | X84: 64.925 | Y84: 67.9875 | Z84: 71.05 | AA84: 73.6375 | AB84: 75.75 | AC84: 77.8625 | AD84: 80.2375 | AE84: 82.625 | AF84: 84.875 | AG84: 87 | AH84: 89.125 | AI84: 91.25 | AJ84: 93.375 | AK84: 95.975 | AL84: 99.0375 | AM84: 102.1125 | AN84: 104.475 | AO84: 106.8375 | AP84: 109.0875 | AQ84: 111.2 | AR84: 113.325 | AS84: 115.45 | AT84: 117.575 | AU84: 119.7 | AV84: 121.8375 | AW84: 123.9625 | AZ84: 2000 | BA84: 78 3/4 | BB84: =D84*(1-$BA$4) -> 13.56875 | BC84: =E84*(1-$BA$4) -> 14.421875 | BD84: =F84*(1-$BA$4) -> 15.275 | BE84: =G84*(1-$BA$4) -> 16.39625 | BF84: =H84*(1-$BA$4) -> 17.769375 | BG84: =I84*(1-$BA$4) -> 19.1425 | BH84: =J84*(1-$BA$4) -> 20.68625 | BI84: =K84*(1-$BA$4) -> 22.23 | ... CU84: =AW84*(1-$BA$4) -> 80.575625
B85: 2100 | C85: 82 5/8 | D85: 20.875 | E85: 22.5625 | F85: 24.25 | G85: 26.1875 | H85: 28.375 | I85: 30.5625 | J85: 33 | K85: 35.4375 | L85: 38.225 | M85: 41.3875 | N85: 44.5375 | O85: 46.7125 | P85: 48.9 | Q85: 51.075 | R85: 53.2625 | S85: 55.45 | T85: 57.8875 | U85: 60.325 | V85: 62.6375 | W85: 64.825 | X85: 67.0125 | Y85: 70.1625 | Z85: 73.3125 | AA85: 75.975 | AB85: 78.15 | AC85: 80.3375 | AD85: 82.775 | AE85: 85.2125 | AF85: 87.525 | AG85: 89.7 | AH85: 91.8875 | AI85: 94.075 | AJ85: 96.2625 | AK85: 98.925 | AL85: 102.0875 | AM85: 105.25 | AN85: 107.675 | AO85: 110.1125 | AP85: 112.4125 | AQ85: 114.6 | AR85: 116.775 | AS85: 118.9625 | AT85: 121.15 | AU85: 123.3375 | AV85: 125.525 | AW85: 127.7125 | AZ85: 2100 | BA85: 82 5/8 | BB85: =D85*(1-$BA$4) -> 13.56875 | BC85: =E85*(1-$BA$4) -> 14.665625 | BD85: =F85*(1-$BA$4) -> 15.7625 | BE85: =G85*(1-$BA$4) -> 17.021875 | BF85: =H85*(1-$BA$4) -> 18.44375 | BG85: =I85*(1-$BA$4) -> 19.865625 | BH85: =J85*(1-$BA$4) -> 21.45 | BI85: =K85*(1-$BA$4) -> 23.034375 | ... CU85: =AW85*(1-$BA$4) -> 83.013125
B86: 2200 | C86: 86 5/8 | D86: 20.875 | E86: 22.9375 | F86: 25 | G86: 27.1625 | H86: 29.4125 | I86: 31.6625 | J86: 34.1625 | K86: 36.6625 | L86: 39.5375 | M86: 42.775 | N86: 46.0125 | O86: 48.25 | P86: 50.4875 | Q86: 52.7375 | R86: 54.975 | S86: 57.2125 | T86: 59.7125 | U86: 62.2125 | V86: 64.5875 | W86: 66.8375 | X86: 69.0875 | Y86: 72.325 | Z86: 75.5625 | AA86: 78.3125 | AB86: 80.5625 | AC86: 82.8125 | AD86: 85.3125 | AE86: 87.8 | AF86: 90.175 | AG86: 92.4125 | AH86: 94.65 | AI86: 96.9 | AJ86: 99.1375 | AK86: 101.8875 | AL86: 105.125 | AM86: 108.375 | AN86: 110.875 | AO86: 113.375 | AP86: 115.75 | AQ86: 117.9875 | AR86: 120.225 | AS86: 122.475 | AT86: 124.7125 | AU86: 126.9625 | AV86: 129.2125 | AW86: 131.4625 | AZ86: 2200 | BA86: 86 5/8 | BB86: =D86*(1-$BA$4) -> 13.56875 | BC86: =E86*(1-$BA$4) -> 14.909375 | BD86: =F86*(1-$BA$4) -> 16.25 | BE86: =G86*(1-$BA$4) -> 17.655625 | BF86: =H86*(1-$BA$4) -> 19.118125 | BG86: =I86*(1-$BA$4) -> 20.580625 | BH86: =J86*(1-$BA$4) -> 22.205625 | BI86: =K86*(1-$BA$4) -> 23.830625 | ... CU86: =AW86*(1-$BA$4) -> 85.450625
B87: 2300 | C87: 90 1/2 | D87: 21.625 | E87: 23.6125 | F87: 25.5875 | G87: 27.7375 | H87: 30.0375 | I87: 32.35 | J87: 34.9 | K87: 37.4625 | L87: 40.4125 | M87: 43.7375 | N87: 47.075 | O87: 49.375 | P87: 51.675 | Q87: 53.9875 | R87: 56.2875 | S87: 58.5875 | T87: 61.15 | U87: 63.7125 | V87: 66.1375 | W87: 68.45 | X87: 70.7625 | Y87: 74.0875 | Z87: 77.4125 | AA87: 80.2375 | AB87: 82.55 | AC87: 84.8625 | AD87: 87.4125 | AE87: 89.975 | AF87: 92.4125 | AG87: 94.7125 | AH87: 97.0125 | AI87: 99.3125 | AJ87: 101.6125 | AK87: 104.4375 | AL87: 107.7625 | AM87: 111.1 | AN87: 113.6625 | AO87: 116.225 | AP87: 118.65 | AQ87: 120.9625 | AR87: 123.2625 | AS87: 125.5625 | AT87: 127.875 | AU87: 130.175 | AV87: 132.4875 | AW87: 134.7875 | AZ87: 2300 | BA87: 90 1/2 | BB87: =D87*(1-$BA$4) -> 14.05625 | BC87: =E87*(1-$BA$4) -> 15.348125 | BD87: =F87*(1-$BA$4) -> 16.631875 | BE87: =G87*(1-$BA$4) -> 18.029375 | BF87: =H87*(1-$BA$4) -> 19.524375 | BG87: =I87*(1-$BA$4) -> 21.0275 | BH87: =J87*(1-$BA$4) -> 22.685 | BI87: =K87*(1-$BA$4) -> 24.350625 | ... CU87: =AW87*(1-$BA$4) -> 87.611875
B88: 2400 | C88: 94 1/2 | D88: 22.375 | E88: 24.275 | F88: 26.175 | G88: 28.3 | H88: 30.6625 | I88: 33.025 | J88: 35.65 | K88: 38.2625 | L88: 41.2875 | M88: 44.7 | N88: 48.125 | O88: 50.5 | P88: 52.8625 | Q88: 55.2375 | R88: 57.6 | S88: 59.9625 | T88: 62.5875 | U88: 65.2 | V88: 67.7 | W88: 70.0625 | X88: 72.425 | Y88: 75.85 | Z88: 79.2625 | AA88: 82.1625 | AB88: 84.525 | AC88: 86.9 | AD88: 89.525 | AE88: 92.15 | AF88: 94.6375 | AG88: 97 | AH88: 99.3625 | AI88: 101.725 | AJ88: 104.0875 | AK88: 106.9875 | AL88: 110.4 | AM88: 113.8125 | AN88: 116.4375 | AO88: 119.0625 | AP88: 121.5625 | AQ88: 123.925 | AR88: 126.3 | AS88: 128.6625 | AT88: 131.025 | AU88: 133.3875 | AV88: 135.75 | AW88: 138.1125 | AZ88: 2400 | BA88: 94 1/2 | BB88: =D88*(1-$BA$4) -> 14.54375 | BC88: =E88*(1-$BA$4) -> 15.77875 | BD88: =F88*(1-$BA$4) -> 17.01375 | BE88: =G88*(1-$BA$4) -> 18.395 | BF88: =H88*(1-$BA$4) -> 19.930625 | BG88: =I88*(1-$BA$4) -> 21.46625 | BH88: =J88*(1-$BA$4) -> 23.1725 | BI88: =K88*(1-$BA$4) -> 24.870625 | ... CU88: =AW88*(1-$BA$4) -> 89.773125
B89: 2500 | C89: 98 3/8 | D89: 23.125 | E89: 24.9375 | F89: 26.75 | G89: 28.8625 | H89: 31.2875 | I89: 33.7125 | J89: 36.3875 | K89: 39.0625 | L89: 42.1625 | M89: 45.6875 | N89: 49.2 | O89: 51.625 | P89: 54.05 | Q89: 56.475 | R89: 58.9 | S89: 61.325 | T89: 64 | U89: 66.675 | V89: 69.2375 | W89: 71.6625 | X89: 74.0875 | Y89: 77.6 | Z89: 81.1125 | AA89: 84.0875 | AB89: 86.5125 | AC89: 88.9375 | AD89: 91.625 | AE89: 94.3 | AF89: 96.85 | AG89: 99.275 | AH89: 101.7 | AI89: 104.125 | AJ89: 106.55 | AK89: 109.525 | AL89: 113.0375 | AM89: 116.55 | AN89: 119.2375 | AO89: 121.9125 | AP89: 124.475 | AQ89: 126.9 | AR89: 129.325 | AS89: 131.75 | AT89: 134.175 | AU89: 136.6 | AV89: 139.025 | AW89: 141.45 | AZ89: 2500 | BA89: 98 3/8 | BB89: =D89*(1-$BA$4) -> 15.03125 | BC89: =E89*(1-$BA$4) -> 16.209375 | BD89: =F89*(1-$BA$4) -> 17.3875 | BE89: =G89*(1-$BA$4) -> 18.760625 | BF89: =H89*(1-$BA$4) -> 20.336875 | BG89: =I89*(1-$BA$4) -> 21.913125 | BH89: =J89*(1-$BA$4) -> 23.651875 | BI89: =K89*(1-$BA$4) -> 25.390625 | ... CU89: =AW89*(1-$BA$4) -> 91.9425
B90: 2600 | C90: 102 3/8 | D90: 23.8625 | E90: 25.5875 | F90: 27.3125 | G90: 29.4125 | H90: 31.9 | I90: 34.3875 | J90: 37.125 | K90: 39.8625 | L90: 43.05 | M90: 46.6625 | N90: 50.275 | O90: 52.75 | P90: 55.2375 | Q90: 57.7125 | R90: 60.2 | S90: 62.675 | T90: 65.4125 | U90: 68.15 | V90: 70.775 | W90: 73.2625 | X90: 75.75 | Y90: 79.3625 | Z90: 82.975 | AA90: 86.0125 | AB90: 88.5 | AC90: 90.975 | AD90: 93.7125 | AE90: 96.45 | AF90: 99.0625 | AG90: 101.55 | AH90: 104.0375 | AI90: 106.525 | AJ90: 109.0125 | AK90: 112.0625 | AL90: 115.675 | AM90: 119.2875 | AN90: 122.025 | AO90: 124.7625 | AP90: 127.375 | AQ90: 129.8625 | AR90: 132.3375 | AS90: 134.825 | AT90: 137.3125 | AU90: 139.8 | AV90: 142.2875 | AW90: 144.7875 | AZ90: 2600 | BA90: 102 3/8 | BB90: =D90*(1-$BA$4) -> 15.510625 | BC90: =E90*(1-$BA$4) -> 16.631875 | BD90: =F90*(1-$BA$4) -> 17.753125 | BE90: =G90*(1-$BA$4) -> 19.118125 | BF90: =H90*(1-$BA$4) -> 20.735 | BG90: =I90*(1-$BA$4) -> 22.351875 | BH90: =J90*(1-$BA$4) -> 24.13125 | BI90: =K90*(1-$BA$4) -> 25.910625 | ... CU90: =AW90*(1-$BA$4) -> 94.111875
B91: 2700 | C91: 106 1/4 | D91: 24.6125 | E91: 26.25 | F91: 27.8875 | G91: 29.9875 | H91: 32.5375 | I91: 35.0875 | J91: 37.875 | K91: 40.675 | L91: 43.925 | M91: 47.625 | N91: 51.325 | O91: 53.8625 | P91: 56.4 | Q91: 58.95 | R91: 61.5 | S91: 64.05 | T91: 66.85 | U91: 69.65 | V91: 72.325 | W91: 74.875 | X91: 77.425 | Y91: 81.1125 | Z91: 84.8125 | AA91: 87.9375 | AB91: 90.475 | AC91: 93.025 | AD91: 95.825 | AE91: 98.625 | AF91: 101.3 | AG91: 103.85 | AH91: 106.4 | AI91: 108.95 | AJ91: 111.5 | AK91: 114.625 | AL91: 118.325 | AM91: 122.025 | AN91: 124.8125 | AO91: 127.6125 | AP91: 130.2875 | AQ91: 132.825 | AR91: 135.375 | AS91: 137.925 | AT91: 140.475 | AU91: 143.0125 | AV91: 145.5625 | AW91: 148.1125 | AZ91: 2700 | BA91: 106 1/4 | BB91: =D91*(1-$BA$4) -> 15.998125 | BC91: =E91*(1-$BA$4) -> 17.0625 | BD91: =F91*(1-$BA$4) -> 18.126875 | BE91: =G91*(1-$BA$4) -> 19.491875 | BF91: =H91*(1-$BA$4) -> 21.149375 | BG91: =I91*(1-$BA$4) -> 22.806875 | BH91: =J91*(1-$BA$4) -> 24.61875 | BI91: =K91*(1-$BA$4) -> 26.43875 | ... CU91: =AW91*(1-$BA$4) -> 96.273125
B92: 2800 | C92: 110 1/4 | D92: 25.35 | E92: 26.9125 | F92: 28.475 | G92: 30.55 | H92: 33.1625 | I92: 35.775 | J92: 38.625 | K92: 41.4875 | L92: 44.8 | M92: 48.5875 | N92: 52.375 | O92: 54.975 | P92: 57.575 | Q92: 60.1875 | R92: 62.8 | S92: 65.4125 | T92: 68.275 | U92: 71.1375 | V92: 73.875 | W92: 76.4875 | X92: 79.0875 | Y92: 82.875 | Z92: 86.6625 | AA92: 89.85 | AB92: 92.4625 | AC92: 95.075 | AD92: 97.9375 | AE92: 100.8 | AF92: 103.525 | AG92: 106.1375 | AH92: 108.75 | AI92: 111.3625 | AJ92: 113.975 | AK92: 117.175 | AL92: 120.9625 | AM92: 124.75 | AN92: 127.6 | AO92: 130.4625 | AP92: 133.1875 | AQ92: 135.8 | AR92: 138.4 | AS92: 141.0125 | AT92: 143.625 | AU92: 146.2375 | AV92: 148.8375 | AW92: 151.4375 | AZ92: 2800 | BA92: 110 1/4 | BB92: =D92*(1-$BA$4) -> 16.4775 | BC92: =E92*(1-$BA$4) -> 17.493125 | BD92: =F92*(1-$BA$4) -> 18.50875 | BE92: =G92*(1-$BA$4) -> 19.8575 | BF92: =H92*(1-$BA$4) -> 21.555625 | BG92: =I92*(1-$BA$4) -> 23.25375 | BH92: =J92*(1-$BA$4) -> 25.10625 | BI92: =K92*(1-$BA$4) -> 26.966875 | ... CU92: =AW92*(1-$BA$4) -> 98.434375
... B94: 3000 | C94: 118 1/8 | D94: 26.85 | E94: 28.225 | F94: 29.6125 | G94: 31.6625 | H94: 34.3875 | I94: 37.1125 | J94: 40.1 | K94: 43.0875 | L94: 46.5625 | M94: 50.525 | N94: 54.5 | O94: 57.225 | P94: 59.95 | Q94: 62.675 | R94: 65.4125 | S94: 68.1375 | T94: 71.125 | U94: 74.1125 | V94: 76.9625 | W94: 79.7 | X94: 82.425 | Y94: 86.3875 | Z94: 90.35 | AA94: 93.7 | AB94: 96.4375 | AC94: 99.1625 | AD94: 102.15 | AE94: 105.1375 | AF94: 107.9875 | AG94: 110.7125 | AH94: 113.4375 | AI94: 116.175 | AJ94: 118.9125 | AK94: 122.2625 | AL94: 126.225 | AM94: 130.2 | AN94: 133.175 | AO94: 136.1375 | AP94: 138.9875 | AQ94: 141.725 | AR94: 144.4625 | AS94: 147.2 | AT94: 149.9375 | AU94: 152.6625 | AV94: 155.3875 | AW94: 158.1125 | AZ94: 3000 | BA94: 118 1/8 | BB94: =D94*(1-$BA$4) -> 17.4525 | BC94: =E94*(1-$BA$4) -> 18.34625 | BD94: =F94*(1-$BA$4) -> 19.248125 | BE94: =G94*(1-$BA$4) -> 20.580625 | BF94: =H94*(1-$BA$4) -> 22.351875 | BG94: =I94*(1-$BA$4) -> 24.123125 | BH94: =J94*(1-$BA$4) -> 26.065 | BI94: =K94*(1-$BA$4) -> 28.006875 | ... CU94: =AW94*(1-$BA$4) -> 102.77312
B95: 3100 | C95: 122 | D95: 26.85 | E95: 28.4375 | F95: 30.025 | G95: 32.225 | H95: 35.0125 | I95: 37.8 | J95: 40.8375 | K95: 43.8875 | L95: 47.4375 | M95: 51.5 | N95: 55.5625 | O95: 58.35 | P95: 61.1375 | Q95: 63.925 | R95: 66.7125 | S95: 69.5 | T95: 72.55 | U95: 75.6 | V95: 78.5125 | W95: 81.3 | X95: 84.1 | Y95: 88.15 | Z95: 92.2 | AA95: 95.625 | AB95: 98.425 | AC95: 101.225 | AD95: 104.2625 | AE95: 107.3 | AF95: 110.2125 | AG95: 113 | AH95: 115.7875 | AI95: 118.5875 | AJ95: 121.375 | AK95: 124.8 | AL95: 128.8625 | AM95: 132.925 | AN95: 135.9625 | AO95: 139 | AP95: 141.9125 | AQ95: 144.7 | AR95: 147.5 | AS95: 150.2875 | AT95: 153.0875 | AU95: 155.875 | AV95: 158.65 | AW95: 161.4375 | AZ95: 3100 | BA95: 122 | BB95: =D95*(1-$BA$4) -> 17.4525 | BC95: =E95*(1-$BA$4) -> 18.484375 | BD95: =F95*(1-$BA$4) -> 19.51625 | BE95: =G95*(1-$BA$4) -> 20.94625 | BF95: =H95*(1-$BA$4) -> 22.758125 | BG95: =I95*(1-$BA$4) -> 24.57 | BH95: =J95*(1-$BA$4) -> 26.544375 | BI95: =K95*(1-$BA$4) -> 28.526875 | ... CU95: =AW95*(1-$BA$4) -> 104.93438
B96: 3200 | C96: 126 | D96: 26.85 | E96: 28.65 | F96: 30.45 | G96: 32.775 | H96: 35.625 | I96: 38.475 | J96: 41.575 | K96: 44.6875 | L96: 48.3125 | M96: 52.4625 | N96: 56.6125 | O96: 59.475 | P96: 62.3375 | Q96: 65.1875 | R96: 68.025 | S96: 70.8625 | T96: 73.975 | U96: 77.0875 | V96: 80.0625 | W96: 82.9125 | X96: 85.7625 | Y96: 89.9125 | Z96: 94.05 | AA96: 97.55 | AB96: 100.4125 | AC96: 103.275 | AD96: 106.375 | AE96: 109.475 | AF96: 112.45 | AG96: 115.2875 | AH96: 118.1375 | AI96: 120.9875 | AJ96: 123.85 | AK96: 127.35 | AL96: 131.5 | AM96: 135.65 | AN96: 138.75 | AO96: 141.85 | AP96: 144.825 | AQ96: 147.6875 | AR96: 150.5375 | AS96: 153.3875 | AT96: 156.2375 | AU96: 159.0875 | AV96: 161.925 | AW96: 164.7625 | AZ96: 3200 | BA96: 126 | BB96: =D96*(1-$BA$4) -> 17.4525 | BC96: =E96*(1-$BA$4) -> 18.6225 | BD96: =F96*(1-$BA$4) -> 19.7925 | BE96: =G96*(1-$BA$4) -> 21.30375 | BF96: =H96*(1-$BA$4) -> 23.15625 | BG96: =I96*(1-$BA$4) -> 25.00875 | BH96: =J96*(1-$BA$4) -> 27.02375 | BI96: =K96*(1-$BA$4) -> 29.046875 | ... CU96: =AW96*(1-$BA$4) -> 107.09562
B99: C | C99: mm | D99: 500 | E99: 600 | F99: 700 | G99: 800 | H99: 900 | I99: 1000 | J99: 1100 | K99: 1200 | L99: 1300 | M99: 1400 | N99: 1500 | O99: 1600 | P99: 1700 | Q99: 1800 | R99: 1900 | S99: 2000 | T99: 2100 | U99: 2200 | V99: 2300 | W99: 2400 | X99: 2500 | Y99: 2600 | Z99: 2700 | AA99: 2800 | AB99: 2900 | AC99: 3000 | AD99: 3100 | AE99: 3200 | AF99: 3300 | AG99: 3400 | AH99: 3500 | AI99: 3600 | AJ99: 3700 | AK99: 3800 | AL99: 3900 | AM99: 4000 | AN99: 4100 | AO99: 4200 | AP99: 4300 | AQ99: 4400 | AR99: 4500 | AS99: 4600 | AT99: 4700 | AU99: 4800 | AV99: 4900 | AW99: 5000 | AZ99: C | BA99: mm | BB99: 500 | BC99: 600 | BD99: 700 | BE99: 800 | BF99: 900 | BG99: 1000 | BH99: 1100 | BI99: 1200 | BJ99: 1300 | BK99: 1400 | BL99: 1500 | BM99: 1600 | BN99: 1700 | BO99: 1800 | BP99: 1900 | BQ99: 2000 | BR99: 2100 | BS99: 2200 | BT99: 2300 | BU99: 2400 | BV99: 2500 | BW99: 2600 | BX99: 2700 | BY99: 2800 | BZ99: 2900 | CA99: 3000 | CB99: 3100 | CC99: 3200 | CD99: 3300 | CE99: 3400 | CF99: 3500 | CG99: 3600 | CH99: 3700 | CI99: 3800 | CJ99: 3900 | CK99: 4000 | CL99: 4100 | CM99: 4200 | CN99: 4300 | CO99: 4400 | CP99: 4500 | CQ99: 4600 | CR99: 4700 | CS99: 4800 | CT99: 4900 | CU99: 5000
B100: mm | C100: inch | D100: 19 5/8 | E100: 23 5/8 | F100: 27 1/2 | G100: 31 1/2 | H100: 35 3/8 | I100: 39 3/8 | J100: 43 1/4 | K100: 47 1/4 | L100: 51 1/8 | M100: 55 1/8 | N100: 59 | O100: 63 | P100: 66 7/8 | Q100: 70 7/8 | R100: 74 3/4 | S100: 78 3/4 | T100: 82 5/8 | U100: 86 5/8 | V100: 90 1/2 | W100: 94 1/2 | X100: 98 3/8 | Y100: 102 3/8 | Z100: 106 1/4 | AA100: 110 1/4 | AB100: 114 1/8 | AC100: 118 1/8 | AD100: 122 | AE100: 126 | AF100: 129 7/8 | AG100: 133 7/8 | AH100: 137 3/4 | AI100: 141 3/4 | AJ100: 145 5/8 | AK100: 149 5/8 | AL100: 153 1/2 | AM100: 157 1/2 | AN100: 161 3/8 | AO100: 165 3/8 | AP100: 169 1/4 | AQ100: 173 1/4 | AR100: 177 1/8 | AS100: 181 1/8 | AT100: 185 | AU100: 189 | AV100: 192 7/8 | AW100: 196 7/8 | AZ100: mm | BA100: inch | BB100: 19 5/8 | BC100: 23 5/8 | BD100: 27 1/2 | BE100: 31 1/2 | BF100: 35 3/8 | BG100: 39 3/8 | BH100: 43 1/4 | BI100: 47 1/4 | BJ100: 51 1/8 | BK100: 55 1/8 | BL100: 59 | BM100: 63 | BN100: 66 7/8 | BO100: 70 7/8 | BP100: 74 3/4 | BQ100: 78 3/4 | BR100: 82 5/8 | BS100: 86 5/8 | BT100: 90 1/2 | BU100: 94 1/2 | BV100: 98 3/8 | BW100: 102 3/8 | BX100: 106 1/4 | BY100: 110 1/4 | BZ100: 114 1/8 | CA100: 118 1/8 | CB100: 122 | CC100: 126 | CD100: 129 7/8 | CE100: 133 7/8 | CF100: 137 3/4 | CG100: 141 3/4 | CH100: 145 5/8 | CI100: 149 5/8 | CJ100: 153 1/2 | CK100: 157 1/2 | CL100: 161 3/8 | CM100: 165 3/8 | CN100: 169 1/4 | CO100: 173 1/4 | CP100: 177 1/8 | CQ100: 181 1/8 | CR100: 185 | CS100: 189 | CT100: 192 7/8 | CU100: 196 7/8
B101: 600 | C101: 23 5/8 | D101: 21.1875 | E101: 21.1875 | F101: 21.1875 | G101: 21.475 | H101: 22.0375 | I101: 22.6 | J101: 22.9875 | K101: 23.375 | L101: 24.7875 | M101: 27.225 | N101: 29.6625 | O101: 30.8 | P101: 31.9375 | Q101: 32.9875 | R101: 33.95 | S101: 34.9125 | T101: 36.4625 | U101: 38.025 | V101: 39.4625 | W101: 40.8 | X101: 42.125 | Y101: 44 | Z101: 45.8875 | AA101: 47.4875 | AB101: 48.8 | AC101: 50.125 | AD101: 51.6875 | AE101: 53.25 | AF101: 54.6875 | AG101: 56.0125 | AH101: 57.3375 | AI101: 58.6625 | AJ101: 60 | AK101: 61.6 | AL101: 63.475 | AM101: 65.35 | AN101: 66.9 | AO101: 68.4625 | AP101: 69.9 | AQ101: 71.2375 | AR101: 72.5625 | AS101: 73.8875 | AT101: 75.2125 | AU101: 76.5375 | AV101: 77.8625 | AW101: 79.1875 | AZ101: 600 | BA101: 23 5/8 | BB101: =D101*(1-$BA$4) -> 13.771875 | BC101: =E101*(1-$BA$4) -> 13.771875 | BD101: =F101*(1-$BA$4) -> 13.771875 | BE101: =G101*(1-$BA$4) -> 13.95875 | BF101: =H101*(1-$BA$4) -> 14.324375 | BG101: =I101*(1-$BA$4) -> 14.69 | BH101: =J101*(1-$BA$4) -> 14.941875 | BI101: =K101*(1-$BA$4) -> 15.19375 | ... CU101: =AW101*(1-$BA$4) -> 51.471875
B102: 700 | C102: 27 1/2 | D102: 21.1875 | E102: 21.1875 | F102: 21.1875 | G102: 21.475 | H102: 22.0375 | I102: 22.6 | J102: 23.4125 | K102: 24.2375 | L102: 25.775 | M102: 28.05 | N102: 30.325 | O102: 31.6375 | P102: 32.9375 | Q102: 34.2125 | R102: 35.4375 | S102: 36.6625 | T102: 38.3 | U102: 39.9375 | V102: 41.45 | W102: 42.85 | X102: 44.25 | Y102: 46.25 | Z102: 48.25 | AA102: 49.95 | AB102: 51.35 | AC102: 52.75 | AD102: 54.375 | AE102: 56.0125 | AF102: 57.5375 | AG102: 58.9375 | AH102: 60.3375 | AI102: 61.75 | AJ102: 63.15 | AK102: 64.85 | AL102: 66.8375 | AM102: 68.8375 | AN102: 70.4625 | AO102: 72.1 | AP102: 73.625 | AQ102: 75.025 | AR102: 76.4375 | AS102: 77.8375 | AT102: 79.2375 | AU102: 80.65 | AV102: 82.05 | AW102: 83.45 | AZ102: 700 | BA102: 27 1/2 | BB102: =D102*(1-$BA$4) -> 13.771875 | BC102: =E102*(1-$BA$4) -> 13.771875 | BD102: =F102*(1-$BA$4) -> 13.771875 | BE102: =G102*(1-$BA$4) -> 13.95875 | BF102: =H102*(1-$BA$4) -> 14.324375 | BG102: =I102*(1-$BA$4) -> 14.69 | BH102: =J102*(1-$BA$4) -> 15.218125 | BI102: =K102*(1-$BA$4) -> 15.754375 | ... CU102: =AW102*(1-$BA$4) -> 54.2425
B103: 800 | C103: 31 1/2 | D103: 21.1875 | E103: 21.1875 | F103: 21.1875 | G103: 21.475 | H103: 22.0375 | I103: 22.6 | J103: 23.85 | K103: 25.0875 | L103: 26.7625 | M103: 28.875 | N103: 30.9875 | O103: 32.4625 | P103: 33.95 | Q103: 35.425 | R103: 36.9125 | S103: 38.4 | T103: 40.125 | U103: 41.8375 | V103: 43.4375 | W103: 44.9 | X103: 46.375 | Y103: 48.4875 | Z103: 50.6 | AA103: 52.4 | AB103: 53.8875 | AC103: 55.3625 | AD103: 57.075 | AE103: 58.7875 | AF103: 60.375 | AG103: 61.8625 | AH103: 63.3375 | AI103: 64.825 | AJ103: 66.3125 | AK103: 68.1 | AL103: 70.2125 | AM103: 72.3125 | AN103: 74.025 | AO103: 75.7375 | AP103: 77.3375 | AQ103: 78.825 | AR103: 80.3 | AS103: 81.7875 | AT103: 83.275 | AU103: 84.75 | AV103: 86.2375 | AW103: 87.7125 | AZ103: 800 | BA103: 31 1/2 | BB103: =D103*(1-$BA$4) -> 13.771875 | BC103: =E103*(1-$BA$4) -> 13.771875 | BD103: =F103*(1-$BA$4) -> 13.771875 | BE103: =G103*(1-$BA$4) -> 13.95875 | BF103: =H103*(1-$BA$4) -> 14.324375 | BG103: =I103*(1-$BA$4) -> 14.69 | BH103: =J103*(1-$BA$4) -> 15.5025 | BI103: =K103*(1-$BA$4) -> 16.306875 | ... CU103: =AW103*(1-$BA$4) -> 57.013125
B104: 900 | C104: 35 3/8 | D104: 21.1875 | E104: 21.1875 | F104: 21.1875 | G104: 21.6125 | H104: 22.4625 | I104: 23.3125 | J104: 24.7 | K104: 26.0875 | L104: 27.9 | M104: 30.125 | N104: 32.35 | O104: 33.9 | P104: 35.4625 | Q104: 37.025 | R104: 38.5875 | S104: 40.15 | T104: 41.9375 | U104: 43.7375 | V104: 45.4125 | W104: 46.9625 | X104: 48.5125 | Y104: 50.7375 | Z104: 52.975 | AA104: 54.8625 | AB104: 56.425 | AC104: 57.9875 | AD104: 59.775 | AE104: 61.5625 | AF104: 63.225 | AG104: 64.7875 | AH104: 66.35 | AI104: 67.9125 | AJ104: 69.4625 | AK104: 71.3625 | AL104: 73.5875 | AM104: 75.8125 | AN104: 77.6 | AO104: 79.3875 | AP104: 81.0625 | AQ104: 82.6125 | AR104: 84.175 | AS104: 85.7375 | AT104: 87.3 | AU104: 88.8625 | AV104: 90.425 | AW104: 91.9875 | AZ104: 900 | BA104: 35 3/8 | BB104: =D104*(1-$BA$4) -> 13.771875 | BC104: =E104*(1-$BA$4) -> 13.771875 | BD104: =F104*(1-$BA$4) -> 13.771875 | BE104: =G104*(1-$BA$4) -> 14.048125 | BF104: =H104*(1-$BA$4) -> 14.600625 | BG104: =I104*(1-$BA$4) -> 15.153125 | BH104: =J104*(1-$BA$4) -> 16.055 | BI104: =K104*(1-$BA$4) -> 16.956875 | ... CU104: =AW104*(1-$BA$4) -> 59.791875
B105: 1000 | C105: 39 3/8 | D105: 21.1875 | E105: 21.1875 | F105: 21.1875 | G105: 21.75 | H105: 22.8875 | I105: 24.0125 | J105: 25.55 | K105: 27.0875 | L105: 29.025 | M105: 31.3625 | N105: 33.7 | O105: 35.3375 | P105: 36.975 | Q105: 38.6125 | R105: 40.25 | S105: 41.8875 | T105: 43.7625 | U105: 45.625 | V105: 47.375 | W105: 49.0125 | X105: 50.65 | Y105: 53 | Z105: 55.3375 | AA105: 57.325 | AB105: 58.9625 | AC105: 60.6 | AD105: 62.4625 | AE105: 64.325 | AF105: 66.0875 | AG105: 67.725 | AH105: 69.3625 | AI105: 70.9875 | AJ105: 72.625 | AK105: 74.6125 | AL105: 76.95 | AM105: 79.3 | AN105: 81.1625 | AO105: 83.025 | AP105: 84.775 | AQ105: 86.4125 | AR105: 88.05 | AS105: 89.6875 | AT105: 91.325 | AU105: 92.975 | AV105: 94.6125 | AW105: 96.25 | AZ105: 1000 | BA105: 39 3/8 | BB105: =D105*(1-$BA$4) -> 13.771875 | BC105: =E105*(1-$BA$4) -> 13.771875 | BD105: =F105*(1-$BA$4) -> 13.771875 | BE105: =G105*(1-$BA$4) -> 14.1375 | BF105: =H105*(1-$BA$4) -> 14.876875 | BG105: =I105*(1-$BA$4) -> 15.608125 | BH105: =J105*(1-$BA$4) -> 16.6075 | BI105: =K105*(1-$BA$4) -> 17.606875 | ... CU105: =AW105*(1-$BA$4) -> 62.5625
B106: 1100 | C106: 43 1/4 | D106: 21.1875 | E106: 21.475 | F106: 21.75 | G106: 22.4125 | H106: 23.4375 | I106: 24.4625 | J106: 26.25 | K106: 28.025 | L106: 30.15 | M106: 32.6 | N106: 35.0625 | O106: 36.775 | P106: 38.4875 | Q106: 40.2 | R106: 41.9125 | S106: 43.625 | T106: 45.575 | U106: 47.525 | V106: 49.3625 | W106: 51.075 | X106: 52.7875 | Y106: 55.25 | Z106: 57.7125 | AA106: 59.7875 | AB106: 61.5 | AC106: 63.2125 | AD106: 65.1625 | AE106: 67.1 | AF106: 68.9375 | AG106: 70.65 | AH106: 72.3625 | AI106: 74.075 | AJ106: 75.7875 | AK106: 77.8625 | AL106: 80.325 | AM106: 82.7875 | AN106: 84.725 | AO106: 86.675 | AP106: 88.5 | AQ106: 90.2125 | AR106: 91.925 | AS106: 93.6375 | AT106: 95.35 | AU106: 97.075 | AV106: 98.7875 | AW106: 100.5125 | AZ106: 1100 | BA106: 43 1/4 | BB106: =D106*(1-$BA$4) -> 13.771875 | BC106: =E106*(1-$BA$4) -> 13.95875 | BD106: =F106*(1-$BA$4) -> 14.1375 | BE106: =G106*(1-$BA$4) -> 14.568125 | BF106: =H106*(1-$BA$4) -> 15.234375 | BG106: =I106*(1-$BA$4) -> 15.900625 | BH106: =J106*(1-$BA$4) -> 17.0625 | BI106: =K106*(1-$BA$4) -> 18.21625 | ... CU106: =AW106*(1-$BA$4) -> 65.333125
B107: 1200 | C107: 47 1/4 | D107: 21.1875 | E107: 21.75 | F107: 22.3125 | G107: 23.0625 | H107: 23.9875 | I107: 24.9125 | J107: 26.9375 | K107: 28.9625 | L107: 31.2625 | M107: 33.85 | N107: 36.425 | O107: 38.2125 | P107: 40 | Q107: 41.775 | R107: 43.5625 | S107: 45.35 | T107: 47.3875 | U107: 49.425 | V107: 51.3375 | W107: 53.125 | X107: 54.9125 | Y107: 57.4875 | Z107: 60.075 | AA107: 62.25 | AB107: 64.0375 | AC107: 65.825 | AD107: 67.85 | AE107: 69.875 | AF107: 71.7875 | AG107: 73.575 | AH107: 75.3625 | AI107: 77.15 | AJ107: 78.9375 | AK107: 81.125 | AL107: 83.7 | AM107: 86.275 | AN107: 88.3 | AO107: 90.3125 | AP107: 92.225 | AQ107: 94.0125 | AR107: 95.8 | AS107: 97.5875 | AT107: 99.375 | AU107: 101.175 | AV107: 102.9625 | AW107: 104.7625 | AZ107: 1200 | BA107: 47 1/4 | BB107: =D107*(1-$BA$4) -> 13.771875 | BC107: =E107*(1-$BA$4) -> 14.1375 | BD107: =F107*(1-$BA$4) -> 14.503125 | BE107: =G107*(1-$BA$4) -> 14.990625 | BF107: =H107*(1-$BA$4) -> 15.591875 | BG107: =I107*(1-$BA$4) -> 16.193125 | BH107: =J107*(1-$BA$4) -> 17.509375 | BI107: =K107*(1-$BA$4) -> 18.825625 | ... CU107: =AW107*(1-$BA$4) -> 68.095625
B108: 1300 | C108: 51 1/8 | D108: 21.9 | E108: 22.1 | F108: 22.3 | G108: 23.1125 | H108: 24.55 | I108: 25.9875 | J108: 28.0875 | K108: 30.1875 | L108: 32.5875 | M108: 35.275 | N108: 37.975 | O108: 39.8375 | P108: 41.7125 | Q108: 43.575 | R108: 45.4375 | S108: 47.3 | T108: 49.4 | U108: 51.5125 | V108: 53.5 | W108: 55.3625 | X108: 57.2375 | Y108: 59.925 | Z108: 62.625 | AA108: 64.9 | AB108: 66.775 | AC108: 68.6375 | AD108: 70.7375 | AE108: 72.8375 | AF108: 74.825 | AG108: 76.6875 | AH108: 78.5625 | AI108: 80.425 | AJ108: 82.3 | AK108: 84.575 | AL108: 87.2625 | AM108: 89.9625 | AN108: 92.05 | AO108: 94.15 | AP108: 96.1375 | AQ108: 98.0125 | AR108: 99.8875 | AS108: 101.75 | AT108: 103.6125 | AU108: 105.4875 | AV108: 107.35 | AW108: 109.225 | AZ108: 1300 | BA108: 51 1/8 | BB108: =D108*(1-$BA$4) -> 14.235 | BC108: =E108*(1-$BA$4) -> 14.365 | BD108: =F108*(1-$BA$4) -> 14.495 | BE108: =G108*(1-$BA$4) -> 15.023125 | BF108: =H108*(1-$BA$4) -> 15.9575 | BG108: =I108*(1-$BA$4) -> 16.891875 | BH108: =J108*(1-$BA$4) -> 18.256875 | BI108: =K108*(1-$BA$4) -> 19.621875 | ... CU108: =AW108*(1-$BA$4) -> 70.99625
B109: 1400 | C109: 55 1/8 | D109: 22.6 | E109: 22.4375 | F109: 22.275 | G109: 23.1625 | H109: 25.1 | I109: 27.05 | J109: 29.2375 | K109: 31.425 | L109: 33.9125 | M109: 36.7125 | N109: 39.5125 | O109: 41.4625 | P109: 43.425 | Q109: 45.375 | R109: 47.3125 | S109: 49.25 | T109: 51.425 | U109: 53.6 | V109: 55.6625 | W109: 57.6125 | X109: 59.5625 | Y109: 62.3625 | Z109: 65.175 | AA109: 67.55 | AB109: 69.5 | AC109: 71.45 | AD109: 73.625 | AE109: 75.8 | AF109: 77.8625 | AG109: 79.8 | AH109: 81.75 | AI109: 83.7 | AJ109: 85.65 | AK109: 88.025 | AL109: 90.8375 | AM109: 93.6375 | AN109: 95.8125 | AO109: 97.9875 | AP109: 100.05 | AQ109: 102.0125 | AR109: 103.9625 | AS109: 105.9125 | AT109: 107.85 | AU109: 109.8 | AV109: 111.7375 | AW109: 113.675 | AZ109: 1400 | BA109: 55 1/8 | BB109: =D109*(1-$BA$4) -> 14.69 | BC109: =E109*(1-$BA$4) -> 14.584375 | BD109: =F109*(1-$BA$4) -> 14.47875 | BE109: =G109*(1-$BA$4) -> 15.055625 | BF109: =H109*(1-$BA$4) -> 16.315 | BG109: =I109*(1-$BA$4) -> 17.5825 | BH109: =J109*(1-$BA$4) -> 19.004375 | BI109: =K109*(1-$BA$4) -> 20.42625 | ... CU109: =AW109*(1-$BA$4) -> 73.88875
B110: 1500 | C110: 59 | D110: 22.6 | E110: 22.7 | F110: 22.8125 | G110: 23.875 | H110: 25.9 | I110: 27.925 | J110: 30.1875 | K110: 32.4375 | L110: 35.025 | M110: 37.95 | N110: 40.875 | O110: 42.9 | P110: 44.925 | Q110: 46.95 | R110: 48.975 | S110: 51 | T110: 53.25 | U110: 55.5 | V110: 57.65 | W110: 59.675 | X110: 61.7 | Y110: 64.625 | Z110: 67.55 | AA110: 70.0125 | AB110: 72.0375 | AC110: 74.0625 | AD110: 76.3125 | AE110: 78.575 | AF110: 80.7125 | AG110: 82.7375 | AH110: 84.7625 | AI110: 86.7875 | AJ110: 88.8125 | AK110: 91.275 | AL110: 94.2 | AM110: 97.125 | AN110: 99.375 | AO110: 101.625 | AP110: 103.775 | AQ110: 105.8 | AR110: 107.8375 | AS110: 109.85 | AT110: 111.875 | AU110: 113.9 | AV110: 115.9125 | AW110: 117.9375 | AZ110: 1500 | BA110: 59 | BB110: =D110*(1-$BA$4) -> 14.69 | BC110: =E110*(1-$BA$4) -> 14.755 | BD110: =F110*(1-$BA$4) -> 14.828125 | BE110: =G110*(1-$BA$4) -> 15.51875 | BF110: =H110*(1-$BA$4) -> 16.835 | BG110: =I110*(1-$BA$4) -> 18.15125 | BH110: =J110*(1-$BA$4) -> 19.621875 | BI110: =K110*(1-$BA$4) -> 21.084375 | ... CU110: =AW110*(1-$BA$4) -> 76.659375
B111: 1600 | C111: 63 | D111: 22.5875 | E111: 22.9625 | F111: 23.35 | G111: 24.5875 | H111: 26.7 | I111: 28.8 | J111: 31.125 | K111: 33.4625 | L111: 36.15 | M111: 39.1875 | N111: 42.2375 | O111: 44.3375 | P111: 46.425 | Q111: 48.525 | R111: 50.6375 | S111: 52.7375 | T111: 55.075 | U111: 57.4125 | V111: 59.625 | W111: 61.725 | X111: 63.825 | Y111: 66.875 | Z111: 69.9125 | AA111: 72.4875 | AB111: 74.575 | AC111: 76.675 | AD111: 79.0125 | AE111: 81.35 | AF111: 83.5625 | AG111: 85.6625 | AH111: 87.7625 | AI111: 89.8625 | AJ111: 91.9625 | AK111: 94.5375 | AL111: 97.575 | AM111: 100.6125 | AN111: 102.9375 | AO111: 105.275 | AP111: 107.4875 | AQ111: 109.6 | AR111: 111.7 | AS111: 113.8 | AT111: 115.9 | AU111: 118 | AV111: 120.1 | AW111: 122.2 | AZ111: 1600 | BA111: 63 | BB111: =D111*(1-$BA$4) -> 14.681875 | BC111: =E111*(1-$BA$4) -> 14.925625 | BD111: =F111*(1-$BA$4) -> 15.1775 | BE111: =G111*(1-$BA$4) -> 15.981875 | BF111: =H111*(1-$BA$4) -> 17.355 | BG111: =I111*(1-$BA$4) -> 18.72 | BH111: =J111*(1-$BA$4) -> 20.23125 | BI111: =K111*(1-$BA$4) -> 21.750625 | ... CU111: =AW111*(1-$BA$4) -> 79.43
...

Sheet Slats only
H2: Slats Only Trade Price List 2026 Ex Vat - List Price | AJ2: Slats Only Trade Price List 2026 Ex Vat - Discounted Price
AG3: Discount | AH3: ='Master Control'!C30 -> 0.25
B4: 89mm Slats Only Ex Vat | M4: 89mm Slats Only Ex Vat | X4: 89mm Slats Only Ex Vat | AG4: 89mm Slats Only Ex Vat | AR4: 89mm Slats Only Ex Vat | BC4: 89mm Slats Only Ex Vat
B5: White - Black- Anthracite weights, Chain & Hangers - Or Chainless | L5: Metal Welded or Sewn in | V5: Beige Weights, Hangers, White Hangers | AG5: Standard - Black or Anthracite weights, Chain & Hangers - Chainless | AQ5: Metal Welded or Sewn in | BA5: Beige Weights, Hangers, White Hangers
B6: MM | C6: INCHES | D6: AA | E6: A | F6: B | G6: C | H6: D | I6: E | J6: F | L6: MM | M6: INCHES | N6: AA | O6: A | P6: B | Q6: C | R6: D | S6: E | T6: F | V6: MM | W6: INCHES | X6: AA | Y6: A | Z6: B | AA6: C | AB6: D | AC6: E | AD6: F | AG6: MM | AH6: INCHES | AI6: AA | AJ6: A | AK6: B | AL6: C | AM6: D | AN6: E | AO6: F | AQ6: MM | AR6: INCHES | AS6: AA | AT6: A | AU6: B | AV6: C | AW6: D | AX6: E | AY6: F | BA6: MM | BB6: INCHES | BC6: AA | BD6: A | BE6: B | BF6: C | BG6: D | BH6: E | BI6: F
B7: 600 | C7: 23 5/8" | D7: 0.6375 | E7: 0.7625 | F7: 1.0125 | G7: 1.075 | H7: 1.2625 | I7: 1.8625 | J7: 2.775 | L7: 600 | M7: 23 5/8" | N7: 1.1625 | O7: 1.2875 | P7: 1.525 | Q7: 1.6375 | R7: 1.7625 | S7: 2.4125 | T7: 3.2 | V7: 600 | W7: 23 5/8" | X7: 1.0625 | Y7: 1.1875 | Z7: 1.4125 | AA7: 1.5375 | AB7: 1.6625 | AC7: 2.3125 | AD7: 3.1 | AG7: 600 | AH7: 23 5/8" | AI7: =D7*(1-$AH$3) -> 0.478125 | AJ7: =E7*(1-$AH$3) -> 0.571875 | AK7: =F7*(1-$AH$3) -> 0.759375 | AL7: =G7*(1-$AH$3) -> 0.80625 | AM7: =H7*(1-$AH$3) -> 0.946875 | AN7: =I7*(1-$AH$3) -> 1.396875 | AO7: =J7*(1-$AH$3) -> 2.08125 | AQ7: 600 | AR7: 23 5/8" | AS7: =N7*(1-$AH$3) -> 0.871875 | AT7: =O7*(1-$AH$3) -> 0.965625 | AU7: =P7*(1-$AH$3) -> 1.14375 | AV7: =Q7*(1-$AH$3) -> 1.228125 | AW7: =R7*(1-$AH$3) -> 1.321875 | AX7: =S7*(1-$AH$3) -> 1.809375 | AY7: =T7*(1-$AH$3) -> 2.4 | BA7: 600 | BB7: 23 5/8" | BC7: =X7*(1-$AH$3) -> 0.796875 | BD7: =Y7*(1-$AH$3) -> 0.890625 | BE7: =Z7*(1-$AH$3) -> 1.059375 | BF7: =AA7*(1-$AH$3) -> 1.153125 | BG7: =AB7*(1-$AH$3) -> 1.246875 | BH7: =AC7*(1-$AH$3) -> 1.734375 | BI7: =AD7*(1-$AH$3) -> 2.325
B8: 700 | C8: 27 1/2" | D8: 0.6625 | E8: 0.8 | F8: 1.0625 | G8: 1.075 | H8: 1.325 | I8: 1.875 | J8: 2.925 | L8: 700 | M8: 27 1/2" | N8: 1.1875 | O8: 1.325 | P8: 1.575 | Q8: 1.6375 | R8: 1.825 | S8: 2.425 | T8: 3.3375 | V8: 700 | W8: 27 1/2" | X8: 1.0875 | Y8: 1.2125 | Z8: 1.4625 | AA8: 1.5375 | AB8: 1.725 | AC8: 2.325 | AD8: 3.2375 | AG8: 700 | AH8: 27 1/2" | AI8: =D8*(1-$AH$3) -> 0.496875 | AJ8: =E8*(1-$AH$3) -> 0.6 | AK8: =F8*(1-$AH$3) -> 0.796875 | AL8: =G8*(1-$AH$3) -> 0.80625 | AM8: =H8*(1-$AH$3) -> 0.99375 | AN8: =I8*(1-$AH$3) -> 1.40625 | AO8: =J8*(1-$AH$3) -> 2.19375 | AQ8: 700 | AR8: 27 1/2" | AS8: =N8*(1-$AH$3) -> 0.890625 | AT8: =O8*(1-$AH$3) -> 0.99375 | AU8: =P8*(1-$AH$3) -> 1.18125 | AV8: =Q8*(1-$AH$3) -> 1.228125 | AW8: =R8*(1-$AH$3) -> 1.36875 | AX8: =S8*(1-$AH$3) -> 1.81875 | AY8: =T8*(1-$AH$3) -> 2.503125 | BA8: 700 | BB8: 27 1/2" | BC8: =X8*(1-$AH$3) -> 0.815625 | BD8: =Y8*(1-$AH$3) -> 0.909375 | BE8: =Z8*(1-$AH$3) -> 1.096875 | BF8: =AA8*(1-$AH$3) -> 1.153125 | BG8: =AB8*(1-$AH$3) -> 1.29375 | BH8: =AC8*(1-$AH$3) -> 1.74375 | BI8: =AD8*(1-$AH$3) -> 2.428125
B9: 800 | C9: 31 1/2" | D9: 0.6875 | E9: 0.825 | F9: 1.0625 | G9: 1.125 | H9: 1.4 | I9: 1.975 | J9: 3.0625 | L9: 800 | M9: 31 1/2" | N9: 1.225 | O9: 1.35 | P9: 1.6125 | Q9: 1.6375 | R9: 1.8875 | S9: 2.4375 | T9: 3.475 | V9: 800 | W9: 31 1/2" | X9: 1.125 | Y9: 1.25 | Z9: 1.5125 | AA9: 1.5375 | AB9: 1.7875 | AC9: 2.3375 | AD9: 3.375 | AG9: 800 | AH9: 31 1/2" | AI9: =D9*(1-$AH$3) -> 0.515625 | AJ9: =E9*(1-$AH$3) -> 0.61875 | AK9: =F9*(1-$AH$3) -> 0.796875 | AL9: =G9*(1-$AH$3) -> 0.84375 | AM9: =H9*(1-$AH$3) -> 1.05 | AN9: =I9*(1-$AH$3) -> 1.48125 | AO9: =J9*(1-$AH$3) -> 2.296875 | AQ9: 800 | AR9: 31 1/2" | AS9: =N9*(1-$AH$3) -> 0.91875 | AT9: =O9*(1-$AH$3) -> 1.0125 | AU9: =P9*(1-$AH$3) -> 1.209375 | AV9: =Q9*(1-$AH$3) -> 1.228125 | AW9: =R9*(1-$AH$3) -> 1.415625 | AX9: =S9*(1-$AH$3) -> 1.828125 | AY9: =T9*(1-$AH$3) -> 2.60625 | BA9: 800 | BB9: 31 1/2" | BC9: =X9*(1-$AH$3) -> 0.84375 | BD9: =Y9*(1-$AH$3) -> 0.9375 | BE9: =Z9*(1-$AH$3) -> 1.134375 | BF9: =AA9*(1-$AH$3) -> 1.153125 | BG9: =AB9*(1-$AH$3) -> 1.340625 | BH9: =AC9*(1-$AH$3) -> 1.753125 | BI9: =AD9*(1-$AH$3) -> 2.53125
B10: 900 | C10: 35 3/8" | D10: 0.725 | E10: 0.8625 | F10: 1.0625 | G10: 1.175 | H10: 1.475 | I10: 2.075 | J10: 3.2 | L10: 900 | M10: 35 3/8" | N10: 1.25 | O10: 1.3875 | P10: 1.6125 | Q10: 1.6875 | R10: 1.9625 | S10: 2.5375 | T10: 3.625 | V10: 900 | W10: 35 3/8" | X10: 1.15 | Y10: 1.275 | Z10: 1.5125 | AA10: 1.5875 | AB10: 1.8625 | AC10: 2.4375 | AD10: 3.5125 | AG10: 900 | AH10: 35 3/8" | AI10: =D10*(1-$AH$3) -> 0.54375 | AJ10: =E10*(1-$AH$3) -> 0.646875 | AK10: =F10*(1-$AH$3) -> 0.796875 | AL10: =G10*(1-$AH$3) -> 0.88125 | AM10: =H10*(1-$AH$3) -> 1.10625 | AN10: =I10*(1-$AH$3) -> 1.55625 | AO10: =J10*(1-$AH$3) -> 2.4 | AQ10: 900 | AR10: 35 3/8" | AS10: =N10*(1-$AH$3) -> 0.9375 | AT10: =O10*(1-$AH$3) -> 1.040625 | AU10: =P10*(1-$AH$3) -> 1.209375 | AV10: =Q10*(1-$AH$3) -> 1.265625 | AW10: =R10*(1-$AH$3) -> 1.471875 | AX10: =S10*(1-$AH$3) -> 1.903125 | AY10: =T10*(1-$AH$3) -> 2.71875 | BA10: 900 | BB10: 35 3/8" | BC10: =X10*(1-$AH$3) -> 0.8625 | BD10: =Y10*(1-$AH$3) -> 0.95625 | BE10: =Z10*(1-$AH$3) -> 1.134375 | BF10: =AA10*(1-$AH$3) -> 1.190625 | BG10: =AB10*(1-$AH$3) -> 1.396875 | BH10: =AC10*(1-$AH$3) -> 1.828125 | BI10: =AD10*(1-$AH$3) -> 2.634375
B11: 1000 | C11: 39 3/8" | D11: 0.75 | E11: 0.8875 | F11: 1.1 | G11: 1.2125 | H11: 1.55 | I11: 2.175 | J11: 3.3375 | L11: 1000 | M11: 39 3/8" | N11: 1.275 | O11: 1.4125 | P11: 1.6125 | Q11: 1.7375 | R11: 2.0375 | S11: 2.6375 | T11: 3.7625 | V11: 1000 | W11: 39 3/8" | X11: 1.175 | Y11: 1.3125 | Z11: 1.5125 | AA11: 1.6375 | AB11: 1.9375 | AC11: 2.525 | AD11: 3.6625 | AG11: 1000 | AH11: 39 3/8" | AI11: =D11*(1-$AH$3) -> 0.5625 | AJ11: =E11*(1-$AH$3) -> 0.665625 | AK11: =F11*(1-$AH$3) -> 0.825 | AL11: =G11*(1-$AH$3) -> 0.909375 | AM11: =H11*(1-$AH$3) -> 1.1625 | AN11: =I11*(1-$AH$3) -> 1.63125 | AO11: =J11*(1-$AH$3) -> 2.503125 | AQ11: 1000 | AR11: 39 3/8" | AS11: =N11*(1-$AH$3) -> 0.95625 | AT11: =O11*(1-$AH$3) -> 1.059375 | AU11: =P11*(1-$AH$3) -> 1.209375 | AV11: =Q11*(1-$AH$3) -> 1.303125 | AW11: =R11*(1-$AH$3) -> 1.528125 | AX11: =S11*(1-$AH$3) -> 1.978125 | AY11: =T11*(1-$AH$3) -> 2.821875 | BA11: 1000 | BB11: 39 3/8" | BC11: =X11*(1-$AH$3) -> 0.88125 | BD11: =Y11*(1-$AH$3) -> 0.984375 | BE11: =Z11*(1-$AH$3) -> 1.134375 | BF11: =AA11*(1-$AH$3) -> 1.228125 | BG11: =AB11*(1-$AH$3) -> 1.453125 | BH11: =AC11*(1-$AH$3) -> 1.89375 | BI11: =AD11*(1-$AH$3) -> 2.746875
B12: 1100 | C12: 43 1/4" | D12: 0.775 | E12: 0.925 | F12: 1.15 | G12: 1.2375 | H12: 1.625 | I12: 2.275 | J12: 3.4875 | L12: 1100 | M12: 43 1/4" | N12: 1.3125 | O12: 1.45 | P12: 1.6625 | Q12: 1.7625 | R12: 2.1125 | S12: 2.7375 | T12: 3.9 | V12: 1100 | W12: 43 1/4" | X12: 1.2 | Y12: 1.35 | Z12: 1.5625 | AA12: 1.6625 | AB12: 2.0125 | AC12: 2.625 | AD12: 3.8 | AG12: 1100 | AH12: 43 1/4" | AI12: =D12*(1-$AH$3) -> 0.58125 | AJ12: =E12*(1-$AH$3) -> 0.69375 | AK12: =F12*(1-$AH$3) -> 0.8625 | AL12: =G12*(1-$AH$3) -> 0.928125 | AM12: =H12*(1-$AH$3) -> 1.21875 | AN12: =I12*(1-$AH$3) -> 1.70625 | AO12: =J12*(1-$AH$3) -> 2.615625 | AQ12: 1100 | AR12: 43 1/4" | AS12: =N12*(1-$AH$3) -> 0.984375 | AT12: =O12*(1-$AH$3) -> 1.0875 | AU12: =P12*(1-$AH$3) -> 1.246875 | AV12: =Q12*(1-$AH$3) -> 1.321875 | AW12: =R12*(1-$AH$3) -> 1.584375 | AX12: =S12*(1-$AH$3) -> 2.053125 | AY12: =T12*(1-$AH$3) -> 2.925 | BA12: 1100 | BB12: 43 1/4" | BC12: =X12*(1-$AH$3) -> 0.9 | BD12: =Y12*(1-$AH$3) -> 1.0125 | BE12: =Z12*(1-$AH$3) -> 1.171875 | BF12: =AA12*(1-$AH$3) -> 1.246875 | BG12: =AB12*(1-$AH$3) -> 1.509375 | BH12: =AC12*(1-$AH$3) -> 1.96875 | BI12: =AD12*(1-$AH$3) -> 2.85
B13: 1200 | C13: 47 1/4" | D13: 0.825 | E13: 0.9625 | F13: 1.2125 | G13: 1.3125 | H13: 1.725 | I13: 2.3875 | J13: 3.65 | L13: 1200 | M13: 47 1/4" | N13: 1.3375 | O13: 1.475 | P13: 1.7 | Q13: 1.8 | R13: 2.1875 | S13: 2.825 | T13: 4.0375 | V13: 1200 | W13: 47 1/4" | X13: 1.2375 | Y13: 1.375 | Z13: 1.6 | AA13: 1.7 | AB13: 2.0875 | AC13: 2.725 | AD13: 3.9375 | AG13: 1200 | AH13: 47 1/4" | AI13: =D13*(1-$AH$3) -> 0.61875 | AJ13: =E13*(1-$AH$3) -> 0.721875 | AK13: =F13*(1-$AH$3) -> 0.909375 | AL13: =G13*(1-$AH$3) -> 0.984375 | AM13: =H13*(1-$AH$3) -> 1.29375 | AN13: =I13*(1-$AH$3) -> 1.790625 | AO13: =J13*(1-$AH$3) -> 2.7375 | AQ13: 1200 | AR13: 47 1/4" | AS13: =N13*(1-$AH$3) -> 1.003125 | AT13: =O13*(1-$AH$3) -> 1.10625 | AU13: =P13*(1-$AH$3) -> 1.275 | AV13: =Q13*(1-$AH$3) -> 1.35 | AW13: =R13*(1-$AH$3) -> 1.640625 | AX13: =S13*(1-$AH$3) -> 2.11875 | AY13: =T13*(1-$AH$3) -> 3.028125 | BA13: 1200 | BB13: 47 1/4" | BC13: =X13*(1-$AH$3) -> 0.928125 | BD13: =Y13*(1-$AH$3) -> 1.03125 | BE13: =Z13*(1-$AH$3) -> 1.2 | BF13: =AA13*(1-$AH$3) -> 1.275 | BG13: =AB13*(1-$AH$3) -> 1.565625 | BH13: =AC13*(1-$AH$3) -> 2.04375 | BI13: =AD13*(1-$AH$3) -> 2.953125
B14: 1300 | C14: 51 1/8" | D14: 0.8625 | E14: 1.0125 | F14: 1.275 | G14: 1.4 | H14: 1.8125 | I14: 2.5125 | J14: 3.825 | L14: 1300 | M14: 51 1/8" | N14: 1.375 | O14: 1.525 | P14: 1.7625 | Q14: 1.875 | R14: 2.275 | S14: 2.95 | T14: 4.2125 | V14: 1300 | W14: 51 1/8" | X14: 1.275 | Y14: 1.425 | Z14: 1.6625 | AA14: 1.775 | AB14: 2.175 | AC14: 2.85 | AD14: 4.1125 | AG14: 1300 | AH14: 51 1/8" | AI14: =D14*(1-$AH$3) -> 0.646875 | AJ14: =E14*(1-$AH$3) -> 0.759375 | AK14: =F14*(1-$AH$3) -> 0.95625 | AL14: =G14*(1-$AH$3) -> 1.05 | AM14: =H14*(1-$AH$3) -> 1.359375 | AN14: =I14*(1-$AH$3) -> 1.884375 | AO14: =J14*(1-$AH$3) -> 2.86875 | AQ14: 1300 | AR14: 51 1/8" | AS14: =N14*(1-$AH$3) -> 1.03125 | AT14: =O14*(1-$AH$3) -> 1.14375 | AU14: =P14*(1-$AH$3) -> 1.321875 | AV14: =Q14*(1-$AH$3) -> 1.40625 | AW14: =R14*(1-$AH$3) -> 1.70625 | AX14: =S14*(1-$AH$3) -> 2.2125 | AY14: =T14*(1-$AH$3) -> 3.159375 | BA14: 1300 | BB14: 51 1/8" | BC14: =X14*(1-$AH$3) -> 0.95625 | BD14: =Y14*(1-$AH$3) -> 1.06875 | BE14: =Z14*(1-$AH$3) -> 1.246875 | BF14: =AA14*(1-$AH$3) -> 1.33125 | BG14: =AB14*(1-$AH$3) -> 1.63125 | BH14: =AC14*(1-$AH$3) -> 2.1375 | BI14: =AD14*(1-$AH$3) -> 3.084375
B15: 1400 | C15: 55 1/8" | D15: 0.8875 | E15: 1.0375 | F15: 1.325 | G15: 1.4625 | H15: 1.8875 | I15: 2.6125 | J15: 3.9625 | L15: 1400 | M15: 55 1/8" | N15: 1.425 | O15: 1.575 | P15: 1.825 | Q15: 1.95 | R15: 2.375 | S15: 3.075 | T15: 4.3875 | V15: 1400 | W15: 55 1/8" | X15: 1.3125 | Y15: 1.4625 | Z15: 1.725 | AA15: 1.85 | AB15: 2.275 | AC15: 2.9625 | AD15: 4.275 | AG15: 1400 | AH15: 55 1/8" | AI15: =D15*(1-$AH$3) -> 0.665625 | AJ15: =E15*(1-$AH$3) -> 0.778125 | AK15: =F15*(1-$AH$3) -> 0.99375 | AL15: =G15*(1-$AH$3) -> 1.096875 | AM15: =H15*(1-$AH$3) -> 1.415625 | AN15: =I15*(1-$AH$3) -> 1.959375 | AO15: =J15*(1-$AH$3) -> 2.971875 | AQ15: 1400 | AR15: 55 1/8" | AS15: =N15*(1-$AH$3) -> 1.06875 | AT15: =O15*(1-$AH$3) -> 1.18125 | AU15: =P15*(1-$AH$3) -> 1.36875 | AV15: =Q15*(1-$AH$3) -> 1.4625 | AW15: =R15*(1-$AH$3) -> 1.78125 | AX15: =S15*(1-$AH$3) -> 2.30625 | AY15: =T15*(1-$AH$3) -> 3.290625 | BA15: 1400 | BB15: 55 1/8" | BC15: =X15*(1-$AH$3) -> 0.984375 | BD15: =Y15*(1-$AH$3) -> 1.096875 | BE15: =Z15*(1-$AH$3) -> 1.29375 | BF15: =AA15*(1-$AH$3) -> 1.3875 | BG15: =AB15*(1-$AH$3) -> 1.70625 | BH15: =AC15*(1-$AH$3) -> 2.221875 | BI15: =AD15*(1-$AH$3) -> 3.20625
B16: 1500 | C16: 59" | D16: 0.9125 | E16: 1.075 | F16: 1.375 | G16: 1.525 | H16: 1.9625 | I16: 2.7125 | J16: 4.1125 | L16: 1500 | M16: 59" | N16: 1.45 | O16: 1.6 | P16: 1.875 | Q16: 2.0125 | R16: 2.45 | S16: 3.175 | T16: 4.525 | V16: 1500 | W16: 59" | X16: 1.35 | Y16: 1.5 | Z16: 1.775 | AA16: 1.9125 | AB16: 2.35 | AC16: 3.0625 | AD16: 4.425 | AG16: 1500 | AH16: 59" | AI16: =D16*(1-$AH$3) -> 0.684375 | AJ16: =E16*(1-$AH$3) -> 0.80625 | AK16: =F16*(1-$AH$3) -> 1.03125 | AL16: =G16*(1-$AH$3) -> 1.14375 | AM16: =H16*(1-$AH$3) -> 1.471875 | AN16: =I16*(1-$AH$3) -> 2.034375 | AO16: =J16*(1-$AH$3) -> 3.084375 | AQ16: 1500 | AR16: 59" | AS16: =N16*(1-$AH$3) -> 1.0875 | AT16: =O16*(1-$AH$3) -> 1.2 | AU16: =P16*(1-$AH$3) -> 1.40625 | AV16: =Q16*(1-$AH$3) -> 1.509375 | AW16: =R16*(1-$AH$3) -> 1.8375 | AX16: =S16*(1-$AH$3) -> 2.38125 | AY16: =T16*(1-$AH$3) -> 3.39375 | BA16: 1500 | BB16: 59" | BC16: =X16*(1-$AH$3) -> 1.0125 | BD16: =Y16*(1-$AH$3) -> 1.125 | BE16: =Z16*(1-$AH$3) -> 1.33125 | BF16: =AA16*(1-$AH$3) -> 1.434375 | BG16: =AB16*(1-$AH$3) -> 1.7625 | BH16: =AC16*(1-$AH$3) -> 2.296875 | BI16: =AD16*(1-$AH$3) -> 3.31875
B17: 1600 | C17: 63" | D17: 0.925 | E17: 1.0875 | F17: 1.425 | G17: 1.5875 | H17: 2.0375 | I17: 2.8125 | J17: 4.25 | L17: 1600 | M17: 63" | N17: 1.475 | O17: 1.6375 | P17: 1.925 | Q17: 2.075 | R17: 2.525 | S17: 3.2625 | T17: 4.6625 | V17: 1600 | W17: 63" | X17: 1.375 | Y17: 1.525 | Z17: 1.825 | AA17: 1.975 | AB17: 2.425 | AC17: 3.1625 | AD17: 4.5625 | AG17: 1600 | AH17: 63" | AI17: =D17*(1-$AH$3) -> 0.69375 | AJ17: =E17*(1-$AH$3) -> 0.815625 | AK17: =F17*(1-$AH$3) -> 1.06875 | AL17: =G17*(1-$AH$3) -> 1.190625 | AM17: =H17*(1-$AH$3) -> 1.528125 | AN17: =I17*(1-$AH$3) -> 2.109375 | AO17: =J17*(1-$AH$3) -> 3.1875 | AQ17: 1600 | AR17: 63" | AS17: =N17*(1-$AH$3) -> 1.10625 | AT17: =O17*(1-$AH$3) -> 1.228125 | AU17: =P17*(1-$AH$3) -> 1.44375 | AV17: =Q17*(1-$AH$3) -> 1.55625 | AW17: =R17*(1-$AH$3) -> 1.89375 | AX17: =S17*(1-$AH$3) -> 2.446875 | AY17: =T17*(1-$AH$3) -> 3.496875 | BA17: 1600 | BB17: 63" | BC17: =X17*(1-$AH$3) -> 1.03125 | BD17: =Y17*(1-$AH$3) -> 1.14375 | BE17: =Z17*(1-$AH$3) -> 1.36875 | BF17: =AA17*(1-$AH$3) -> 1.48125 | BG17: =AB17*(1-$AH$3) -> 1.81875 | BH17: =AC17*(1-$AH$3) -> 2.371875 | BI17: =AD17*(1-$AH$3) -> 3.421875
B18: 1700 | C18: 66 7/8" | D18: 0.925 | E18: 1.0875 | F18: 1.475 | G18: 1.65 | H18: 2.1125 | I18: 2.9 | J18: 4.3875 | L18: 1700 | M18: 66 7/8" | N18: 1.4875 | O18: 1.6375 | P18: 1.975 | Q18: 2.1375 | R18: 2.6 | S18: 3.3625 | T18: 4.8125 | V18: 1700 | W18: 66 7/8" | X18: 1.375 | Y18: 1.5375 | Z18: 1.875 | AA18: 2.0375 | AB18: 2.5 | AC18: 3.2625 | AD18: 4.7 | AG18: 1700 | AH18: 66 7/8" | AI18: =D18*(1-$AH$3) -> 0.69375 | AJ18: =E18*(1-$AH$3) -> 0.815625 | AK18: =F18*(1-$AH$3) -> 1.10625 | AL18: =G18*(1-$AH$3) -> 1.2375 | AM18: =H18*(1-$AH$3) -> 1.584375 | AN18: =I18*(1-$AH$3) -> 2.175 | AO18: =J18*(1-$AH$3) -> 3.290625 | AQ18: 1700 | AR18: 66 7/8" | AS18: =N18*(1-$AH$3) -> 1.115625 | AT18: =O18*(1-$AH$3) -> 1.228125 | AU18: =P18*(1-$AH$3) -> 1.48125 | AV18: =Q18*(1-$AH$3) -> 1.603125 | AW18: =R18*(1-$AH$3) -> 1.95 | AX18: =S18*(1-$AH$3) -> 2.521875 | AY18: =T18*(1-$AH$3) -> 3.609375 | BA18: 1700 | BB18: 66 7/8" | BC18: =X18*(1-$AH$3) -> 1.03125 | BD18: =Y18*(1-$AH$3) -> 1.153125 | BE18: =Z18*(1-$AH$3) -> 1.40625 | BF18: =AA18*(1-$AH$3) -> 1.528125 | BG18: =AB18*(1-$AH$3) -> 1.875 | BH18: =AC18*(1-$AH$3) -> 2.446875 | BI18: =AD18*(1-$AH$3) -> 3.525
... B33: 3200 | C33: 126" | D33: 1.45 | E33: 1.675 | F33: 2.375 | G33: 2.775 | H33: 3.5 | I33: 4.7 | J33: 6.9875 | L33: 3200 | M33: 126" | N33: 1.9125 | O33: 2.1125 | P33: 2.7625 | Q33: 3.125 | R33: 3.8 | S33: 4.925 | T33: 7.0375 | V33: 3200 | W33: 126" | X33: 1.8 | Y33: 2.0125 | Z33: 2.6625 | AA33: 3.025 | AB33: 3.7 | AC33: 4.825 | AD33: 6.9375 | AG33: 3200 | AH33: 126" | AI33: =D33*(1-$AH$3) -> 1.0875 | AJ33: =E33*(1-$AH$3) -> 1.25625 | AK33: =F33*(1-$AH$3) -> 1.78125 | AL33: =G33*(1-$AH$3) -> 2.08125 | AM33: =H33*(1-$AH$3) -> 2.625 | AN33: =I33*(1-$AH$3) -> 3.525 | AO33: =J33*(1-$AH$3) -> 5.240625 | AQ33: 3200 | AR33: 126" | AS33: =N33*(1-$AH$3) -> 1.434375 | AT33: =O33*(1-$AH$3) -> 1.584375 | AU33: =P33*(1-$AH$3) -> 2.071875 | AV33: =Q33*(1-$AH$3) -> 2.34375 | AW33: =R33*(1-$AH$3) -> 2.85 | AX33: =S33*(1-$AH$3) -> 3.69375 | AY33: =T33*(1-$AH$3) -> 5.278125 | BA33: 3200 | BB33: 126" | BC33: =X33*(1-$AH$3) -> 1.35 | BD33: =Y33*(1-$AH$3) -> 1.509375 | BE33: =Z33*(1-$AH$3) -> 1.996875 | BF33: =AA33*(1-$AH$3) -> 2.26875 | BG33: =AB33*(1-$AH$3) -> 2.775 | BH33: =AC33*(1-$AH$3) -> 3.61875 | BI33: =AD33*(1-$AH$3) -> 5.203125
B37: 127mm Slats Only Ex Vat | K37: 127mm Slats Only Ex Vat | AG37: 127mm Slats Only Ex Vat | AP37: 127mm Slats Only Ex Vat
B38: Standard & Chainless | K38: Metal Welded or Metal Sewn in Weights | AG38: Standard & Chainless | AP38: Metal Welded or Metal Sewn in Weights
B39: MM | C39: INCHES | D39: A | E39: B | F39: C | G39: D | H39: E | I39: F | K39: MM | L39: INCHES | M39: A | N39: B | O39: C | P39: D | Q39: E | R39: F | AG39: MM | AH39: INCHES | AI39: A | AJ39: B | AK39: C | AL39: D | AM39: E | AN39: F | AP39: MM | AQ39: INCHES | AR39: A | AS39: B | AT39: C | AU39: D | AV39: E | AW39: F
B40: 600 | C40: 23.62" | D40: 0.75 | E40: 0.875 | F40: 1.375 | G40: 1.5625 | H40: 1.85 | I40: 2.075 | K40: 600 | L40: 23 5/8" | M40: 1.4 | N40: 1.525 | O40: 2.025 | P40: 2.2125 | Q40: 2.5 | R40: 2.725 | AG40: 600 | AH40: 23.62" | AI40: =D40*(1-$AH$3) -> 0.5625 | AJ40: =E40*(1-$AH$3) -> 0.65625 | AK40: =F40*(1-$AH$3) -> 1.03125 | AL40: =G40*(1-$AH$3) -> 1.171875 | AM40: =H40*(1-$AH$3) -> 1.3875 | AN40: =I40*(1-$AH$3) -> 1.55625 | AP40: 600 | AQ40: 23 5/8" | AR40: =M40*(1-$AH$3) -> 1.05 | AS40: =N40*(1-$AH$3) -> 1.14375 | AT40: =O40*(1-$AH$3) -> 1.51875 | AU40: =P40*(1-$AH$3) -> 1.659375 | AV40: =Q40*(1-$AH$3) -> 1.875 | AW40: =R40*(1-$AH$3) -> 2.04375
B41: 700 | C41: 27.56" | D41: 0.875 | E41: 1.0375 | F41: 1.5 | G41: 1.725 | H41: 2.0375 | I41: 2.2875 | K41: 700 | L41: 27 1/2" | M41: 1.525 | N41: 1.6875 | O41: 2.15 | P41: 2.375 | Q41: 2.6875 | R41: 2.9375 | AG41: 700 | AH41: 27.56" | AI41: =D41*(1-$AH$3) -> 0.65625 | AJ41: =E41*(1-$AH$3) -> 0.778125 | AK41: =F41*(1-$AH$3) -> 1.125 | AL41: =G41*(1-$AH$3) -> 1.29375 | AM41: =H41*(1-$AH$3) -> 1.528125 | AN41: =I41*(1-$AH$3) -> 1.715625 | AP41: 700 | AQ41: 27 1/2" | AR41: =M41*(1-$AH$3) -> 1.14375 | AS41: =N41*(1-$AH$3) -> 1.265625 | AT41: =O41*(1-$AH$3) -> 1.6125 | AU41: =P41*(1-$AH$3) -> 1.78125 | AV41: =Q41*(1-$AH$3) -> 2.015625 | AW41: =R41*(1-$AH$3) -> 2.203125
B42: 800 | C42: 31.50" | D42: 0.9875 | E42: 1.1875 | F42: 1.625 | G42: 1.875 | H42: 2.2125 | I42: 2.4875 | K42: 800 | L42: 31 1/2" | M42: 1.6375 | N42: 1.8375 | O42: 2.275 | P42: 2.525 | Q42: 2.8625 | R42: 3.1375 | AG42: 800 | AH42: 31.50" | AI42: =D42*(1-$AH$3) -> 0.740625 | AJ42: =E42*(1-$AH$3) -> 0.890625 | AK42: =F42*(1-$AH$3) -> 1.21875 | AL42: =G42*(1-$AH$3) -> 1.40625 | AM42: =H42*(1-$AH$3) -> 1.659375 | AN42: =I42*(1-$AH$3) -> 1.865625 | AP42: 800 | AQ42: 31 1/2" | AR42: =M42*(1-$AH$3) -> 1.228125 | AS42: =N42*(1-$AH$3) -> 1.378125 | AT42: =O42*(1-$AH$3) -> 1.70625 | AU42: =P42*(1-$AH$3) -> 1.89375 | AV42: =Q42*(1-$AH$3) -> 2.146875 | AW42: =R42*(1-$AH$3) -> 2.353125
B43: 900 | C43: 35.43" | D43: 1.1125 | E43: 1.35 | F43: 1.75 | G43: 2.0375 | H43: 2.4 | I43: 2.7 | K43: 900 | L43: 35 3/8" | M43: 1.7625 | N43: 2 | O43: 2.4 | P43: 2.6875 | Q43: 3.05 | R43: 3.35 | AG43: 900 | AH43: 35.43" | AI43: =D43*(1-$AH$3) -> 0.834375 | AJ43: =E43*(1-$AH$3) -> 1.0125 | AK43: =F43*(1-$AH$3) -> 1.3125 | AL43: =G43*(1-$AH$3) -> 1.528125 | AM43: =H43*(1-$AH$3) -> 1.8 | AN43: =I43*(1-$AH$3) -> 2.025 | AP43: 900 | AQ43: 35 3/8" | AR43: =M43*(1-$AH$3) -> 1.321875 | AS43: =N43*(1-$AH$3) -> 1.5 | AT43: =O43*(1-$AH$3) -> 1.8 | AU43: =P43*(1-$AH$3) -> 2.015625 | AV43: =Q43*(1-$AH$3) -> 2.2875 | AW43: =R43*(1-$AH$3) -> 2.5125
B44: 1000 | C44: 39.37" | D44: 1.1875 | E44: 1.45 | F44: 1.8875 | G44: 2.2 | H44: 2.6 | I44: 2.925 | K44: 1000 | L44: 39 3/8" | M44: 1.8375 | N44: 2.1 | O44: 2.5375 | P44: 2.85 | Q44: 3.25 | R44: 3.575 | AG44: 1000 | AH44: 39.37" | AI44: =D44*(1-$AH$3) -> 0.890625 | AJ44: =E44*(1-$AH$3) -> 1.0875 | AK44: =F44*(1-$AH$3) -> 1.415625 | AL44: =G44*(1-$AH$3) -> 1.65 | AM44: =H44*(1-$AH$3) -> 1.95 | AN44: =I44*(1-$AH$3) -> 2.19375 | AP44: 1000 | AQ44: 39 3/8" | AR44: =M44*(1-$AH$3) -> 1.378125 | AS44: =N44*(1-$AH$3) -> 1.575 | AT44: =O44*(1-$AH$3) -> 1.903125 | AU44: =P44*(1-$AH$3) -> 2.1375 | AV44: =Q44*(1-$AH$3) -> 2.4375 | AW44: =R44*(1-$AH$3) -> 2.68125
B45: 1100 | C45: 43.31" | D45: 1.2625 | E45: 1.5625 | F45: 2.0125 | G45: 2.375 | H45: 2.8 | I45: 3.1625 | K45: 1100 | L45: 43 1/4" | M45: 1.9125 | N45: 2.2125 | O45: 2.6625 | P45: 3.025 | Q45: 3.45 | R45: 3.8125 | AG45: 1100 | AH45: 43.31" | AI45: =D45*(1-$AH$3) -> 0.946875 | AJ45: =E45*(1-$AH$3) -> 1.171875 | AK45: =F45*(1-$AH$3) -> 1.509375 | AL45: =G45*(1-$AH$3) -> 1.78125 | AM45: =H45*(1-$AH$3) -> 2.1 | AN45: =I45*(1-$AH$3) -> 2.371875 | AP45: 1100 | AQ45: 43 1/4" | AR45: =M45*(1-$AH$3) -> 1.434375 | AS45: =N45*(1-$AH$3) -> 1.659375 | AT45: =O45*(1-$AH$3) -> 1.996875 | AU45: =P45*(1-$AH$3) -> 2.26875 | AV45: =Q45*(1-$AH$3) -> 2.5875 | AW45: =R45*(1-$AH$3) -> 2.859375
B46: 1200 | C46: 47.24" | D46: 1.3375 | E46: 1.6625 | F46: 2.15 | G46: 2.5375 | H46: 3 | I46: 3.3875 | K46: 1200 | L46: 47 1/4" | M46: 1.9875 | N46: 2.3125 | O46: 2.8 | P46: 3.1875 | Q46: 3.65 | R46: 4.0375 | AG46: 1200 | AH46: 47.24" | AI46: =D46*(1-$AH$3) -> 1.003125 | AJ46: =E46*(1-$AH$3) -> 1.246875 | AK46: =F46*(1-$AH$3) -> 1.6125 | AL46: =G46*(1-$AH$3) -> 1.903125 | AM46: =H46*(1-$AH$3) -> 2.25 | AN46: =I46*(1-$AH$3) -> 2.540625 | AP46: 1200 | AQ46: 47 1/4" | AR46: =M46*(1-$AH$3) -> 1.490625 | AS46: =N46*(1-$AH$3) -> 1.734375 | AT46: =O46*(1-$AH$3) -> 2.1 | AU46: =P46*(1-$AH$3) -> 2.390625 | AV46: =Q46*(1-$AH$3) -> 2.7375 | AW46: =R46*(1-$AH$3) -> 3.028125
B47: 1300 | C47: 51.18" | D47: 1.425 | E47: 1.775 | F47: 2.3 | G47: 2.7125 | H47: 3.2125 | I47: 3.625 | K47: 1300 | L47: 51 1/8" | M47: 2.075 | N47: 2.425 | O47: 2.95 | P47: 3.3625 | Q47: 3.8625 | R47: 4.275 | AG47: 1300 | AH47: 51.18" | AI47: =D47*(1-$AH$3) -> 1.06875 | AJ47: =E47*(1-$AH$3) -> 1.33125 | AK47: =F47*(1-$AH$3) -> 1.725 | AL47: =G47*(1-$AH$3) -> 2.034375 | AM47: =H47*(1-$AH$3) -> 2.409375 | AN47: =I47*(1-$AH$3) -> 2.71875 | AP47: 1300 | AQ47: 51 1/8" | AR47: =M47*(1-$AH$3) -> 1.55625 | AS47: =N47*(1-$AH$3) -> 1.81875 | AT47: =O47*(1-$AH$3) -> 2.2125 | AU47: =P47*(1-$AH$3) -> 2.521875 | AV47: =Q47*(1-$AH$3) -> 2.896875 | AW47: =R47*(1-$AH$3) -> 3.20625
B48: 1400 | C48: 55.12" | D48: 1.5125 | E48: 1.875 | F48: 2.4625 | G48: 2.9 | H48: 3.425 | I48: 3.875 | K48: 1400 | L48: 55 1/8" | M48: 2.1625 | N48: 2.525 | O48: 3.1125 | P48: 3.55 | Q48: 4.075 | R48: 4.525 | AG48: 1400 | AH48: 55.12" | AI48: =D48*(1-$AH$3) -> 1.134375 | AJ48: =E48*(1-$AH$3) -> 1.40625 | AK48: =F48*(1-$AH$3) -> 1.846875 | AL48: =G48*(1-$AH$3) -> 2.175 | AM48: =H48*(1-$AH$3) -> 2.56875 | AN48: =I48*(1-$AH$3) -> 2.90625 | AP48: 1400 | AQ48: 55 1/8" | AR48: =M48*(1-$AH$3) -> 1.621875 | AS48: =N48*(1-$AH$3) -> 1.89375 | AT48: =O48*(1-$AH$3) -> 2.334375 | AU48: =P48*(1-$AH$3) -> 2.6625 | AV48: =Q48*(1-$AH$3) -> 3.05625 | AW48: =R48*(1-$AH$3) -> 3.39375
B49: 1500 | C49: 59.06" | D49: 1.6 | E49: 1.9875 | F49: 2.6125 | G49: 3.075 | H49: 3.6375 | I49: 4.1125 | K49: 1500 | L49: 59" | M49: 2.25 | N49: 2.6375 | O49: 3.2625 | P49: 3.725 | Q49: 4.2875 | R49: 4.7625 | AG49: 1500 | AH49: 59.06" | AI49: =D49*(1-$AH$3) -> 1.2 | AJ49: =E49*(1-$AH$3) -> 1.490625 | AK49: =F49*(1-$AH$3) -> 1.959375 | AL49: =G49*(1-$AH$3) -> 2.30625 | AM49: =H49*(1-$AH$3) -> 2.728125 | AN49: =I49*(1-$AH$3) -> 3.084375 | AP49: 1500 | AQ49: 59" | AR49: =M49*(1-$AH$3) -> 1.6875 | AS49: =N49*(1-$AH$3) -> 1.978125 | AT49: =O49*(1-$AH$3) -> 2.446875 | AU49: =P49*(1-$AH$3) -> 2.79375 | AV49: =Q49*(1-$AH$3) -> 3.215625 | AW49: =R49*(1-$AH$3) -> 3.571875
B50: 1600 | C50: 62.99" | D50: 1.6875 | E50: 2.1 | F50: 2.7625 | G50: 3.2625 | H50: 3.8625 | I50: 4.3625 | K50: 1600 | L50: 63" | M50: 2.3375 | N50: 2.75 | O50: 3.4125 | P50: 3.9125 | Q50: 4.5125 | R50: 5.0125 | AG50: 1600 | AH50: 62.99" | AI50: =D50*(1-$AH$3) -> 1.265625 | AJ50: =E50*(1-$AH$3) -> 1.575 | AK50: =F50*(1-$AH$3) -> 2.071875 | AL50: =G50*(1-$AH$3) -> 2.446875 | AM50: =H50*(1-$AH$3) -> 2.896875 | AN50: =I50*(1-$AH$3) -> 3.271875 | AP50: 1600 | AQ50: 63" | AR50: =M50*(1-$AH$3) -> 1.753125 | AS50: =N50*(1-$AH$3) -> 2.0625 | AT50: =O50*(1-$AH$3) -> 2.559375 | AU50: =P50*(1-$AH$3) -> 2.934375 | AV50: =Q50*(1-$AH$3) -> 3.384375 | AW50: =R50*(1-$AH$3) -> 3.759375
B51: 1700 | C51: 66.93" | D51: 1.7625 | E51: 2.2 | F51: 2.9125 | G51: 3.4375 | H51: 4.075 | I51: 4.6125 | K51: 1700 | L51: 66 7/8" | M51: 2.4125 | N51: 2.85 | O51: 3.5625 | P51: 4.0875 | Q51: 4.725 | R51: 5.2625 | AG51: 1700 | AH51: 66.93" | AI51: =D51*(1-$AH$3) -> 1.321875 | AJ51: =E51*(1-$AH$3) -> 1.65 | AK51: =F51*(1-$AH$3) -> 2.184375 | AL51: =G51*(1-$AH$3) -> 2.578125 | AM51: =H51*(1-$AH$3) -> 3.05625 | AN51: =I51*(1-$AH$3) -> 3.459375 | AP51: 1700 | AQ51: 66 7/8" | AR51: =M51*(1-$AH$3) -> 1.809375 | AS51: =N51*(1-$AH$3) -> 2.1375 | AT51: =O51*(1-$AH$3) -> 2.671875 | AU51: =P51*(1-$AH$3) -> 3.065625 | AV51: =Q51*(1-$AH$3) -> 3.54375 | AW51: =R51*(1-$AH$3) -> 3.946875
... B66: 3200 | C66: 125.98" | D66: 3 | E66: 3.8125 | F66: 5.1 | G66: 6.0875 | H66: 7.2375 | I66: 8.2125 | K66: 3200 | L66: 126" | M66: 3.65 | N66: 4.4625 | O66: 5.75 | P66: 6.7375 | Q66: 7.8875 | R66: 8.8625 | AG66: 3200 | AH66: 125.98" | AI66: =D66*(1-$AH$3) -> 2.25 | AJ66: =E66*(1-$AH$3) -> 2.859375 | AK66: =F66*(1-$AH$3) -> 3.825 | AL66: =G66*(1-$AH$3) -> 4.565625 | AM66: =H66*(1-$AH$3) -> 5.428125 | AN66: =I66*(1-$AH$3) -> 6.159375 | AP66: 3200 | AQ66: 126" | AR66: =M66*(1-$AH$3) -> 2.7375 | AS66: =N66*(1-$AH$3) -> 3.346875 | AT66: =O66*(1-$AH$3) -> 4.3125 | AU66: =P66*(1-$AH$3) -> 5.053125 | AV66: =Q66*(1-$AH$3) -> 5.915625 | AW66: =R66*(1-$AH$3) -> 6.646875
B67: Above price include plastic white weights, hangers and bottom chain | AG67: Above price include plastic white weights, hangers and bottom chain

Sheet Pvc Rigid
B2: PVC Rigid Trade Price List 2026 Ex VAT - List Price | AY2: PVC Rigid Trade Price List 2026 Ex VAT - Discounted Prices
AY3: Discount | AZ3: ='Master Control'!C26 -> 0.2
B5: Occa | AY5: Occa
B6: A | D6: 26 1/2 | E6: 23.625 | F6: 27 1/2 | G6: 31 1/2 | H6: 35 3/8 | I6: 39 3/8 | J6: 43 1/4 | K6: 47 1/4 | L6: 51 1/8 | M6: 55 1/8 | N6: 59 | O6: 63 | P6: 66 7/8 | Q6: 70 7/8 | R6: 74 3/4 | S6: 78 3/4 | T6: 82 5/8 | U6: 86 5/8 | V6: 90 1/2 | W6: 94 1/2 | X6: 98 3/8 | Y6: 102 3/8 | Z6: 106 1/4 | AA6: 110 1/4 | AB6: 114 1/8 | AC6: 118 1/8 | AD6: 122 | AE6: 126 | AF6: 129 7/8 | AG6: 133 7/8 | AH6: 137 3/4 | AI6: 141 3/4 | AJ6: 145 5/8 | AK6: 149 5/8 | AL6: 153 1/2 | AM6: 157 1/2 | AN6: 161 3/8 | AO6: 165 3/8 | AP6: 150 5/8 | AQ6: 161 1/2 | AR6: 165 1/2 | AS6: 169 3/8 | AT6: 173 3/8 | AU6: 150 5/8 | AV6: 161 1/2 | AW6: 166 1/2 | AY6: A | BA6: 26 1/2 | BB6: 23.625 | BC6: 27 1/2 | BD6: 31 1/2 | BE6: 35 3/8 | BF6: 39 3/8 | BG6: 43 1/4 | BH6: 47 1/4 | BI6: 51 1/8 | BJ6: 55 1/8 | BK6: 59 | BL6: 63 | BM6: 66 7/8 | BN6: 70 7/8 | BO6: 74 3/4 | BP6: 78 3/4 | BQ6: 82 5/8 | BR6: 86 5/8 | BS6: 90 1/2 | BT6: 94 1/2 | BU6: 98 3/8 | BV6: 102 3/8 | BW6: 106 1/4 | BX6: 110 1/4 | BY6: 114 1/8 | BZ6: 118 1/8 | CA6: 122 | CB6: 126 | CC6: 129 7/8 | CD6: 133 7/8 | CE6: 137 3/4 | CF6: 141 3/4 | CG6: 145 5/8 | CH6: 149 5/8 | CI6: 153 1/2 | CJ6: 157 1/2 | CK6: 161 3/8 | CL6: 165 3/8 | CM6: 150 5/8 | CN6: 161 1/2 | CO6: 165 1/2 | CP6: 169 3/8 | CQ6: 173 3/8 | CR6: 150 5/8 | CS6: 161 1/2 | CT6: 166 1/2
D7: 500 | E7: 600 | F7: 700 | G7: 800 | H7: 900 | I7: 1000 | J7: 1100 | K7: 1200 | L7: 1300 | M7: 1400 | N7: 1500 | O7: 1600 | P7: 1700 | Q7: 1800 | R7: 1900 | S7: 2000 | T7: 2100 | U7: 2200 | V7: 2300 | W7: 2400 | X7: 2500 | Y7: 2600 | Z7: 2700 | AA7: 2800 | AB7: 2900 | AC7: 3000 | AD7: 3100 | AE7: 3200 | AF7: 3300 | AG7: 3400 | AH7: 3500 | AI7: 3600 | AJ7: 3700 | AK7: 3800 | AL7: 3900 | AM7: 4000 | AN7: 4100 | AO7: 4200 | AP7: 4300 | AQ7: 4400 | AR7: 4500 | AS7: 4600 | AT7: 4700 | AU7: 4800 | AV7: 4900 | AW7: 5000 | BA7: 500 | BB7: 600 | BC7: 700 | BD7: 800 | BE7: 900 | BF7: 1000 | BG7: 1100 | BH7: 1200 | BI7: 1300 | BJ7: 1400 | BK7: 1500 | BL7: 1600 | BM7: 1700 | BN7: 1800 | BO7: 1900 | BP7: 2000 | BQ7: 2100 | BR7: 2200 | BS7: 2300 | BT7: 2400 | BU7: 2500 | BV7: 2600 | BW7: 2700 | BX7: 2800 | BY7: 2900 | BZ7: 3000 | CA7: 3100 | CB7: 3200 | CC7: 3300 | CD7: 3400 | CE7: 3500 | CF7: 3600 | CG7: 3700 | CH7: 3800 | CI7: 3900 | CJ7: 4000 | CK7: 4100 | CL7: 4200 | CM7: 4300 | CN7: 4400 | CO7: 4500 | CP7: 4600 | CQ7: 4700 | CR7: 4800 | CS7: 4900 | CT7: 5000
B8: 23 5/8 | C8: 600 | D8: 35.5375 | E8: 37.6875 | F8: 39.8375 | G8: 42.2125 | H8: 44.575 | I8: 47.1625 | J8: 49.7125 | K8: 52.1 | L8: 54.45 | M8: 56.8875 | N8: 59.5 | O8: 61.9375 | P8: 64.3 | Q8: 66.675 | R8: 69.05 | S8: 71.475 | T8: 74.075 | U8: 76.5125 | V8: 78.9 | W8: 81.275 | X8: 83.9375 | Y8: 86.775 | Z8: 89.625 | AA8: 92.4625 | AB8: 95.3 | AC8: 96.775 | AD8: 98.775 | AE8: 101.425 | AF8: 104.0875 | AG8: 106.7125 | AH8: 108.975 | AI8: 111.075 | AJ8: 113.5625 | AK8: 116.45 | AL8: 119.3375 | AM8: 122.225 | AN8: 125.1125 | AO8: 125.55 | AP8: 128.9275 | AQ8: 131.325 | AR8: 133.7225 | AS8: 136.12 | AT8: 138.5175 | AU8: 140.915 | AV8: 143.3125 | AW8: 145.71 | AY8: 23 5/8 | AZ8: 600 | BA8: =D8-(1-$AZ$3) -> 34.7375 | BB8: =E8-(1-$AZ$3) -> 36.8875 | BC8: =F8-(1-$AZ$3) -> 39.0375 | BD8: =G8-(1-$AZ$3) -> 41.4125 | BE8: =H8-(1-$AZ$3) -> 43.775 | BF8: =I8-(1-$AZ$3) -> 46.3625 | BG8: =J8-(1-$AZ$3) -> 48.9125 | BH8: =K8-(1-$AZ$3) -> 51.3 | ... CT8: =AW8-(1-$AZ$3) -> 144.91
B9: 27 1/2 | C9: 700 | D9: 36.7875 | E9: 39.0375 | F9: 41.2875 | G9: 43.8 | H9: 46.3 | I9: 49 | J9: 51.65 | K9: 54.1375 | L9: 56.625 | M9: 59.175 | N9: 61.9125 | O9: 64.475 | P9: 66.9625 | Q9: 69.4375 | R9: 71.95 | S9: 74.5 | T9: 77.225 | U9: 79.7875 | V9: 82.2875 | W9: 84.775 | X9: 87.575 | Y9: 90.575 | Z9: 93.575 | AA9: 96.5625 | AB9: 99.5625 | AC9: 101.0625 | AD9: 103.125 | AE9: 105.925 | AF9: 108.7375 | AG9: 111.5125 | AH9: 113.8625 | AI9: 116.05 | AJ9: 118.6625 | AK9: 121.7125 | AL9: 124.7625 | AM9: 127.8 | AN9: 130.85 | AO9: 131.3125 | AP9: 134.87375 | AQ9: 137.4025 | AR9: 139.93125 | AS9: 142.46 | AT9: 144.98875 | AU9: 147.5175 | AV9: 150.04625 | AW9: 152.575 | AY9: 27 1/2 | AZ9: 700 | BA9: =D9-(1-$AZ$3) -> 35.9875 | BB9: =E9-(1-$AZ$3) -> 38.2375 | BC9: =F9-(1-$AZ$3) -> 40.4875 | BD9: =G9-(1-$AZ$3) -> 43 | BE9: =H9-(1-$AZ$3) -> 45.5 | BF9: =I9-(1-$AZ$3) -> 48.2 | BG9: =J9-(1-$AZ$3) -> 50.85 | BH9: =K9-(1-$AZ$3) -> 53.3375 | ... CT9: =AW9-(1-$AZ$3) -> 151.775
B10: 31 1/2 | C10: 800 | D10: 38.15 | E10: 40.525 | F10: 42.9 | G10: 45.55 | H10: 48.1875 | I10: 51.0125 | J10: 53.7875 | K10: 56.4 | L10: 59.025 | M10: 61.725 | N10: 64.5875 | O10: 67.2875 | P10: 69.9125 | Q10: 72.525 | R10: 75.1625 | S10: 77.85 | T10: 80.7125 | U10: 83.4125 | V10: 86.0375 | W10: 88.6625 | X10: 91.625 | Y10: 94.8 | Z10: 97.9625 | AA10: 101.125 | AB10: 104.3 | AC10: 105.8125 | AD10: 107.9625 | AE10: 110.9375 | AF10: 113.9 | AG10: 116.8375 | AH10: 119.3 | AI10: 121.575 | AJ10: 124.325 | AK10: 127.55 | AL10: 130.775 | AM10: 134 | AN10: 137.2125 | AO10: 137.7 | AP10: 141.46875 | AQ10: 144.1425 | AR10: 146.81625 | AS10: 149.49 | AT10: 152.16375 | AU10: 154.8375 | AV10: 157.51125 | AW10: 160.185 | AY10: 31 1/2 | AZ10: 800 | BA10: =D10-(1-$AZ$3) -> 37.35 | BB10: =E10-(1-$AZ$3) -> 39.725 | BC10: =F10-(1-$AZ$3) -> 42.1 | BD10: =G10-(1-$AZ$3) -> 44.75 | BE10: =H10-(1-$AZ$3) -> 47.3875 | BF10: =I10-(1-$AZ$3) -> 50.2125 | BG10: =J10-(1-$AZ$3) -> 52.9875 | BH10: =K10-(1-$AZ$3) -> 55.6 | ... CT10: =AW10-(1-$AZ$3) -> 159.385
B11: 35 3/8 | C11: 900 | D11: 39.5125 | E11: 42.0125 | F11: 44.5125 | G11: 47.2875 | H11: 50.05 | I11: 53.0125 | J11: 55.925 | K11: 58.675 | L11: 61.425 | M11: 64.25 | N11: 67.2625 | O11: 70.0875 | P11: 72.85 | Q11: 75.625 | R11: 78.375 | S11: 81.1875 | T11: 84.175 | U11: 87.025 | V11: 89.8 | W11: 92.5625 | X11: 95.6875 | Y11: 99.025 | Z11: 102.3625 | AA11: 105.7 | AB11: 109.0375 | AC11: 110.5625 | AD11: 112.8 | AE11: 115.95 | AF11: 119.0875 | AG11: 122.1625 | AH11: 124.7375 | AI11: 127.1125 | AJ11: 129.9875 | AK11: 133.3875 | AL11: 136.7875 | AM11: 140.175 | AN11: 143.575 | AO11: 144.0875 | AP11: 148.05875 | AQ11: 150.8775 | AR11: 153.69625 | AS11: 156.515 | AT11: 159.33375 | AU11: 162.1525 | AV11: 164.97125 | AW11: 167.79 | AY11: 35 3/8 | AZ11: 900 | BA11: =D11-(1-$AZ$3) -> 38.7125 | BB11: =E11-(1-$AZ$3) -> 41.2125 | BC11: =F11-(1-$AZ$3) -> 43.7125 | BD11: =G11-(1-$AZ$3) -> 46.4875 | BE11: =H11-(1-$AZ$3) -> 49.25 | BF11: =I11-(1-$AZ$3) -> 52.2125 | BG11: =J11-(1-$AZ$3) -> 55.125 | BH11: =K11-(1-$AZ$3) -> 57.875 | ... CT11: =AW11-(1-$AZ$3) -> 166.99
B12: 39 3/8 | C12: 1000 | D12: 40.9 | E12: 43.5125 | F12: 46.125 | G12: 49.025 | H12: 51.9125 | I12: 55.025 | J12: 58.075 | K12: 60.95 | L12: 63.825 | M12: 66.7875 | N12: 69.95 | O12: 72.9 | P12: 75.8 | Q12: 78.7 | R12: 81.6 | S12: 84.55 | T12: 87.675 | U12: 90.6375 | V12: 93.5375 | W12: 96.4375 | X12: 99.7125 | Y12: 103.225 | Z12: 106.7375 | AA12: 110.25 | AB12: 113.7625 | AC12: 115.325 | AD12: 117.65 | AE12: 120.9375 | AF12: 124.2375 | AG12: 127.475 | AH12: 130.175 | AI12: 132.6375 | AJ12: 135.6625 | AK12: 139.225 | AL12: 142.8 | AM12: 146.3625 | AN12: 149.9375 | AO12: 150.475 | AP12: 154.65125 | AQ12: 157.615 | AR12: 160.57875 | AS12: 163.5425 | AT12: 166.50625 | AU12: 169.47 | AV12: 172.43375 | AW12: 175.3975 | AY12: 39 3/8 | AZ12: 1000 | BA12: =D12-(1-$AZ$3) -> 40.1 | BB12: =E12-(1-$AZ$3) -> 42.7125 | BC12: =F12-(1-$AZ$3) -> 45.325 | BD12: =G12-(1-$AZ$3) -> 48.225 | BE12: =H12-(1-$AZ$3) -> 51.1125 | BF12: =I12-(1-$AZ$3) -> 54.225 | BG12: =J12-(1-$AZ$3) -> 57.275 | BH12: =K12-(1-$AZ$3) -> 60.15 | ... CT12: =AW12-(1-$AZ$3) -> 174.5975
B13: 43 1/4 | C13: 1100 | D13: 42.2875 | E13: 45.0125 | F13: 47.7375 | G13: 50.7625 | H13: 53.7875 | I13: 57.0375 | J13: 60.225 | K13: 63.225 | L13: 66.25 | M13: 69.3375 | N13: 72.625 | O13: 75.725 | P13: 78.7625 | Q13: 81.7875 | R13: 84.825 | S13: 87.9125 | T13: 91.15 | U13: 94.25 | V13: 97.2875 | W13: 100.3125 | X13: 103.75 | Y13: 107.4375 | Z13: 111.125 | AA13: 114.8125 | AB13: 118.5 | AC13: 120.0875 | AD13: 122.4875 | AE13: 125.9375 | AF13: 129.3875 | AG13: 132.8 | AH13: 135.6125 | AI13: 138.175 | AJ13: 141.325 | AK13: 145.0625 | AL13: 148.8125 | AM13: 152.55 | AN13: 156.2875 | AO13: 156.85 | AP13: 161.2275 | AQ13: 164.3325 | AR13: 167.4375 | AS13: 170.5425 | AT13: 173.6475 | AU13: 176.7525 | AV13: 179.8575 | AW13: 182.9625 | AY13: 43 1/4 | AZ13: 1100 | BA13: =D13-(1-$AZ$3) -> 41.4875 | BB13: =E13-(1-$AZ$3) -> 44.2125 | BC13: =F13-(1-$AZ$3) -> 46.9375 | BD13: =G13-(1-$AZ$3) -> 49.9625 | BE13: =H13-(1-$AZ$3) -> 52.9875 | BF13: =I13-(1-$AZ$3) -> 56.2375 | BG13: =J13-(1-$AZ$3) -> 59.425 | BH13: =K13-(1-$AZ$3) -> 62.425 | ... CT13: =AW13-(1-$AZ$3) -> 182.1625
B14: 47 1/4 | C14: 1200 | D14: 43.6375 | E14: 46.4875 | F14: 49.3375 | G14: 52.5125 | H14: 55.675 | I14: 59.025 | J14: 62.3375 | K14: 65.5125 | L14: 68.675 | M14: 71.8875 | N14: 75.2875 | O14: 78.525 | P14: 81.7 | Q14: 84.8625 | R14: 88.0375 | S14: 91.25 | T14: 94.6 | U14: 97.85 | V14: 101.025 | W14: 104.2 | X14: 107.8 | Y14: 111.6625 | Z14: 115.5125 | AA14: 119.375 | AB14: 123.2375 | AC14: 124.8375 | AD14: 127.325 | AE14: 130.9375 | AF14: 134.55 | AG14: 138.1375 | AH14: 141.0625 | AI14: 143.7 | AJ14: 146.9875 | AK14: 150.9 | AL14: 154.8125 | AM14: 158.725 | AN14: 162.6375 | AO14: 163.225 | AP14: 167.8025 | AQ14: 171.05 | AR14: 174.2975 | AS14: 177.545 | AT14: 180.7925 | AU14: 184.04 | AV14: 187.2875 | AW14: 190.535 | AY14: 47 1/4 | AZ14: 1200 | BA14: =D14-(1-$AZ$3) -> 42.8375 | BB14: =E14-(1-$AZ$3) -> 45.6875 | BC14: =F14-(1-$AZ$3) -> 48.5375 | BD14: =G14-(1-$AZ$3) -> 51.7125 | BE14: =H14-(1-$AZ$3) -> 54.875 | BF14: =I14-(1-$AZ$3) -> 58.225 | BG14: =J14-(1-$AZ$3) -> 61.5375 | BH14: =K14-(1-$AZ$3) -> 64.7125 | ... CT14: =AW14-(1-$AZ$3) -> 189.735
B15: 51 1/8 | C15: 1300 | D15: 44.9875 | E15: 47.9625 | F15: 50.9375 | G15: 54.2375 | H15: 57.55 | I15: 61.025 | J15: 64.475 | K15: 67.7875 | L15: 71.075 | M15: 74.425 | N15: 77.9625 | O15: 81.4 | P15: 84.75 | Q15: 87.9625 | R15: 91.25 | S15: 94.5875 | T15: 98.0875 | U15: 101.4625 | V15: 104.775 | W15: 108.0875 | X15: 111.8375 | Y15: 115.875 | Z15: 119.9125 | AA15: 123.9375 | AB15: 127.975 | AC15: 129.6 | AD15: 132.1625 | AE15: 135.9375 | AF15: 139.725 | AG15: 143.4625 | AH15: 146.4875 | AI15: 149.2375 | AJ15: 152.65 | AK15: 156.7375 | AL15: 160.825 | AM15: 164.9125 | AN15: 169 | AO15: 169.6125 | AP15: 174.395 | AQ15: 177.7875 | AR15: 181.18 | AS15: 184.5725 | AT15: 187.965 | AU15: 191.3575 | AV15: 194.75 | AW15: 198.1425 | AY15: 51 1/8 | AZ15: 1300 | BA15: =D15-(1-$AZ$3) -> 44.1875 | BB15: =E15-(1-$AZ$3) -> 47.1625 | BC15: =F15-(1-$AZ$3) -> 50.1375 | BD15: =G15-(1-$AZ$3) -> 53.4375 | BE15: =H15-(1-$AZ$3) -> 56.75 | BF15: =I15-(1-$AZ$3) -> 60.225 | BG15: =J15-(1-$AZ$3) -> 63.675 | BH15: =K15-(1-$AZ$3) -> 66.9875 | ... CT15: =AW15-(1-$AZ$3) -> 197.3425
B16: 55 1/8 | C16: 1400 | D16: 46.3625 | E16: 49.45 | F16: 52.5375 | G16: 55.975 | H16: 59.4125 | I16: 63.025 | J16: 66.6125 | K16: 70.0625 | L16: 73.4875 | M16: 76.975 | N16: 80.65 | O16: 84.2875 | P16: 87.825 | Q16: 91.075 | R16: 94.4625 | S16: 97.9375 | T16: 101.5875 | U16: 105.1 | V16: 108.5375 | W16: 111.975 | X16: 115.8875 | Y16: 120.1 | Z16: 124.3 | AA16: 128.5 | AB16: 132.7 | AC16: 134.35 | AD16: 137.0125 | AE16: 140.95 | AF16: 144.9 | AG16: 148.7875 | AH16: 151.925 | AI16: 154.7625 | AJ16: 158.3125 | AK16: 162.575 | AL16: 166.8375 | AM16: 171.1 | AN16: 175.375 | AO16: 176.0125 | AP16: 181.00375 | AQ16: 184.545 | AR16: 188.08625 | AS16: 191.6275 | AT16: 195.16875 | AU16: 198.71 | AV16: 202.25125 | AW16: 205.7925 | AY16: 55 1/8 | AZ16: 1400 | BA16: =D16-(1-$AZ$3) -> 45.5625 | BB16: =E16-(1-$AZ$3) -> 48.65 | BC16: =F16-(1-$AZ$3) -> 51.7375 | BD16: =G16-(1-$AZ$3) -> 55.175 | BE16: =H16-(1-$AZ$3) -> 58.6125 | BF16: =I16-(1-$AZ$3) -> 62.225 | BG16: =J16-(1-$AZ$3) -> 65.8125 | BH16: =K16-(1-$AZ$3) -> 69.2625 | ... CT16: =AW16-(1-$AZ$3) -> 204.9925
B17: 59 | C17: 1500 | D17: 47.7375 | E17: 50.9375 | F17: 54.1375 | G17: 57.7 | H17: 61.275 | I17: 65.0375 | J17: 68.75 | K17: 72.3375 | L17: 75.8875 | M17: 79.525 | N17: 83.3375 | O17: 87.175 | P17: 90.8875 | Q17: 94.175 | R17: 97.6625 | S17: 101.2875 | T17: 105.0875 | U17: 108.725 | V17: 112.3 | W17: 115.875 | X17: 119.9375 | Y17: 124.3125 | Z17: 128.6875 | AA17: 133.0625 | AB17: 137.425 | AC17: 139.1 | AD17: 141.85 | AE17: 145.9625 | AF17: 150.0875 | AG17: 154.1125 | AH17: 157.35 | AI17: 160.2875 | AJ17: 163.975 | AK17: 168.4125 | AL17: 172.85 | AM17: 177.3 | AN17: 181.7375 | AO17: 182.4 | AP17: 187.59875 | AQ17: 191.285 | AR17: 194.97125 | AS17: 198.6575 | AT17: 202.34375 | AU17: 206.03 | AV17: 209.71625 | AW17: 213.4025 | AY17: 59 | AZ17: 1500 | BA17: =D17-(1-$AZ$3) -> 46.9375 | BB17: =E17-(1-$AZ$3) -> 50.1375 | BC17: =F17-(1-$AZ$3) -> 53.3375 | BD17: =G17-(1-$AZ$3) -> 56.9 | BE17: =H17-(1-$AZ$3) -> 60.475 | BF17: =I17-(1-$AZ$3) -> 64.2375 | BG17: =J17-(1-$AZ$3) -> 67.95 | BH17: =K17-(1-$AZ$3) -> 71.5375 | ... CT17: =AW17-(1-$AZ$3) -> 212.6025
B18: 63 | C18: 1600 | D18: 49.1 | E18: 52.425 | F18: 55.75 | G18: 59.4375 | H18: 63.15 | I18: 67.0375 | J18: 70.9 | K18: 74.6125 | L18: 78.3 | M18: 82.0625 | N18: 86.025 | O18: 89.95 | P18: 93.775 | Q18: 97.2375 | R18: 100.875 | S18: 104.6375 | T18: 108.5625 | U18: 112.35 | V18: 116.0625 | W18: 119.7625 | X18: 123.9875 | Y18: 128.5375 | Z18: 133.075 | AA18: 137.625 | AB18: 142.1625 | AC18: 143.8625 | AD18: 146.6875 | AE18: 150.9625 | AF18: 155.225 | AG18: 159.425 | AH18: 162.7875 | AI18: 165.8125 | AJ18: 169.625 | AK18: 174.25 | AL18: 178.8625 | AM18: 183.4875 | AN18: 188.1125 | AO18: 188.8 | AP18: 194.2075 | AQ18: 198.0425 | AR18: 201.8775 | AS18: 205.7125 | AT18: 209.5475 | AU18: 213.3825 | AV18: 217.2175 | AW18: 221.0525 | AY18: 63 | AZ18: 1600 | BA18: =D18-(1-$AZ$3) -> 48.3 | BB18: =E18-(1-$AZ$3) -> 51.625 | BC18: =F18-(1-$AZ$3) -> 54.95 | BD18: =G18-(1-$AZ$3) -> 58.6375 | BE18: =H18-(1-$AZ$3) -> 62.35 | BF18: =I18-(1-$AZ$3) -> 66.2375 | BG18: =J18-(1-$AZ$3) -> 70.1 | BH18: =K18-(1-$AZ$3) -> 73.8125 | ... CT18: =AW18-(1-$AZ$3) -> 220.2525
B19: 66 7/8 | C19: 1700 | D19: 50.45 | E19: 53.9 | F19: 57.35 | G19: 61.1875 | H19: 65.025 | I19: 69.05 | J19: 73.0375 | K19: 76.8875 | L19: 80.7 | M19: 84.6 | N19: 88.7 | O19: 92.6875 | P19: 96.5875 | Q19: 100.2875 | R19: 104.0875 | S19: 107.975 | T19: 112.05 | U19: 115.975 | V19: 119.8125 | W19: 123.6625 | X19: 128.05 | Y19: 132.7625 | Z19: 137.475 | AA19: 142.1875 | AB19: 146.9 | AC19: 148.625 | AD19: 151.525 | AE19: 155.95 | AF19: 160.375 | AG19: 164.7375 | AH19: 168.225 | AI19: 171.325 | AJ19: 175.2875 | AK19: 180.0875 | AL19: 184.8875 | AM19: 189.6875 | AN19: 194.4875 | AO19: 195.2 | AP19: 200.8175 | AQ19: 204.8 | AR19: 208.7825 | AS19: 212.765 | AT19: 216.7475 | AU19: 220.73 | AV19: 224.7125 | AW19: 228.695 | AY19: 66 7/8 | AZ19: 1700 | BA19: =D19-(1-$AZ$3) -> 49.65 | BB19: =E19-(1-$AZ$3) -> 53.1 | BC19: =F19-(1-$AZ$3) -> 56.55 | BD19: =G19-(1-$AZ$3) -> 60.3875 | BE19: =H19-(1-$AZ$3) -> 64.225 | BF19: =I19-(1-$AZ$3) -> 68.25 | BG19: =J19-(1-$AZ$3) -> 72.2375 | BH19: =K19-(1-$AZ$3) -> 76.0875 | ... CT19: =AW19-(1-$AZ$3) -> 227.895
... B32: 118 1/8 | C32: 3000 | D32: 66.9375 | E32: 71.875 | F32: 76.8125 | G32: 82.325 | H32: 87.8875 | I32: 93.475 | J32: 99.025 | K32: 104.4875 | L32: 109.9375 | M32: 115.4625 | N32: 121.1875 | O32: 126.725 | P32: 132.2 | Q32: 137.6375 | R32: 143.1 | S32: 148.6125 | T32: 154.3125 | U32: 159.8625 | V32: 165.3375 | W32: 170.8125 | X32: 177.1 | Y32: 183.9 | Z32: 190.7 | AA32: 197.5 | AB32: 204.3 | AC32: 206.3 | AD32: 210.2375 | AE32: 216.625 | AF32: 223.025 | AG32: 229.3125 | AH32: 234.1375 | AI32: 238.375 | AJ32: 243.95 | AK32: 250.8875 | AL32: 257.825 | AM32: 264.75 | AN32: 271.6875 | AO32: 272.725 | AP32: 280.83625 | AQ32: 286.59 | AR32: 292.34375 | AS32: 298.0975 | AT32: 303.85125 | AU32: 309.605 | AV32: 315.35875 | AW32: 321.1125 | AY32: 118 1/8 | AZ32: 3000 | BA32: =D32-(1-$AZ$3) -> 66.1375 | BB32: =E32-(1-$AZ$3) -> 71.075 | BC32: =F32-(1-$AZ$3) -> 76.0125 | BD32: =G32-(1-$AZ$3) -> 81.525 | BE32: =H32-(1-$AZ$3) -> 87.0875 | BF32: =I32-(1-$AZ$3) -> 92.675 | BG32: =J32-(1-$AZ$3) -> 98.225 | BH32: =K32-(1-$AZ$3) -> 103.6875 | ... CT32: =AW32-(1-$AZ$3) -> 320.3125
B34: Amari - Kuta - Perlato - Turilli - Zurich - Carerra | AY34: Amari - Kuta - Perlato - Turilli - Zurich - Carerra
B35: B | D35: 26 1/2 | E35: 23.625 | F35: 27 1/2 | G35: 31 1/2 | H35: 35 3/8 | I35: 39 3/8 | J35: 43 1/4 | K35: 47 1/4 | L35: 51 1/8 | M35: 55 1/8 | N35: 59 | O35: 63 | P35: 66 7/8 | Q35: 70 7/8 | R35: 74 3/4 | S35: 78 3/4 | T35: 82 5/8 | U35: 86 5/8 | V35: 90 1/2 | W35: 94 1/2 | X35: 98 3/8 | Y35: 102 3/8 | Z35: 106 1/4 | AA35: 110 1/4 | AB35: 114 1/8 | AC35: 118 1/8 | AD35: 122 | AE35: 126 | AF35: 129 7/8 | AG35: 133 7/8 | AH35: 137 3/4 | AI35: 141 3/4 | AJ35: 145 5/8 | AK35: 149 5/8 | AL35: 153 1/2 | AM35: 157 1/2 | AN35: 161 3/8 | AO35: 165 3/8 | AP35: 158 1/2 | AQ35: 169 3/8 | AR35: 173 3/8 | AS35: 159 1/2 | AT35: 177 3/8 | AU35: 181 3/8 | AV35: 160 1/2 | AW35: 174 3/8 | AY35: B | BA35: 26 1/2 | BB35: 23.625 | BC35: 27 1/2 | BD35: 31 1/2 | BE35: 35 3/8 | BF35: 39 3/8 | BG35: 43 1/4 | BH35: 47 1/4 | BI35: 51 1/8 | BJ35: 55 1/8 | BK35: 59 | BL35: 63 | BM35: 66 7/8 | BN35: 70 7/8 | BO35: 74 3/4 | BP35: 78 3/4 | BQ35: 82 5/8 | BR35: 86 5/8 | BS35: 90 1/2 | BT35: 94 1/2 | BU35: 98 3/8 | BV35: 102 3/8 | BW35: 106 1/4 | BX35: 110 1/4 | BY35: 114 1/8 | BZ35: 118 1/8 | CA35: 122 | CB35: 126 | CC35: 129 7/8 | CD35: 133 7/8 | CE35: 137 3/4 | CF35: 141 3/4 | CG35: 145 5/8 | CH35: 149 5/8 | CI35: 153 1/2 | CJ35: 157 1/2 | CK35: 161 3/8 | CL35: 165 3/8 | CM35: 158 1/2 | CN35: 169 3/8 | CO35: 173 3/8 | CP35: 159 1/2 | CQ35: 177 3/8 | CR35: 181 3/8 | CS35: 160 1/2 | CT35: 174 3/8
D36: 500 | E36: 600 | F36: 700 | G36: 800 | H36: 900 | I36: 1000 | J36: 1100 | K36: 1200 | L36: 1300 | M36: 1400 | N36: 1500 | O36: 1600 | P36: 1700 | Q36: 1800 | R36: 1900 | S36: 2000 | T36: 2100 | U36: 2200 | V36: 2300 | W36: 2400 | X36: 2500 | Y36: 2600 | Z36: 2700 | AA36: 2800 | AB36: 2900 | AC36: 3000 | AD36: 3100 | AE36: 3200 | AF36: 3300 | AG36: 3400 | AH36: 3500 | AI36: 3600 | AJ36: 3700 | AK36: 3800 | AL36: 3900 | AM36: 4000 | AN36: 4100 | AO36: 4200 | AP36: 4300 | AQ36: 4400 | AR36: 4500 | AS36: 4600 | AT36: 4700 | AU36: 4800 | AV36: 4900 | AW36: 5000 | BA36: 500 | BB36: 600 | BC36: 700 | BD36: 800 | BE36: 900 | BF36: 1000 | BG36: 1100 | BH36: 1200 | BI36: 1300 | BJ36: 1400 | BK36: 1500 | BL36: 1600 | BM36: 1700 | BN36: 1800 | BO36: 1900 | BP36: 2000 | BQ36: 2100 | BR36: 2200 | BS36: 2300 | BT36: 2400 | BU36: 2500 | BV36: 2600 | BW36: 2700 | BX36: 2800 | BY36: 2900 | BZ36: 3000 | CA36: 3100 | CB36: 3200 | CC36: 3300 | CD36: 3400 | CE36: 3500 | CF36: 3600 | CG36: 3700 | CH36: 3800 | CI36: 3900 | CJ36: 4000 | CK36: 4100 | CL36: 4200 | CM36: 4300 | CN36: 4400 | CO36: 4500 | CP36: 4600 | CQ36: 4700 | CR36: 4800 | CS36: 4900 | CT36: 5000
B37: 23 5/8 | C37: 600 | D37: 40.2 | E37: 42.6125 | F37: 45.025 | G37: 47.7125 | H37: 50.4 | I37: 53.3125 | J37: 56.175 | K37: 58.85 | L37: 61.5375 | M37: 64.2875 | N37: 67.225 | O37: 69.975 | P37: 72.675 | Q37: 75.3625 | R37: 78.05 | S37: 80.775 | T37: 83.7 | U37: 86.475 | V37: 89.175 | W37: 91.8625 | X37: 94.875 | Y37: 98.0875 | Z37: 101.2875 | AA37: 104.5 | AB37: 107.7125 | AC37: 109.375 | AD37: 111.625 | AE37: 114.625 | AF37: 117.625 | AG37: 120.5875 | AH37: 123.15 | AI37: 125.5375 | AJ37: 128.3625 | AK37: 131.625 | AL37: 134.875 | AM37: 138.1375 | AN37: 141.3875 | AO37: 141.875 | AP37: 144.20417 | AQ37: 146.07292 | AR37: 147.94167 | AS37: 149.81042 | AT37: 151.67917 | AU37: 153.54792 | AV37: 155.41667 | AW37: 157.28542 | AY37: 23 5/8 | AZ37: 600 | BA37: =D37*(1-$AZ$3) -> 32.16 | BB37: =E37*(1-$AZ$3) -> 34.09 | BC37: =F37*(1-$AZ$3) -> 36.02 | BD37: =G37*(1-$AZ$3) -> 38.17 | BE37: =H37*(1-$AZ$3) -> 40.32 | BF37: =I37*(1-$AZ$3) -> 42.65 | BG37: =J37*(1-$AZ$3) -> 44.94 | BH37: =K37*(1-$AZ$3) -> 47.08 | ... CT37: =AW37*(1-$AZ$3) -> 125.82833
B38: 27 1/2 | C38: 700 | D38: 41.5875 | E38: 44.125 | F38: 46.6625 | G38: 49.4875 | H38: 52.3125 | I38: 55.375 | J38: 58.3625 | K38: 61.1625 | L38: 63.9875 | M38: 66.875 | N38: 69.95 | O38: 72.8375 | P38: 75.6625 | Q38: 78.475 | R38: 81.3 | S38: 84.1875 | T38: 87.2625 | U38: 90.1625 | V38: 92.9875 | W38: 95.8 | X38: 98.975 | Y38: 102.3625 | Z38: 105.7375 | AA38: 109.125 | AB38: 112.5125 | AC38: 114.2 | AD38: 116.5375 | AE38: 119.7 | AF38: 122.8625 | AG38: 126 | AH38: 128.675 | AI38: 131.15 | AJ38: 134.1 | AK38: 137.5375 | AL38: 140.975 | AM38: 144.425 | AN38: 147.8625 | AO38: 148.375 | AP38: 150.8375 | AQ38: 152.8125 | AR38: 154.7875 | AS38: 156.7625 | AT38: 158.7375 | AU38: 160.7125 | AV38: 162.6875 | AW38: 164.6625 | AY38: 27 1/2 | AZ38: 700 | BA38: =D38*(1-$AZ$3) -> 33.27 | BB38: =E38*(1-$AZ$3) -> 35.3 | BC38: =F38*(1-$AZ$3) -> 37.33 | BD38: =G38*(1-$AZ$3) -> 39.59 | BE38: =H38*(1-$AZ$3) -> 41.85 | BF38: =I38*(1-$AZ$3) -> 44.3 | BG38: =J38*(1-$AZ$3) -> 46.69 | BH38: =K38*(1-$AZ$3) -> 48.93 | ... CT38: =AW38*(1-$AZ$3) -> 131.73
B39: 31 1/2 | C39: 800 | D39: 43.15 | E39: 45.8125 | F39: 48.475 | G39: 51.45 | H39: 54.4375 | I39: 57.65 | J39: 60.7875 | K39: 63.725 | L39: 66.7 | M39: 69.75 | N39: 72.975 | O39: 76.025 | P39: 78.9875 | Q39: 81.9375 | R39: 84.925 | S39: 87.9625 | T39: 91.2 | U39: 94.2625 | V39: 97.225 | W39: 100.2 | X39: 103.55 | Y39: 107.125 | Z39: 110.7 | AA39: 114.2875 | AB39: 117.8625 | AC39: 119.575 | AD39: 122.0125 | AE39: 125.35 | AF39: 128.7 | AG39: 132.0125 | AH39: 134.8 | AI39: 137.3875 | AJ39: 140.4875 | AK39: 144.125 | AL39: 147.7625 | AM39: 151.4125 | AN39: 155.05 | AO39: 155.5875 | AP39: 158.19167 | AQ39: 160.27917 | AR39: 162.36667 | AS39: 164.45417 | AT39: 166.54167 | AU39: 168.62917 | AV39: 170.71667 | AW39: 172.80417 | AY39: 31 1/2 | AZ39: 800 | BA39: =D39*(1-$AZ$3) -> 34.52 | BB39: =E39*(1-$AZ$3) -> 36.65 | BC39: =F39*(1-$AZ$3) -> 38.78 | BD39: =G39*(1-$AZ$3) -> 41.16 | BE39: =H39*(1-$AZ$3) -> 43.55 | BF39: =I39*(1-$AZ$3) -> 46.12 | BG39: =J39*(1-$AZ$3) -> 48.63 | BH39: =K39*(1-$AZ$3) -> 50.98 | ... CT39: =AW39*(1-$AZ$3) -> 138.24333
B40: 35 3/8 | C40: 900 | D40: 44.7 | E40: 47.5 | F40: 50.3 | G40: 53.4125 | H40: 56.5625 | I40: 59.9 | J40: 63.1875 | K40: 66.3 | L40: 69.4125 | M40: 72.6125 | N40: 76.0125 | O40: 79.2 | P40: 82.3125 | Q40: 85.4375 | R40: 88.5625 | S40: 91.7375 | T40: 95.1125 | U40: 98.3375 | V40: 101.475 | W40: 104.6125 | X40: 108.1375 | Y40: 111.9125 | Z40: 115.6875 | AA40: 119.4625 | AB40: 123.2375 | AC40: 124.9625 | AD40: 127.475 | AE40: 131.025 | AF40: 134.5625 | AG40: 138.025 | AH40: 140.9375 | AI40: 143.6375 | AJ40: 146.9 | AK40: 150.725 | AL40: 154.5625 | AM40: 158.4 | AN40: 162.225 | AO40: 162.8 | AP40: 165.54167 | AQ40: 167.74167 | AR40: 169.94167 | AS40: 172.14167 | AT40: 174.34167 | AU40: 176.54167 | AV40: 178.74167 | AW40: 180.94167 | AY40: 35 3/8 | AZ40: 900 | BA40: =D40*(1-$AZ$3) -> 35.76 | BB40: =E40*(1-$AZ$3) -> 38 | BC40: =F40*(1-$AZ$3) -> 40.24 | BD40: =G40*(1-$AZ$3) -> 42.73 | BE40: =H40*(1-$AZ$3) -> 45.25 | BF40: =I40*(1-$AZ$3) -> 47.92 | BG40: =J40*(1-$AZ$3) -> 50.55 | BH40: =K40*(1-$AZ$3) -> 53.04 | ... CT40: =AW40*(1-$AZ$3) -> 144.75333
B41: 39 3/8 | C41: 1000 | D41: 46.2375 | E41: 49.175 | F41: 52.1125 | G41: 55.3875 | H41: 58.675 | I41: 62.175 | J41: 65.625 | K41: 68.875 | L41: 72.1375 | M41: 75.4875 | N41: 79.05 | O41: 82.3875 | P41: 85.6625 | Q41: 88.9375 | R41: 92.2125 | S41: 95.5375 | T41: 99.0625 | U41: 102.4375 | V41: 105.7125 | W41: 108.9875 | X41: 112.7 | Y41: 116.6625 | Z41: 120.6375 | AA41: 124.6 | AB41: 128.5625 | AC41: 130.325 | AD41: 132.95 | AE41: 136.675 | AF41: 140.4 | AG41: 144.0375 | AH41: 147.0875 | AI41: 149.875 | AJ41: 153.3 | AK41: 157.325 | AL41: 161.3625 | AM41: 165.3875 | AN41: 169.425 | AO41: 170.025 | AP41: 172.91667 | AQ41: 175.23542 | AR41: 177.55417 | AS41: 179.87292 | AT41: 182.19167 | AU41: 184.51042 | AV41: 186.82917 | AW41: 189.14792 | AY41: 39 3/8 | AZ41: 1000 | BA41: =D41*(1-$AZ$3) -> 36.99 | BB41: =E41*(1-$AZ$3) -> 39.34 | BC41: =F41*(1-$AZ$3) -> 41.69 | BD41: =G41*(1-$AZ$3) -> 44.31 | BE41: =H41*(1-$AZ$3) -> 46.94 | BF41: =I41*(1-$AZ$3) -> 49.74 | BG41: =J41*(1-$AZ$3) -> 52.5 | BH41: =K41*(1-$AZ$3) -> 55.1 | ... CT41: =AW41*(1-$AZ$3) -> 151.31833
B42: 43 1/4 | C42: 1100 | D42: 47.7625 | E42: 50.85 | F42: 53.9375 | G42: 57.3625 | H42: 60.8 | I42: 64.45 | J42: 68.0375 | K42: 71.45 | L42: 74.875 | M42: 78.3625 | N42: 82.0625 | O42: 85.575 | P42: 89.0125 | Q42: 92.425 | R42: 95.8625 | S42: 99.3375 | T42: 103.0125 | U42: 106.525 | V42: 109.95 | W42: 113.375 | X42: 117.2625 | Y42: 121.425 | Z42: 125.575 | AA42: 129.7375 | AB42: 133.9 | AC42: 135.7 | AD42: 138.4125 | AE42: 142.3125 | AF42: 146.2125 | AG42: 150.0625 | AH42: 153.225 | AI42: 156.125 | AJ42: 159.6875 | AK42: 163.925 | AL42: 168.15 | AM42: 172.375 | AN42: 176.6125 | AO42: 177.2375 | AP42: 180.27083 | AQ42: 182.70208 | AR42: 185.13333 | AS42: 187.56458 | AT42: 189.99583 | AU42: 192.42708 | AV42: 194.85833 | AW42: 197.28958 | AY42: 43 1/4 | AZ42: 1100 | BA42: =D42*(1-$AZ$3) -> 38.21 | BB42: =E42*(1-$AZ$3) -> 40.68 | BC42: =F42*(1-$AZ$3) -> 43.15 | BD42: =G42*(1-$AZ$3) -> 45.89 | BE42: =H42*(1-$AZ$3) -> 48.64 | BF42: =I42*(1-$AZ$3) -> 51.56 | BG42: =J42*(1-$AZ$3) -> 54.43 | BH42: =K42*(1-$AZ$3) -> 57.16 | ... CT42: =AW42*(1-$AZ$3) -> 157.83167
B43: 47 1/4 | C43: 1200 | D43: 49.3 | E43: 52.525 | F43: 55.75 | G43: 59.3375 | H43: 62.9125 | I43: 66.7 | J43: 70.4375 | K43: 74.0375 | L43: 77.5875 | M43: 81.225 | N43: 85.0875 | O43: 88.75 | P43: 92.3375 | Q43: 95.8875 | R43: 99.475 | S43: 103.125 | T43: 106.925 | U43: 110.5875 | V43: 114.175 | W43: 117.7625 | X43: 121.825 | Y43: 126.1875 | Z43: 130.55 | AA43: 134.9125 | AB43: 139.275 | AC43: 141.075 | AD43: 143.875 | AE43: 147.95 | AF43: 152.0375 | AG43: 156.0875 | AH43: 159.375 | AI43: 162.375 | AJ43: 166.075 | AK43: 170.5125 | AL43: 174.9375 | AM43: 179.3625 | AN43: 183.7875 | AO43: 184.45 | AP43: 187.62083 | AQ43: 190.16458 | AR43: 192.70833 | AS43: 195.25208 | AT43: 197.79583 | AU43: 200.33958 | AV43: 202.88333 | AW43: 205.42708 | AY43: 47 1/4 | AZ43: 1200 | BA43: =D43*(1-$AZ$3) -> 39.44 | BB43: =E43*(1-$AZ$3) -> 42.02 | BC43: =F43*(1-$AZ$3) -> 44.6 | BD43: =G43*(1-$AZ$3) -> 47.47 | BE43: =H43*(1-$AZ$3) -> 50.33 | BF43: =I43*(1-$AZ$3) -> 53.36 | BG43: =J43*(1-$AZ$3) -> 56.35 | BH43: =K43*(1-$AZ$3) -> 59.23 | ... CT43: =AW43*(1-$AZ$3) -> 164.34167
B44: 51 1/8 | C44: 1300 | D44: 50.8375 | E44: 54.2 | F44: 57.5625 | G44: 61.3 | H44: 65.025 | I44: 68.95 | J44: 72.85 | K44: 76.6 | L44: 80.3125 | M44: 84.1 | N44: 88.1125 | O44: 91.9875 | P44: 95.775 | Q44: 99.3875 | R44: 103.1125 | S44: 106.9 | T44: 110.8625 | U44: 114.675 | V44: 118.4125 | W44: 122.15 | X44: 126.3875 | Y44: 130.95 | Z44: 135.5 | AA44: 140.0625 | AB44: 144.6125 | AC44: 146.4375 | AD44: 149.3375 | AE44: 153.6125 | AF44: 157.8875 | AG44: 162.1 | AH44: 165.525 | AI44: 168.6125 | AJ44: 172.475 | AK44: 177.1 | AL44: 181.725 | AM44: 186.3625 | AN44: 190.9875 | AO44: 191.675 | AP44: 194.9875 | AQ44: 197.64375 | AR44: 200.3 | AS44: 202.95625 | AT44: 205.6125 | AU44: 208.26875 | AV44: 210.925 | AW44: 213.58125 | AY44: 51 1/8 | AZ44: 1300 | BA44: =D44*(1-$AZ$3) -> 40.67 | BB44: =E44*(1-$AZ$3) -> 43.36 | BC44: =F44*(1-$AZ$3) -> 46.05 | BD44: =G44*(1-$AZ$3) -> 49.04 | BE44: =H44*(1-$AZ$3) -> 52.02 | BF44: =I44*(1-$AZ$3) -> 55.16 | BG44: =J44*(1-$AZ$3) -> 58.28 | BH44: =K44*(1-$AZ$3) -> 61.28 | ... CT44: =AW44*(1-$AZ$3) -> 170.865
B45: 55 1/8 | C45: 1400 | D45: 52.4 | E45: 55.8875 | F45: 59.375 | G45: 63.25 | H45: 67.125 | I45: 71.225 | J45: 75.275 | K45: 79.1625 | L45: 83.0375 | M45: 86.975 | N45: 91.15 | O45: 95.25 | P45: 99.2375 | Q45: 102.9 | R45: 106.7375 | S45: 110.675 | T45: 114.8125 | U45: 118.775 | V45: 122.6625 | W45: 126.5375 | X45: 130.9625 | Y45: 135.7125 | Z45: 140.45 | AA45: 145.2 | AB45: 149.95 | AC45: 151.8125 | AD45: 154.8125 | AE45: 159.275 | AF45: 163.7375 | AG45: 168.1125 | AH45: 171.6625 | AI45: 174.8625 | AJ45: 178.875 | AK45: 183.7 | AL45: 188.525 | AM45: 193.35 | AN45: 198.175 | AO45: 198.9 | AP45: 202.35833 | AQ45: 205.13333 | AR45: 207.90833 | AS45: 210.68333 | AT45: 213.45833 | AU45: 216.23333 | AV45: 219.00833 | AW45: 221.78333 | AY45: 55 1/8 | AZ45: 1400 | BA45: =D45*(1-$AZ$3) -> 41.92 | BB45: =E45*(1-$AZ$3) -> 44.71 | BC45: =F45*(1-$AZ$3) -> 47.5 | BD45: =G45*(1-$AZ$3) -> 50.6 | BE45: =H45*(1-$AZ$3) -> 53.7 | BF45: =I45*(1-$AZ$3) -> 56.98 | BG45: =J45*(1-$AZ$3) -> 60.22 | BH45: =K45*(1-$AZ$3) -> 63.33 | ... CT45: =AW45*(1-$AZ$3) -> 177.42667
B46: 59 | C46: 1500 | D46: 54 | E46: 57.5875 | F46: 61.175 | G46: 65.2 | H46: 69.2375 | I46: 73.4875 | J46: 77.6875 | K46: 81.7375 | L46: 85.75 | M46: 89.85 | N46: 94.175 | O46: 98.5 | P46: 102.6875 | Q46: 106.4125 | R46: 110.3625 | S46: 114.45 | T46: 118.75 | U46: 122.875 | V46: 126.9125 | W46: 130.9375 | X46: 135.525 | Y46: 140.475 | Z46: 145.4125 | AA46: 150.35 | AB46: 155.2875 | AC46: 157.175 | AD46: 160.2875 | AE46: 164.9375 | AF46: 169.6 | AG46: 174.125 | AH46: 177.8 | AI46: 181.1125 | AJ46: 185.275 | AK46: 190.3 | AL46: 195.325 | AM46: 200.35 | AN46: 205.375 | AO46: 206.125 | AP46: 209.725 | AQ46: 212.6125 | AR46: 215.5 | AS46: 218.3875 | AT46: 221.275 | AU46: 224.1625 | AV46: 227.05 | AW46: 229.9375 | AY46: 59 | AZ46: 1500 | BA46: =D46*(1-$AZ$3) -> 43.2 | BB46: =E46*(1-$AZ$3) -> 46.07 | BC46: =F46*(1-$AZ$3) -> 48.94 | BD46: =G46*(1-$AZ$3) -> 52.16 | BE46: =H46*(1-$AZ$3) -> 55.39 | BF46: =I46*(1-$AZ$3) -> 58.79 | BG46: =J46*(1-$AZ$3) -> 62.15 | BH46: =K46*(1-$AZ$3) -> 65.39 | ... CT46: =AW46*(1-$AZ$3) -> 183.95
B47: 63 | C47: 1600 | D47: 55.5125 | E47: 59.25 | F47: 62.9875 | G47: 67.1625 | H47: 71.35 | I47: 75.7625 | J47: 80.1125 | K47: 84.3125 | L47: 88.475 | M47: 92.725 | N47: 97.2 | O47: 101.6375 | P47: 105.95 | Q47: 109.875 | R47: 113.9875 | S47: 118.2375 | T47: 122.6875 | U47: 126.9625 | V47: 131.15 | W47: 135.325 | X47: 140.1 | Y47: 145.2375 | Z47: 150.375 | AA47: 155.5 | AB47: 160.6375 | AC47: 162.55 | AD47: 165.75 | AE47: 170.5875 | AF47: 175.425 | AG47: 180.1375 | AH47: 183.9375 | AI47: 187.35 | AJ47: 191.675 | AK47: 196.9 | AL47: 202.125 | AM47: 207.35 | AN47: 212.575 | AO47: 213.35 | AP47: 217.09167 | AQ47: 220.09167 | AR47: 223.09167 | AS47: 226.09167 | AT47: 229.09167 | AU47: 232.09167 | AV47: 235.09167 | AW47: 238.09167 | AY47: 63 | AZ47: 1600 | BA47: =D47*(1-$AZ$3) -> 44.41 | BB47: =E47*(1-$AZ$3) -> 47.4 | BC47: =F47*(1-$AZ$3) -> 50.39 | BD47: =G47*(1-$AZ$3) -> 53.73 | BE47: =H47*(1-$AZ$3) -> 57.08 | BF47: =I47*(1-$AZ$3) -> 60.61 | BG47: =J47*(1-$AZ$3) -> 64.09 | BH47: =K47*(1-$AZ$3) -> 67.45 | ... CT47: =AW47*(1-$AZ$3) -> 190.47333
B48: 66 7/8 | C48: 1700 | D48: 57 | E48: 60.9 | F48: 64.8 | G48: 69.1375 | H48: 73.475 | I48: 78.025 | J48: 82.5375 | K48: 86.875 | L48: 91.2 | M48: 95.6 | N48: 100.2125 | O48: 104.725 | P48: 109.1375 | Q48: 113.3125 | R48: 117.625 | S48: 122.025 | T48: 126.625 | U48: 131.05 | V48: 135.3875 | W48: 139.725 | X48: 144.675 | Y48: 150.0125 | Z48: 155.3375 | AA48: 160.6625 | AB48: 166 | AC48: 167.9375 | AD48: 171.225 | AE48: 176.225 | AF48: 181.2375 | AG48: 186.15 | AH48: 190.075 | AI48: 193.6 | AJ48: 198.0625 | AK48: 203.4875 | AL48: 208.9125 | AM48: 214.3375 | AN48: 219.7625 | AO48: 220.575 | AP48: 224.4625 | AQ48: 227.58125 | AR48: 230.7 | AS48: 233.81875 | AT48: 236.9375 | AU48: 240.05625 | AV48: 243.175 | AW48: 246.29375 | AY48: 66 7/8 | AZ48: 1700 | BA48: =D48*(1-$AZ$3) -> 45.6 | BB48: =E48*(1-$AZ$3) -> 48.72 | BC48: =F48*(1-$AZ$3) -> 51.84 | BD48: =G48*(1-$AZ$3) -> 55.31 | BE48: =H48*(1-$AZ$3) -> 58.78 | BF48: =I48*(1-$AZ$3) -> 62.42 | BG48: =J48*(1-$AZ$3) -> 66.03 | BH48: =K48*(1-$AZ$3) -> 69.5 | ... CT48: =AW48*(1-$AZ$3) -> 197.035
... B61: 118 1/8 | C61: 3000 | D61: 75.675 | E61: 81.2375 | F61: 86.8 | G61: 93.0125 | H61: 99.2875 | I61: 105.6125 | J61: 111.9 | K61: 118.0875 | L61: 124.2375 | M61: 130.4625 | N61: 136.95 | O61: 143.225 | P61: 149.3875 | Q61: 155.5125 | R61: 161.6875 | S61: 167.9375 | T61: 174.375 | U61: 180.65 | V61: 186.825 | W61: 193.0125 | X61: 200.125 | Y61: 207.8125 | Z61: 215.5 | AA61: 223.175 | AB61: 230.8625 | AC61: 233.125 | AD61: 237.5875 | AE61: 244.8125 | AF61: 252.0375 | AG61: 259.125 | AH61: 264.575 | AI61: 269.375 | AJ61: 275.6875 | AK61: 283.525 | AL61: 291.3625 | AM61: 299.1875 | AN61: 307.025 | AO61: 308.2 | AP61: 313.81667 | AQ61: 318.32292 | AR61: 322.82917 | AS61: 327.33542 | AT61: 331.84167 | AU61: 336.34792 | AV61: 340.85417 | AW61: 345.36042 | AY61: 118 1/8 | AZ61: 3000 | BA61: =D61*(1-$AZ$3) -> 60.54 | BB61: =E61*(1-$AZ$3) -> 64.99 | BC61: =F61*(1-$AZ$3) -> 69.44 | BD61: =G61*(1-$AZ$3) -> 74.41 | BE61: =H61*(1-$AZ$3) -> 79.43 | BF61: =I61*(1-$AZ$3) -> 84.49 | BG61: =J61*(1-$AZ$3) -> 89.52 | BH61: =K61*(1-$AZ$3) -> 94.47 | ... CT61: =AW61*(1-$AZ$3) -> 276.28833
B63: Serino - Alaya - Tosca | AY63: Serino - Alaya - Tosca
B64: C | D64: 26 1/2 | E64: 23.625 | F64: 27 1/2 | G64: 31 1/2 | H64: 35 3/8 | I64: 39 3/8 | J64: 43 1/4 | K64: 47 1/4 | L64: 51 1/8 | M64: 55 1/8 | N64: 59 | O64: 63 | P64: 66 7/8 | Q64: 70 7/8 | R64: 74 3/4 | S64: 78 3/4 | T64: 82 5/8 | U64: 86 5/8 | V64: 90 1/2 | W64: 94 1/2 | X64: 98 3/8 | Y64: 102 3/8 | Z64: 106 1/4 | AA64: 110 1/4 | AB64: 114 1/8 | AC64: 118 1/8 | AD64: 122 | AE64: 126 | AF64: 129 7/8 | AG64: 133 7/8 | AH64: 137 3/4 | AI64: 141 3/4 | AJ64: 145 5/8 | AK64: 149 5/8 | AL64: 153 1/2 | AM64: 157 1/2 | AN64: 161 3/8 | AO64: 165 3/8 | AP64: 161 1/2 | AQ64: 165 1/2 | AR64: 169 3/8 | AS64: 173 3/8 | AT64: 169 1/2 | AU64: 173 1/2 | AV64: 177 3/8 | AW64: 177 3/8 | AY64: C | BA64: 26 1/2 | BB64: 23.625 | BC64: 27 1/2 | BD64: 31 1/2 | BE64: 35 3/8 | BF64: 39 3/8 | BG64: 43 1/4 | BH64: 47 1/4 | BI64: 51 1/8 | BJ64: 55 1/8 | BK64: 59 | BL64: 63 | BM64: 66 7/8 | BN64: 70 7/8 | BO64: 74 3/4 | BP64: 78 3/4 | BQ64: 82 5/8 | BR64: 86 5/8 | BS64: 90 1/2 | BT64: 94 1/2 | BU64: 98 3/8 | BV64: 102 3/8 | BW64: 106 1/4 | BX64: 110 1/4 | BY64: 114 1/8 | BZ64: 118 1/8 | CA64: 122 | CB64: 126 | CC64: 129 7/8 | CD64: 133 7/8 | CE64: 137 3/4 | CF64: 141 3/4 | CG64: 145 5/8 | CH64: 149 5/8 | CI64: 153 1/2 | CJ64: 157 1/2 | CK64: 161 3/8 | CL64: 165 3/8 | CM64: 161 1/2 | CN64: 165 1/2 | CO64: 169 3/8 | CP64: 173 3/8 | CQ64: 169 1/2 | CR64: 173 1/2 | CS64: 177 3/8 | CT64: 177 3/8
D65: 500 | E65: 600 | F65: 700 | G65: 800 | H65: 900 | I65: 1000 | J65: 1100 | K65: 1200 | L65: 1300 | M65: 1400 | N65: 1500 | O65: 1600 | P65: 1700 | Q65: 1800 | R65: 1900 | S65: 2000 | T65: 2100 | U65: 2200 | V65: 2300 | W65: 2400 | X65: 2500 | Y65: 2600 | Z65: 2700 | AA65: 2800 | AB65: 2900 | AC65: 3000 | AD65: 3100 | AE65: 3200 | AF65: 3300 | AG65: 3400 | AH65: 3500 | AI65: 3600 | AJ65: 3700 | AK65: 3800 | AL65: 3900 | AM65: 4000 | AN65: 4100 | AO65: 4200 | AP65: 4300 | AQ65: 4400 | AR65: 4500 | AS65: 4600 | AT65: 4700 | AU65: 4800 | AV65: 4900 | AW65: 5000 | BA65: 500 | BB65: 600 | BC65: 700 | BD65: 800 | BE65: 900 | BF65: 1000 | BG65: 1100 | BH65: 1200 | BI65: 1300 | BJ65: 1400 | BK65: 1500 | BL65: 1600 | BM65: 1700 | BN65: 1800 | BO65: 1900 | BP65: 2000 | BQ65: 2100 | BR65: 2200 | BS65: 2300 | BT65: 2400 | BU65: 2500 | BV65: 2600 | BW65: 2700 | BX65: 2800 | BY65: 2900 | BZ65: 3000 | CA65: 3100 | CB65: 3200 | CC65: 3300 | CD65: 3400 | CE65: 3500 | CF65: 3600 | CG65: 3700 | CH65: 3800 | CI65: 3900 | CJ65: 4000 | CK65: 4100 | CL65: 4200 | CM65: 4300 | CN65: 4400 | CO65: 4500 | CP65: 4600 | CQ65: 4700 | CR65: 4800 | CS65: 4900 | CT65: 5000
